Workbook
Name _1F17_Attr_Indvƒ: #REF!
Name _1F17_Attr_Indvƒ: #REF!
Name _2F17_Attr_Indvƒ__00000000: #REF!
Name _2F17_Attr_Indvƒ__00000000: #REF!
Name a: #REF!
Name a: #REF!
Name aaaaaaa: #REF!
Name aaaaaaa: #REF!
Name Ass: #REF!
Name Ass: #REF!
Name CF17_Attr_ABnk_15D_Am_AMD: #REF!
Name CF17_Attr_ABnk_15D_Am_AMD: #REF!
Name CF17_Attr_ABnk_15D_Am_EUR: #REF!
Name CF17_Attr_ABnk_15D_Am_EUR: #REF!
Name CF17_Attr_ABnk_15D_Am_OthC: #REF!
Name CF17_Attr_ABnk_15D_Am_OthC: #REF!
Name CF17_Attr_ABnk_15D_Am_RUR: #REF!
Name CF17_Attr_ABnk_15D_Am_RUR: #REF!
Name CF17_Attr_ABnk_15D_Am_USD: #REF!
Name CF17_Attr_ABnk_15D_Am_USD: #REF!
Name CF17_Attr_ABnk_15D_I_AMD: #REF!
Name CF17_Attr_ABnk_15D_I_AMD: #REF!
Name CF17_Attr_ABnk_15D_I_EUR: #REF!
Name CF17_Attr_ABnk_15D_I_EUR: #REF!
Name CF17_Attr_ABnk_15D_I_OthC: #REF!
Name CF17_Attr_ABnk_15D_I_OthC: #REF!
Name CF17_Attr_ABnk_15D_I_RUR: #REF!
Name CF17_Attr_ABnk_15D_I_RUR: #REF!
Name CF17_Attr_ABnk_15D_I_USD: #REF!
Name CF17_Attr_ABnk_15D_I_USD: #REF!
Name CF17_Attr_ABnk_180D_Am_AMD: #REF!
Name CF17_Attr_ABnk_180D_Am_AMD: #REF!
Name CF17_Attr_ABnk_180D_Am_EUR: #REF!
Name CF17_Attr_ABnk_180D_Am_EUR: #REF!
Name CF17_Attr_ABnk_180D_Am_OthC: #REF!
Name CF17_Attr_ABnk_180D_Am_OthC: #REF!
Name CF17_Attr_ABnk_180D_Am_RUR: #REF!
Name CF17_Attr_ABnk_180D_Am_RUR: #REF!
Name CF17_Attr_ABnk_180D_Am_USD: #REF!
Name CF17_Attr_ABnk_180D_Am_USD: #REF!
Name CF17_Attr_ABnk_180D_I_AMD: #REF!
Name CF17_Attr_ABnk_180D_I_AMD: #REF!
Name CF17_Attr_ABnk_180D_I_EUR: #REF!
Name CF17_Attr_ABnk_180D_I_EUR: #REF!
Name CF17_Attr_ABnk_180D_I_OthC: #REF!
Name CF17_Attr_ABnk_180D_I_OthC: #REF!
Name CF17_Attr_ABnk_180D_I_RUR: #REF!
Name CF17_Attr_ABnk_180D_I_RUR: #REF!
Name CF17_Attr_ABnk_180D_I_USD: #REF!
Name CF17_Attr_ABnk_180D_I_USD: #REF!
Name CF17_Attr_ABnk_30D_Am_AMD: #REF!
Name CF17_Attr_ABnk_30D_Am_AMD: #REF!
Name CF17_Attr_ABnk_30D_Am_EUR: #REF!
Name CF17_Attr_ABnk_30D_Am_EUR: #REF!
Name CF17_Attr_ABnk_30D_Am_OthC: #REF!
Name CF17_Attr_ABnk_30D_Am_OthC: #REF!
Name CF17_Attr_ABnk_30D_Am_RUR: #REF!
Name CF17_Attr_ABnk_30D_Am_RUR: #REF!
Name CF17_Attr_ABnk_30D_Am_USD: #REF!
Name CF17_Attr_ABnk_30D_Am_USD: #REF!

Sheet Local model data
A1: Date | B1: Real GDP Q flows | C1: Financial Cycle Index | D1: Level | E1: Steepness | F1: Curvature | G1: Policy rate | H1: RoE | I1: Liquidity ratio (HLA/Assets) | J1: CAR | K1: Mortgage stock | L1: Mortgage Q flows | M1: Mortgage interest rate | N1: Construction loans | O1: Real estate prices | P1: Exchange rate | Q1: Trade balance | R1: Copper prices
A2: 37711 | B2: =GDP!D18 -> 279363.28 | C2: 0.033258725 | D2: =AVERAGE('tb %'!P18:R18) -> 0.15999453 | E2: ='tb %'!R18-'tb %'!P18 -> 0.045436377 | F2: ='tb %'!P18+'tb %'!R18-2*'tb %'!Q18 -> -0.0044069219 | I2: 0.44478408 | J2: 0.15691012 | N2: ='Construction loans'!P3 -> 3442836.7 | O2: 93932.64 | P2: 586.58333 | Q2: -481.7738 | R2: ='Copper prices'!G191 -> 0.763
A3: 37802 | B3: =GDP!D19 -> 375920.39 | C3: 0.031645416 | D3: =AVERAGE('tb %'!P19:R19) -> 0.16183983 | E3: ='tb %'!R19-'tb %'!P19 -> 0.051851953 | F3: ='tb %'!P19+'tb %'!R19-2*'tb %'!Q19 -> -0.010822498 | I3: 0.47770158 | J3: 0.20620947 | N3: ='Construction loans'!P4 -> 3781467.7 | O3: 100010.68 | P3: 586.42333 | Q3: -534.9315 | R3: ='Copper prices'!G192 -> 0.7496254
A4: 37894 | B4: =GDP!D20 -> 554155.58 | C4: 0.029565294 | D4: =AVERAGE('tb %'!P20:R20) -> 0.14765833 | E4: ='tb %'!R20-'tb %'!P20 -> 0.073915325 | F4: ='tb %'!P20+'tb %'!R20-2*'tb %'!Q20 -> -0.032885869 | I4: 0.47634938 | J4: 0.21124957 | N4: ='Construction loans'!P5 -> 4388627.7 | O4: 107539.47 | P4: 577.48667 | Q4: -534.99369 | R4: ='Copper prices'!G193 -> 0.80331719
A5: 37986 | B5: =GDP!D21 -> 573667.67 | C5: 0.027746709 | D5: =AVERAGE('tb %'!P21:R21) -> 0.087761168 | E5: ='tb %'!R21-'tb %'!P21 -> -0.0078095501 | F5: ='tb %'!P21+'tb %'!R21-2*'tb %'!Q21 -> 0.048839005 | G5: ='policy tool rates'!N8 -> 0.09 | H5: =RoE!F5 -> 0.17759128 | I5: 0.47553712 | J5: 0.29392251 | N5: ='Construction loans'!P6 -> 4986759.3 | O5: 111243.17 | P5: 564.55667 | Q5: -547.92715 | R5: ='Copper prices'!G194 -> 0.93481935
A6: 38077 | B6: =GDP!D22 -> 301698 | C6: 0.027983893 | D6: =AVERAGE('tb %'!P22:R22) -> 0.093703594 | E6: ='tb %'!R22-'tb %'!P22 -> 0.051533672 | F6: ='tb %'!P22+'tb %'!R22-2*'tb %'!Q22 -> -0.010504217 | G6: ='policy tool rates'!N9 -> 0.09 | H6: =RoE!F6 -> 0.25097346 | I6: 0.46411757 | J6: 0.31353983 | N6: ='Construction loans'!P7 -> 5024665 | O6: 118544.63 | P6: 565.22667 | Q6: -585.92759 | R6: ='Copper prices'!G195 -> 1.2404279
A7: 38168 | B7: =GDP!D23 -> 414986.11 | C7: 0.031176494 | D7: =AVERAGE('tb %'!P23:R23) -> 0.086521576 | E7: ='tb %'!R23-'tb %'!P23 -> 0.055620728 | F7: ='tb %'!P23+'tb %'!R23-2*'tb %'!Q23 -> -0.014591272 | G7: ='policy tool rates'!N10 -> 0.06 | H7: =RoE!F7 -> 0.25399792 | I7: 0.4450622 | J7: 0.30447544 | N7: ='Construction loans'!P8 -> 5275383.1 | O7: 124009.2 | P7: 551.14 | Q7: -598.87975 | R7: ='Copper prices'!G196 -> 1.23235
A8: 38260 | B8: =GDP!D24 -> 625249.13 | C8: 0.036945181 | D8: =AVERAGE('tb %'!P24:R24) -> 0.071845569 | E8: ='tb %'!R24-'tb %'!P24 -> 0.042520611 | F8: ='tb %'!P24+'tb %'!R24-2*'tb %'!Q24 -> -0.0039592501 | G8: ='policy tool rates'!N11 -> 0.055 | H8: =RoE!F8 -> 0.21843329 | I8: 0.4755256 | J8: 0.30183717 | N8: ='Construction loans'!P9 -> 5653119.8 | O8: 123600 | P8: 518.98667 | Q8: -655.44499 | R8: ='Copper prices'!G197 -> 1.2847844
A9: 38352 | B9: =GDP!D25 -> 627826.47 | C9: 0.041911984 | D9: =AVERAGE('tb %'!P25:R25) -> 0.066344069 | E9: ='tb %'!R25-'tb %'!P25 -> 0.052695792 | F9: ='tb %'!P25+'tb %'!R25-2*'tb %'!Q25 -> -5.3791667e-05 | G9: ='policy tool rates'!N12 -> 0.04 | H9: =RoE!F9 -> 0.32586859 | I9: 0.47075936 | J9: 0.32355024 | N9: ='Construction loans'!P10 -> 5419070.3 | O9: 126200 | P9: 498.45333 | Q9: -645.18631 | R9: ='Copper prices'!G198 -> 1.3831823
A10: 38442 | B10: =GDP!D26 -> 327135.6 | C10: 0.043873531 | D10: =AVERAGE('tb %'!P26:R26) -> 0.054354407 | E10: ='tb %'!R26-'tb %'!P26 -> 0.028075444 | F10: ='tb %'!P26+'tb %'!R26-2*'tb %'!Q26 -> 0.0054472222 | G10: ='policy tool rates'!N13 -> 0.0375 | H10: =RoE!F10 -> 0.30676664 | I10: 0.46280625 | J10: 0.36380199 | N10: ='Construction loans'!P11 -> 5559564.6 | O10: 135500 | P10: 477.02667 | Q10: -669.06436 | R10: ='Copper prices'!G199 -> 1.4456279
A11: 38533 | B11: =GDP!D27 -> 474747.6 | C11: 0.047258442 | D11: =AVERAGE('tb %'!P27:R27) -> 0.057678143 | E11: ='tb %'!R27-'tb %'!P27 -> 0.027834403 | F11: ='tb %'!P27+'tb %'!R27-2*'tb %'!Q27 -> 0.01263693 | G11: ='policy tool rates'!N14 -> 0.045 | H11: =RoE!F11 -> 0.27623124 | I11: 0.45120407 | J11: 0.31670004 | K11: 6454380 | L11: 1078386.2 | N11: ='Construction loans'!P12 -> 6289087.3 | O11: 151000 | P11: 448.69667 | Q11: -699.09406 | R11: ='Copper prices'!G200 -> 1.484775
A12: 38625 | B12: =GDP!D28 -> 705065.9 | C12: 0.052827964 | D12: =AVERAGE('tb %'!P28:R28) -> 0.047665148 | E12: ='tb %'!R28-'tb %'!P28 -> 0.016494556 | F12: ='tb %'!P28+'tb %'!R28-2*'tb %'!Q28 -> -0.012731556 | G12: ='policy tool rates'!N15 -> 0.0375 | H12: =RoE!F12 -> 0.25989059 | I12: 0.45571907 | J12: 0.33593299 | K12: 8537812 | L12: 1426482.3 | N12: ='Construction loans'!P13 -> 7141805.4 | O12: 163600 | P12: 452.68 | Q12: -695.86463 | R12: ='Copper prices'!G201 -> 1.6361891
A13: 38717 | B13: =GDP!D29 -> 735931.8 | C13: 0.061105607 | D13: =AVERAGE('tb %'!P29:R29) -> 0.05922625 | E13: ='tb %'!R29-'tb %'!P29 -> 0.05064175 | F13: ='tb %'!P29+'tb %'!R29-2*'tb %'!Q29 -> 0.02207325 | G13: ='policy tool rates'!N16 -> 0.03 | H13: =RoE!F13 -> 0.15247996 | I13: 0.44177802 | J13: 0.33670813 | K13: 11105554 | L13: 1855496 | N13: ='Construction loans'!P14 -> 7744711.1 | O13: 173700 | P13: 452.34667 | Q13: -782.59364 | R13: ='Copper prices'!G202 -> 1.9362597
A14: 38807 | B14: =GDP!D30 -> 370000.4 | C14: 0.068417244 | D14: =AVERAGE('tb %'!P30:R30) -> 0.058996931 | E14: ='tb %'!R30-'tb %'!P30 -> 0.043767293 | F14: ='tb %'!P30+'tb %'!R30-2*'tb %'!Q30 -> 0.029669793 | G14: ='policy tool rates'!N17 -> 0.0375 | H14: =RoE!F14 -> 0.15518108 | I14: 0.44724372 | J14: 0.33826987 | K14: 13261886 | L14: 2215772.1 | N14: ='Construction loans'!P15 -> 7750122.7 | O14: 184700 | P14: 450.94667 | Q14: -823.10027 | R14: ='Copper prices'!G203 -> 2.2317274
A15: 38898 | B15: =GDP!D31 -> 565444.8 | C15: 0.073056264 | D15: =AVERAGE('tb %'!P31:R31) -> 0.070539311 | E15: ='tb %'!R31-'tb %'!P31 -> 0.050502401 | F15: ='tb %'!P31+'tb %'!R31-2*'tb %'!Q31 -> 0.017936932 | G15: ='policy tool rates'!N18 -> 0.04 | H15: =RoE!F15 -> 0.16243635 | I15: 0.40832204 | J15: 0.33680469 | K15: 17026009 | L15: 2844675.1 | N15: ='Construction loans'!P16 -> 8884002.7 | O15: 189100 | P15: 436.78333 | Q15: -869.22431 | R15: ='Copper prices'!G204 -> 3.2993355
A16: 38990 | B16: =GDP!D32 -> 790806.1 | C16: 0.078102746 | D16: =AVERAGE('tb %'!P32:R32) -> 0.069952677 | E16: ='tb %'!R32-'tb %'!P32 -> 0.046423826 | F16: ='tb %'!P32+'tb %'!R32-2*'tb %'!Q32 -> 0.015549434 | G16: ='policy tool rates'!N19 -> 0.04125 | H16: =RoE!F16 -> 0.16067328 | I16: 0.42274397 | J16: 0.35308267 | K16: 19907567 | L16: 3326120.6 | N16: ='Construction loans'!P17 -> 9057415.1 | O16: 207000 | P16: 402.38667 | Q16: -961.70852 | R16: ='Copper prices'!G205 -> 3.5010435
A17: 39082 | B17: =GDP!D33 -> 812645.1 | C17: 0.085940502 | D17: =AVERAGE('tb %'!P33:R33) -> 0.071795703 | E17: ='tb %'!R33-'tb %'!P33 -> 0.038857891 | F17: ='tb %'!P33+'tb %'!R33-2*'tb %'!Q33 -> 0.014804109 | G17: ='policy tool rates'!N20 -> 0.045 | H17: =RoE!F17 -> 0.15848487 | I17: 0.41241139 | J17: 0.34870915 | K17: 23770050 | L17: 3971457.3 | N17: ='Construction loans'!P18 -> 10629354 | O17: 221900 | P17: 374.04 | Q17: -1035.2546 | R17: ='Copper prices'!G206 -> 3.2066032
A18: 39172 | B18: =GDP!D34 -> 414861.4 | C18: 0.10309264 | D18: =AVERAGE('tb %'!P34:R34) -> 0.069200111 | E18: ='tb %'!R34-'tb %'!P34 -> 0.020956 | F18: ='tb %'!P34+'tb %'!R34-2*'tb %'!Q34 -> 0.0013073333 | G18: ='policy tool rates'!N21 -> 0.04625 | H18: =RoE!F18 -> 0.1549072 | I18: 0.41026271 | J18: 0.35252402 | K18: 27713815 | L18: 4630374.6 | N18: ='Construction loans'!P19 -> 12296063 | O18: 236300 | P18: 359.44 | Q18: -1198.4505 | R18: ='Copper prices'!G207 -> 2.7150098
A19: 39263 | B19: =GDP!D35 -> 622876.5 | C19: 0.12882532 | D19: =AVERAGE('tb %'!P35:R35) -> 0.064360778 | E19: ='tb %'!R35-'tb %'!P35 -> 0.007508 | F19: ='tb %'!P35+'tb %'!R35-2*'tb %'!Q35 -> -0.0044926667 | G19: ='policy tool rates'!N22 -> 0.0475 | H19: =RoE!F19 -> 0.15357269 | I19: 0.36749868 | J19: 0.32701138 | K19: 35158958 | L19: 5874295.7 | N19: ='Construction loans'!P20 -> 14477815 | O19: 258800 | P19: 353.96667 | Q19: -1347.4561 | R19: ='Copper prices'!G208 -> 3.4612778
A20: 39355 | B20: =GDP!D36 -> 915268.8 | C20: 0.16384462 | D20: =AVERAGE('tb %'!P36:R36) -> 0.063946056 | E20: ='tb %'!R36-'tb %'!P36 -> 0.0077536667 | F20: ='tb %'!P36+'tb %'!R36-2*'tb %'!Q36 -> -0.0038093333 | G20: ='policy tool rates'!N23 -> 0.045 | H20: =RoE!F20 -> 0.15467611 | I20: 0.34709983 | J20: 0.31364639 | K20: 45981845 | L20: 7682564.2 | N20: ='Construction loans'!P21 -> 15949385 | O20: 270300 | P20: 337.83 | Q20: -1541.1551 | R20: ='Copper prices'!G209 -> 3.4640683
A21: 39447 | B21: =GDP!D37 -> 934967.7 | C21: 0.20036084 | D21: =AVERAGE('tb %'!P37:R37) -> 0.077068944 | E21: ='tb %'!R37-'tb %'!P37 -> 0.029163 | F21: ='tb %'!P37+'tb %'!R37-2*'tb %'!Q37 -> 0.016839333 | G21: ='policy tool rates'!N24 -> 0.05 | H21: =RoE!F21 -> 0.14769788 | I21: 0.33659507 | J21: 0.30052349 | K21: 53582565 | L21: 8952478.9 | N21: ='Construction loans'!P22 -> 20214525 | O21: 282600 | P21: 317.07667 | Q21: -1906.8454 | R21: ='Copper prices'!G210 -> 3.2696312
A22: 39538 | B22: =GDP!D38 -> 469131 | C22: 0.24733797 | D22: =AVERAGE('tb %'!P38:R38) -> 0.085225345 | E22: ='tb %'!R38-'tb %'!P38 -> 0.035318191 | F22: ='tb %'!P38+'tb %'!R38-2*'tb %'!Q38 -> 0.0081117066 | G22: ='policy tool rates'!N25 -> 0.05875 | H22: =RoE!F22 -> 0.14185166 | I22: 0.30459945 | J22: 0.27152321 | K22: 59327163 | L22: 9912276.1 | N22: ='Construction loans'!P23 -> 23640640 | O22: 286700 | P22: 308.05333 | Q22: -2099.3634 | R22: ='Copper prices'!G211 -> 3.5233217
A23: 39629 | B23: =GDP!D39 -> 683115.2 | C23: 0.29499948 | D23: =AVERAGE('tb %'!P39:R39) -> 0.083571415 | E23: ='tb %'!R39-'tb %'!P39 -> 0.032653281 | F23: ='tb %'!P39+'tb %'!R39-2*'tb %'!Q39 -> 0.020317355 | G23: ='policy tool rates'!N26 -> 0.065 | H23: =RoE!F23 -> 0.13166144 | I23: 0.27106157 | J23: 0.2627484 | K23: 71722895 | L23: 11983333 | M23: ='Mortgage rate'!J5 -> 0.19534078 | N23: ='Construction loans'!P24 -> 29692298 | O23: 303300 | P23: 307.11 | Q23: -2416.3129 | R23: ='Copper prices'!G212 -> 3.7874435
A24: 39721 | B24: =GDP!D40 -> 1056298.5 | C24: 0.31648703 | D24: =AVERAGE('tb %'!P40:R40) -> 0.088830781 | E24: ='tb %'!R40-'tb %'!P40 -> 0.026018264 | F24: ='tb %'!P40+'tb %'!R40-2*'tb %'!Q40 -> 0.023428609 | G24: ='policy tool rates'!N27 -> 0.0725 | H24: =RoE!F24 -> 0.12499891 | I24: 0.25487924 | J24: 0.27246067 | K24: 81031249 | L24: 13538556 | M24: ='Mortgage rate'!J6 -> 0.14502906 | N24: ='Construction loans'!P25 -> 36330940 | O24: 301000 | P24: 302.30333 | Q24: -2824.1362 | R24: ='Copper prices'!G213 -> 3.4150889
A25: 39813 | B25: =GDP!D41 -> 880076.1 | C25: 0.28248119 | D25: =AVERAGE('tb %'!P41:R41) -> 0.099770586 | E25: ='tb %'!R41-'tb %'!P41 -> 0.029384579 | F25: ='tb %'!P41+'tb %'!R41-2*'tb %'!Q41 -> 0.016859789 | G25: ='policy tool rates'!N28 -> 0.0775 | H25: =RoE!F25 -> 0.13391005 | I25: 0.23830184 | J25: 0.27487577 | K25: 83620888 | L25: 6914117.7 | M25: ='Mortgage rate'!J7 -> 0.14221443 | N25: ='Construction loans'!P26 -> 40211511 | O25: 292000 | P25: 306.41 | Q25: -3127.4859 | R25: ='Copper prices'!G214 -> 1.7621794
A26: 39903 | B26: =GDP!D42 -> 439029.2 | C26: 0.20012739 | D26: =AVERAGE('tb %'!P42:R42) -> 0.11109524 | E26: ='tb %'!R42-'tb %'!P42 -> 0.029181794 | F26: ='tb %'!P42+'tb %'!R42-2*'tb %'!Q42 -> 0.018689206 | G26: ='policy tool rates'!N29 -> 0.07 | H26: =RoE!F26 -> 0.095964303 | I26: 0.29054774 | J26: 0.26145861 | K26: 86367095 | L26: 3074293.7 | M26: ='Mortgage rate'!J8 -> 0.16803473 | N26: ='Construction loans'!P27 -> 39875378 | O26: 289800 | P26: 325.56 | Q26: -3046.1682 | R26: ='Copper prices'!G215 -> 1.583265
A27: 39994 | B27: =GDP!D43 -> 555120.5 | C27: 0.11179937 | D27: =AVERAGE('tb %'!P43:R43) -> 0.13300999 | E27: ='tb %'!R43-'tb %'!P43 -> 0.045577599 | F27: ='tb %'!P43+'tb %'!R43-2*'tb %'!Q43 -> -0.0038627305 | G27: ='policy tool rates'!N30 -> 0.071875 | H27: =RoE!F27 -> 0.066188057 | I27: 0.31981529 | J27: 0.27961931 | K27: 83108252 | L27: 2768462.5 | M27: ='Mortgage rate'!J9 -> 0.16278515 | N27: ='Construction loans'!P28 -> 43410654 | O27: 259300 | P27: 370.53 | Q27: -2834.8227 | R27: ='Copper prices'!G216 -> 2.1462063
A28: 40086 | B28: =GDP!D44 -> 847261.5 | C28: 0.074922158 | D28: =AVERAGE('tb %'!P44:R44) -> 0.10539538 | E28: ='tb %'!R44-'tb %'!P44 -> 0.057307556 | F28: ='tb %'!P44+'tb %'!R44-2*'tb %'!Q44 -> -0.0042369462 | G28: ='policy tool rates'!N31 -> 0.055833333 | H28: =RoE!F28 -> 0.034273531 | I28: 0.35226608 | J28: 0.28278232 | K28: 83370314 | L28: 4998103.1 | M28: ='Mortgage rate'!J10 -> 0.15403407 | N28: ='Construction loans'!P29 -> 47915409 | O28: 255000 | P28: 372.64333 | Q28: -2541.9245 | R28: ='Copper prices'!G217 -> 2.6759406
A29: 40178 | B29: =GDP!D45 -> 810170.1 | C29: 0.069551834 | D29: =AVERAGE('tb %'!P45:R45) -> 0.11921809 | E29: ='tb %'!R45-'tb %'!P45 -> 0.063267681 | F29: ='tb %'!P45+'tb %'!R45-2*'tb %'!Q45 -> -0.02760637 | G29: ='policy tool rates'!N32 -> 0.05 | H29: =RoE!F29 -> 0.033640082 | I29: 0.3444143 | J29: 0.28431055 | K29: 83959876 | L29: 7369728.3 | M29: ='Mortgage rate'!J11 -> 0.14499949 | N29: ='Construction loans'!P30 -> 51940096 | O29: 268500 | P29: 384.4 | Q29: -2366.2823 | R29: ='Copper prices'!G218 -> 3.0407905
A30: 40268 | B30: =GDP!D46 -> 470555.8 | C30: 0.079725921 | D30: =AVERAGE('tb %'!P46:R46) -> 0.12721754 | E30: ='tb %'!R46-'tb %'!P46 -> 0.071142968 | F30: ='tb %'!P46+'tb %'!R46-2*'tb %'!Q46 -> -0.021781775 | G30: ='policy tool rates'!N33 -> 0.0575 | H30: =RoE!F30 -> 0.050094178 | I30: 0.33919914 | J30: 0.28550298 | K30: 85140166 | L30: 4967865.9 | M30: ='Mortgage rate'!J12 -> 0.14000675 | N30: ='Construction loans'!P31 -> 54654652 | O30: 274100 | P30: 384.07667 | Q30: -2417.4731 | R30: ='Copper prices'!G219 -> 3.2999034
A31: 40359 | B31: =GDP!D47 -> 606073.7 | C31: 0.10107671 | D31: =AVERAGE('tb %'!P47:R47) -> 0.13658662 | E31: ='tb %'!R47-'tb %'!P47 -> 0.037577257 | F31: ='tb %'!P47+'tb %'!R47-2*'tb %'!Q47 -> -0.02504352 | G31: ='policy tool rates'!N34 -> 0.069166667 | H31: =RoE!F31 -> 0.076372994 | I31: 0.30089697 | J31: 0.28855471 | K31: 83483241 | L31: 7158954.5 | M31: ='Mortgage rate'!J13 -> 0.13882834 | N31: ='Construction loans'!P32 -> 59235869 | O31: 283000 | P31: 384.3297 | Q31: -2461.7697 | R31: ='Copper prices'!G220 -> 3.1917206
A32: 40451 | B32: =GDP!D48 -> 798927.7 | C32: 0.13306634 | D32: =AVERAGE('tb %'!P48:R48) -> 0.13084849 | E32: ='tb %'!R48-'tb %'!P48 -> 0.061320036 | F32: ='tb %'!P48+'tb %'!R48-2*'tb %'!Q48 -> -0.012018526 | G32: ='policy tool rates'!N35 -> 0.0725 | H32: =RoE!F32 -> 0.10173047 | I32: 0.30145125 | J32: 0.26714555 | K32: 85202144 | L32: 6544487.5 | M32: ='Mortgage rate'!J14 -> 0.13754829 | N32: ='Construction loans'!P33 -> 62626793 | O32: 270200 | P32: 365.51071 | Q32: -2454.0357 | R32: ='Copper prices'!G221 -> 3.2979419
A33: 40543 | B33: =GDP!D49 -> 834358.9 | C33: 0.16742348 | D33: =AVERAGE('tb %'!P49:R49) -> 0.13109406 | E33: ='tb %'!R49-'tb %'!P49 -> 0.063589667 | F33: ='tb %'!P49+'tb %'!R49-2*'tb %'!Q49 -> -0.037999829 | G33: ='policy tool rates'!N36 -> 0.0725 | H33: =RoE!F33 -> 0.10225911 | I33: 0.29472548 | J33: 0.22239053 | K33: 88114470 | L33: 15714436 | M33: ='Mortgage rate'!J15 -> 0.12821951 | N33: ='Construction loans'!P34 -> 71189811 | O33: 260700 | P33: 360.72633 | Q33: -2326.4898 | R33: ='Copper prices'!G222 -> 3.9360328
A34: 40633 | B34: =GDP!D50 -> 479643.2 | C34: 0.19897625 | D34: =AVERAGE('tb %'!P50:R50) -> 0.12376232 | E34: ='tb %'!R50-'tb %'!P50 -> 0.072743548 | F34: ='tb %'!P50+'tb %'!R50-2*'tb %'!Q50 -> -0.039170048 | G34: ='policy tool rates'!N37 -> 0.074166667 | H34: =RoE!F34 -> 0.11098567 | I34: 0.2888072 | J34: 0.21303481 | K34: 90637384 | L34: 7444247.2 | M34: ='Mortgage rate'!J16 -> 0.12678789 | N34: ='Construction loans'!P35 -> 76454417 | O34: 257700 | P34: 366.14318 | Q34: -2279.7152 | R34: ='Copper prices'!G223 -> 4.3905607
... A86: 45382 | B86: =GDP!D102 -> 1007112.7 | C86: 0.13502651 | D86: =AVERAGE('tb %'!P102:R102) -> 0.10325053 | E86: ='tb %'!R102-'tb %'!P102 -> 0.0098299156 | F86: ='tb %'!P102+'tb %'!R102-2*'tb %'!Q102 -> 0.0081510844 | G86: ='policy tool rates'!N89 -> 0.09 | H86: =RoE!F86 -> 0.13868405 | I86: 0.34227062 | J86: 0.19206155 | K86: 1078741000 | L86: 64048874 | M86: ='Mortgage rate'!J68 -> 0.12569002 | N86: ='Construction loans'!P87 -> 5.2872528e+08 | O86: 455672.73 | P86: 404.27 | Q86: -413.34215 | R86: ='Copper prices'!G275 -> 3.86752

Sheet GDP
A1: Date | B1: Real_GDP | C1: From Karapetyan Hayk | D1: Real GDP Q flows FINAL | E1: Yearly flows
A2: 1999Q1 | B2: 199447.85 | D2: =B2 -> 199447.85
A3: 1999Q2 | B3: 264207.59 | D3: =B3 -> 264207.59
A4: 1999Q3 | B4: 349324.03 | D4: =B4 -> 349324.03
A5: 1999Q4 | B5: 399625 | D5: =B5 -> 399625 | E5: =SUM(D2:D5) -> 1212604.5
A6: 2000Q1 | B6: 208525.11 | D6: =B6 -> 208525.11 | E6: =SUM(D3:D6) -> 1221681.7
A7: 2000Q2 | B7: 279056.48 | D7: =B7 -> 279056.48 | E7: =SUM(D4:D7) -> 1236530.6
A8: 2000Q3 | B8: 372232.77 | D8: =B8 -> 372232.77 | E8: =SUM(D5:D8) -> 1259439.4
A9: 2000Q4 | B9: 401097.01 | D9: =B9 -> 401097.01 | E9: =SUM(D6:D9) -> 1260911.4
A10: 2001Q1 | B10: 232482.62 | D10: =B10 -> 232482.62 | E10: =SUM(D7:D10) -> 1284868.9
A11: 2001Q2 | B11: 294822.87 | D11: =B11 -> 294822.87 | E11: =SUM(D8:D11) -> 1300635.3
A12: 2001Q3 | B12: 428508.83 | D12: =B12 -> 428508.83 | E12: =SUM(D9:D12) -> 1356911.3
A13: 2001Q4 | B13: 425597.83 | D13: =B13 -> 425597.83 | E13: =SUM(D10:D13) -> 1381412.2
A14: 2002Q1 | B14: 251947.39 | D14: =B14 -> 251947.39 | E14: =SUM(D11:D14) -> 1400876.9
A15: 2002Q2 | B15: 323479.07 | D15: =B15 -> 323479.07 | E15: =SUM(D12:D15) -> 1429533.1
A16: 2002Q3 | B16: 484926.23 | D16: =B16 -> 484926.23 | E16: =SUM(D13:D16) -> 1485950.5
... A25: 2004Q4 | B25: 627826.47 | D25: =B25 -> 627826.47 | E25: =SUM(D22:D25) -> 1969759.7
A26: 2005Q1 | B26: 327135.6 | C26: 327135.6 | D26: =C26 -> 327135.6 | E26: =SUM(D23:D26) -> 1995197.3
A27: 2005Q2 | B27: 474747.6 | C27: 474747.6 | D27: =C27 -> 474747.6 | E27: =SUM(D24:D27) -> 2054958.8
A28: 2005Q3 | B28: 705065.9 | C28: 705065.9 | D28: =C28 -> 705065.9 | E28: =SUM(D25:D28) -> 2134775.6
A29: 2005Q4 | B29: 735931.8 | C29: 735931.8 | D29: =C29 -> 735931.8 | E29: =SUM(D26:D29) -> 2242880.9
A30: 2006Q1 | B30: 370000.4 | C30: 370000.4 | D30: =C30 -> 370000.4 | E30: =SUM(D27:D30) -> 2285745.7
A31: 2006Q2 | B31: 565444.8 | C31: 565444.8 | D31: =C31 -> 565444.8 | E31: =SUM(D28:D31) -> 2376442.9
A32: 2006Q3 | B32: 790806.1 | C32: 790806.1 | D32: =C32 -> 790806.1 | E32: =SUM(D29:D32) -> 2462183.1
A33: 2006Q4 | B33: 812645.1 | C33: 812645.1 | D33: =C33 -> 812645.1 | E33: =SUM(D30:D33) -> 2538896.4
A34: 2007Q1 | B34: 414861.4 | C34: 414861.4 | D34: =C34 -> 414861.4 | E34: =SUM(D31:D34) -> 2583757.4
A35: 2007Q2 | B35: 622876.5 | C35: 622876.5 | D35: =C35 -> 622876.5 | E35: =SUM(D32:D35) -> 2641189.1
A36: 2007Q3 | B36: 915268.8 | C36: 915268.8 | D36: =C36 -> 915268.8 | E36: =SUM(D33:D36) -> 2765651.8
A37: 2007Q4 | B37: 934967.7 | C37: 934967.7 | D37: =C37 -> 934967.7 | E37: =SUM(D34:D37) -> 2887974.4
... A84: 2019Q3 | B84: 1166417.8 | C84: 1175036 | D84: =C84 -> 1175036 | E84: =SUM(D81:D84) -> 4017353.2
C85: 1259863.3 | D85: =C85 -> 1259863.3 | E85: =SUM(D82:D85) -> 4106171
C86: 795320.43 | D86: =C86 -> 795320.43 | E86: =SUM(D83:D86) -> 4138403.2
C87: 784214.85 | D87: =C87 -> 784214.85 | E87: =SUM(D84:D87) -> 4014434.6
C88: 1072123.1 | D88: =C88 -> 1072123.1 | E88: =SUM(D85:D88) -> 3911521.7
C89: 1150682.6 | D89: =C89 -> 1150682.6 | E89: =SUM(D86:D89) -> 3802341
C90: 782063.96 | D90: =C90 -> 782063.96 | E90: =SUM(D87:D90) -> 3789084.5
C91: 857161.48 | D91: =C91 -> 857161.48 | E91: =SUM(D88:D91) -> 3862031.2
C92: 1096694.3 | D92: =C92 -> 1096694.3 | E92: =SUM(D89:D92) -> 3886602.3
C93: 1282998.3 | D93: =C93 -> 1282998.3 | E93: =SUM(D90:D93) -> 4018918
C94: 850030.59 | D94: =C94 -> 850030.59 | E94: =SUM(D91:D94) -> 4086884.6
C95: 970379.82 | D95: =C95 -> 970379.82 | E95: =SUM(D92:D95) -> 4200103
C96: 1258662.1 | D96: =C96 -> 1258662.1 | E96: =SUM(D93:D96) -> 4362070.8
... C102: 1007112.7 | D102: =C102 -> 1007112.7 | E102: =SUM(D99:D102) -> 4903732.2

Sheet RoE
A1: Date | B1: RoE | E1: Date | F1: RoE
A2: 37986 | B2: 0.17759128 | E2: 37711 | F2: =F3 -> 0.17759128
A3: 38017 | B3: 0.19277691 | E3: 37802 | F3: =F4 -> 0.17759128
A4: 38046 | B4: 0.23901323 | E4: 37894 | F4: =F5 -> 0.17759128
A5: 38077 | B5: 0.25097346 | E5: 37986 | F5: =VLOOKUP(E5,$A$2:$B$244,2,FALSE) -> 0.17759128
A6: 38107 | B6: 0.25107097 | E6: 38077 | F6: =VLOOKUP(E6,$A$2:$B$244,2,FALSE) -> 0.25097346
A7: 38138 | B7: 0.28646016 | E7: 38168 | F7: =VLOOKUP(E7,$A$2:$B$244,2,FALSE) -> 0.25399792
A8: 38168 | B8: 0.25399792 | E8: 38260 | F8: =VLOOKUP(E8,$A$2:$B$244,2,FALSE) -> 0.21843329
A9: 38199 | B9: 0.20987313 | E9: 38352 | F9: =VLOOKUP(E9,$A$2:$B$244,2,FALSE) -> 0.32586859
A10: 38230 | B10: 0.20075484 | E10: 38442 | F10: =VLOOKUP(E10,$A$2:$B$244,2,FALSE) -> 0.30676664
A11: 38260 | B11: 0.21843329 | E11: 38533 | F11: =VLOOKUP(E11,$A$2:$B$244,2,FALSE) -> 0.27623124
A12: 38291 | B12: 0.35307261 | E12: 38625 | F12: =VLOOKUP(E12,$A$2:$B$244,2,FALSE) -> 0.25989059
A13: 38321 | B13: 0.35254778 | E13: 38717 | F13: =VLOOKUP(E13,$A$2:$B$244,2,FALSE) -> 0.15247996
A14: 38352 | B14: 0.32586859 | E14: 38807 | F14: =VLOOKUP(E14,$A$2:$B$244,2,FALSE) -> 0.15518108
A15: 38383 | B15: 0.32212597 | E15: 38898 | F15: =VLOOKUP(E15,$A$2:$B$244,2,FALSE) -> 0.16243635
A16: 38411 | B16: 0.32326388 | E16: 38990 | F16: =VLOOKUP(E16,$A$2:$B$244,2,FALSE) -> 0.16067328
... A85: 40512 | B85: 0.11293182 | E85: 45291 | F85: =VLOOKUP(E85,$A$2:$B$244,2,FALSE) -> 0.1310008
A86: 40543 | B86: 0.10225911 | E86: 45382 | F86: =B244 -> 0.13868405
A87: 40574 | B87: 0.10543306
A88: 40602 | B88: 0.1069003
A89: 40633 | B89: 0.11098567
A90: 40663 | B90: 0.11249519
A91: 40694 | B91: 0.1146213
A92: 40724 | B92: 0.117503
A93: 40755 | B93: 0.11061318
A94: 40786 | B94: 0.11108552
A95: 40816 | B95: 0.10326304
A96: 40847 | B96: 0.09684772
A97: 40877 | B97: 0.097524249
A98: 40908 | B98: 0.087227465
... A244: 45351 | B244: 0.13868405

Sheet Spot yield curve
A1: Հաշվարկի ամսաթիվը/ Date | B1: Quarter | C1: 1 օր/day | D1: 1 ամիս/month | E1: 3 ամիս/month | F1: 6 ամիս/month | G1: 9 ամիս/month | H1: 1 տարի/year | I1: 2 տարի/year | J1: 3 տարի/year | K1: 4 տարի/year | L1: 5 տարի/year | M1: 7 տարի/year | N1: 10 տարի/year | O1: 15 տարի/year | P1: 20 տարի/year | Q1: 30 տարի/year
A2: 41464 | B2: =YEAR(A2)&" q"&ROUNDUP(MONTH(A2)/3,0) -> 2013 q3 | C2: 8.2018 | D2: 8.1811 | E2: 8.1384 | F2: 8.3117 | G2: 8.7937 | H2: 9.2775 | I2: 11.3609 | J2: 12.8422 | K2: 13.6499 | L2: 14.3069 | M2: 14.922 | N2: 15.3031 | O2: 15.7026 | P2: 16.102
A3: 41465 | B3: =YEAR(A3)&" q"&ROUNDUP(MONTH(A3)/3,0) -> 2013 q3 | C3: 8.1896 | D3: 8.1795 | E3: 8.1587 | F3: 8.3417 | G3: 8.7484 | H3: 9.1597 | I3: 10.9772 | J3: 12.6168 | K3: 13.5179 | L3: 14.2508 | M3: 14.9721 | N3: 15.4165 | O3: 15.8874 | P3: 16.3582
A4: 41466 | B4: =YEAR(A4)&" q"&ROUNDUP(MONTH(A4)/3,0) -> 2013 q3 | C4: 8.2421 | D4: 8.2106 | E4: 8.1456 | F4: 8.3472 | G4: 8.8477 | H4: 9.351 | I4: 11.451 | J4: 12.8881 | K4: 13.6577 | L4: 14.2737 | M4: 14.8502 | N4: 15.2033 | O4: 15.5763 | P4: 15.9494
A5: 41467 | B5: =YEAR(A5)&" q"&ROUNDUP(MONTH(A5)/3,0) -> 2013 q3 | C5: 8.1093 | D5: 8.167 | E5: 8.2861 | F5: 8.5834 | G5: 8.9944 | H5: 9.4211 | I5: 11.1281 | J5: 12.6624 | K5: 13.5037 | L5: 14.1881 | M5: 14.8747 | N5: 15.2972 | O5: 15.747 | P5: 16.1968
A6: 41468 | B6: =YEAR(A6)&" q"&ROUNDUP(MONTH(A6)/3,0) -> 2013 q3 | C6: 8.1403 | D6: 8.173 | E6: 8.2404 | F6: 8.5874 | G6: 9.1601 | H6: 9.7475 | I6: 11.9003 | J6: 13.1288 | K6: 13.7717 | L6: 14.2812 | M6: 14.7508 | N6: 15.0371 | O6: 15.3402 | P6: 15.6433
A7: 41470 | B7: =YEAR(A7)&" q"&ROUNDUP(MONTH(A7)/3,0) -> 2013 q3 | C7: 8.111 | D7: 8.1703 | E7: 8.2927 | F7: 8.5978 | G7: 9.01 | H7: 9.4359 | I7: 11.1396 | J7: 12.6665 | K7: 13.5072 | L7: 14.1883 | M7: 14.8748 | N7: 15.2957 | O7: 15.7453 | P7: 16.1948
A8: 41471 | B8: =YEAR(A8)&" q"&ROUNDUP(MONTH(A8)/3,0) -> 2013 q3 | C8: 8.1238 | D8: 8.2158 | E8: 8.4059 | F8: 8.6992 | G8: 9.3546 | H8: 9.9404 | I8: 12.0625 | J8: 13.2315 | K8: 13.8804 | L8: 14.2269 | M8: 14.6717 | N8: 14.9347 | O8: 15.2079 | P8: 15.4811
A9: 41472 | B9: =YEAR(A9)&" q"&ROUNDUP(MONTH(A9)/3,0) -> 2013 q3 | C9: 8.1284 | D9: 8.2172 | E9: 8.4005 | F9: 8.685 | G9: 9.2449 | H9: 9.7941 | I9: 11.8211 | J9: 13.098 | K9: 13.8605 | L9: 14.28 | M9: 14.8246 | N9: 15.1466 | O9: 15.482 | P9: 15.8174
A10: 41473 | B10: =YEAR(A10)&" q"&ROUNDUP(MONTH(A10)/3,0) -> 2013 q3 | C10: 8.1228 | D10: 8.2104 | E10: 8.3913 | F10: 8.6754 | G10: 9.2365 | H10: 9.7881 | I10: 11.8213 | J10: 13.1013 | K10: 13.8653 | L10: 14.2891 | M10: 14.8316 | N10: 15.1526 | O10: 15.4885 | P10: 15.8244
A11: 41474 | B11: =YEAR(A11)&" q"&ROUNDUP(MONTH(A11)/3,0) -> 2013 q3 | C11: 8.1064 | D11: 8.2051 | E11: 8.4088 | F11: 8.726 | G11: 9.2428 | H11: 9.7584 | I11: 11.6774 | J11: 12.9665 | K11: 13.7736 | L11: 14.2284 | M11: 14.8271 | N11: 15.1806 | O11: 15.5507 | P11: 15.9208
A12: 41477 | B12: =YEAR(A12)&" q"&ROUNDUP(MONTH(A12)/3,0) -> 2013 q3 | C12: 8.036 | D12: 8.1449 | E12: 8.3696 | F12: 8.7196 | G12: 9.25 | H12: 9.7709 | I12: 11.7032 | J12: 12.9831 | K12: 13.7785 | L12: 14.2246 | M12: 14.8118 | N12: 15.1576 | O12: 15.5201 | P12: 15.8827
A13: 41478 | B13: =YEAR(A13)&" q"&ROUNDUP(MONTH(A13)/3,0) -> 2013 q3 | C13: 8.1383 | D13: 8.2717 | E13: 8.547 | F13: 9.0242 | G13: 9.5038 | H13: 9.9595 | I13: 11.6652 | J13: 12.8773 | K13: 13.6953 | L13: 14.1813 | M13: 14.8445 | N13: 15.237 | O13: 15.6546 | P13: 16.0721
... A984: 42894 | B984: =YEAR(A984)&" q"&ROUNDUP(MONTH(A984)/3,0) -> 2017 q2 | C984: 5.783 | D984: 5.8597 | E984: 6.018 | F984: 6.254 | G984: 6.4838 | H984: 6.7131 | I984: 7.5695 | J984: 8.3585 | K984: 9.0742 | L984: 9.6599 | M984: 10.8313 | N984: 12.2658 | O984: 14.1513 | P984: 15.4347
A985: 42895 | B985: =YEAR(A985)&" q"&ROUNDUP(MONTH(A985)/3,0) -> 2017 q2 | C985: 5.771 | D985: 5.8491 | E985: 6.0104 | F985: 6.2506 | G985: 6.484 | H985: 6.7168 | I985: 7.5819 | J985: 8.374 | K985: 9.087 | L985: 9.6624 | M985: 10.8131 | N985: 12.2047 | O985: 14.0025 | P985: 15.1974 | Q985: 17.587
A986: 42898 | B986: =YEAR(A986)&" q"&ROUNDUP(MONTH(A986)/3,0) -> 2017 q2 | C986: 5.8659 | D986: 5.9363 | E986: 6.0817 | F986: 6.2989 | G986: 6.512 | H986: 6.7246 | I986: 7.5347 | J986: 8.2985 | K986: 9.0098 | L986: 9.6249 | M986: 10.8552 | N986: 12.4361 | O986: 14.6544 | P986: 16.252 | Q986: 18.5318
A987: 42899 | B987: =YEAR(A987)&" q"&ROUNDUP(MONTH(A987)/3,0) -> 2017 q2 | C987: 5.8072 | D987: 5.8798 | E987: 6.0297 | F987: 6.2535 | G987: 6.4743 | H987: 6.6845 | I987: 7.5185 | J987: 8.2948 | K987: 9.0123 | L987: 9.6252 | M987: 10.851 | N987: 12.4047 | O987: 14.5503 | P987: 16.0539 | Q987: 18.1477
A988: 42900 | B988: =YEAR(A988)&" q"&ROUNDUP(MONTH(A988)/3,0) -> 2017 q2 | C988: 5.7231 | D988: 5.8019 | E988: 5.9644 | F988: 6.2068 | G988: 6.4447 | H988: 6.6757 | I988: 7.5482 | J988: 8.3479 | K988: 9.0675 | L988: 9.6514 | M988: 10.8193 | N988: 12.2317 | O988: 14.0642 | P988: 15.2884 | Q988: 17.7369
A989: 42901 | B989: =YEAR(A989)&" q"&ROUNDUP(MONTH(A989)/3,0) -> 2017 q2 | C989: 5.7292 | D989: 5.8075 | E989: 5.9691 | F989: 6.21 | G989: 6.4465 | H989: 6.6761 | I989: 7.5443 | J989: 8.3408 | K989: 9.0581 | L989: 9.6418 | M989: 10.8091 | N989: 12.223 | O989: 14.0626 | P989: 15.2963 | Q989: 17.7637
A990: 42902 | B990: =YEAR(A990)&" q"&ROUNDUP(MONTH(A990)/3,0) -> 2017 q2 | C990: 5.7874 | D990: 5.8614 | E990: 6.0142 | F990: 6.242 | G990: 6.4664 | H990: 6.685 | I990: 7.519 | J990: 8.2937 | K990: 9.0014 | L990: 9.5943 | M990: 10.78 | N990: 12.2526 | O990: 14.2362 | P990: 15.5704 | Q990: 17.3633
A991: 42905 | B991: =YEAR(A991)&" q"&ROUNDUP(MONTH(A991)/3,0) -> 2017 q2 | C991: 5.7298 | D991: 5.8085 | E991: 5.9712 | F991: 6.2134 | G991: 6.451 | H991: 6.6812 | I991: 7.5501 | J991: 8.3443 | K991: 9.0558 | L991: 9.6305 | M991: 10.7799 | N991: 12.1607 | O991: 13.9396 | P991: 15.1162 | Q991: 17.4694
A992: 42906 | B992: =YEAR(A992)&" q"&ROUNDUP(MONTH(A992)/3,0) -> 2017 q2 | C992: 5.7262 | D992: 5.8073 | E992: 5.9748 | F992: 6.2236 | G992: 6.4668 | H992: 6.7009 | I992: 7.5765 | J992: 8.364 | K992: 9.0559 | L992: 9.5964 | M992: 10.6775 | N992: 11.937 | O992: 13.493 | P992: 14.4669 | Q992: 16.4148
A993: 42907 | B993: =YEAR(A993)&" q"&ROUNDUP(MONTH(A993)/3,0) -> 2017 q2 | C993: 5.831 | D993: 5.9015 | E993: 6.0469 | F993: 6.2637 | G993: 6.4771 | H993: 6.6851 | I993: 7.4806 | J993: 8.2211 | K993: 8.9088 | L993: 9.5409 | M993: 10.6417 | N993: 12.0367 | O993: 13.9677 | P993: 15.2788 | Q993: 17.057
A994: 42908 | B994: =YEAR(A994)&" q"&ROUNDUP(MONTH(A994)/3,0) -> 2017 q2 | C994: 5.9723 | D994: 6.0302 | E994: 6.1498 | F994: 6.3288 | G994: 6.5064 | H994: 6.6819 | I994: 7.3696 | J994: 8.0348 | K994: 8.6771 | L994: 9.2967 | M994: 10.4677 | N994: 12.0288 | O994: 14.4315 | P994: 16.3743 | Q994: 19.4539
A995: 42909 | B995: =YEAR(A995)&" q"&ROUNDUP(MONTH(A995)/3,0) -> 2017 q2 | C995: 5.9668 | D995: 6.0256 | E995: 6.147 | F995: 6.3285 | G995: 6.5086 | H995: 6.6864 | I995: 7.3822 | J995: 8.0536 | K995: 8.6981 | L995: 9.3079 | M995: 10.4956 | N995: 12.0473 | O995: 14.4237 | P995: 16.321 | Q995: 19.2895
A996: 42912 | B996: =YEAR(A996)&" q"&ROUNDUP(MONTH(A996)/3,0) -> 2017 q2 | C996: 5.7949 | D996: 5.8695 | E996: 6.0235 | F996: 6.2526 | G996: 6.4778 | H996: 6.6962 | I996: 7.5276 | J996: 8.2945 | K996: 8.9873 | L996: 9.5607 | M996: 10.7077 | N996: 12.107 | O996: 13.9579 | P996: 15.2269 | Q996: 17.765
... A2725: 45429 | B2725: =YEAR(A2725)&" q"&ROUNDUP(MONTH(A2725)/3,0) -> 2024 q2 | C2725: 8.5088 | D2725: 8.5738 | E2725: 8.708 | F2725: 8.9202 | G2725: 9.143 | H2725: 9.3448 | I2725: 9.5283 | J2725: 9.575 | K2725: 9.6203 | L2725: 9.637 | M2725: 9.6554 | N2725: 9.6742 | O2725: 9.6845 | P2725: 9.69 | Q2725: 9.7009

Sheet tb %
A1: Առաջնային շուկայում պետական պարտատոմսերի եկամտաբերություն 1
H3: (%)
B4: Պետական կարճաժամկետ պարտատոմսերի եկամտաբերություն | F4: Միջինժամկետ մասնակի մարումներով արժեկտրոնային ՊՊ եկամտաբերություն | G4: Միջինժամկետ ՊՊ միջին եկամտաբերություն | H4: Երկարաժամկետ ՊՊ միջին եկամտաբերություն
B5: 91-օրյա | C5: 182-օրյա | D5: 273-օրյա | E5: 364-օրյա | I5: Date | J5: Quarter | K5: Short term | L5: Mid Term | M5: Long term | P5: Short term | Q5: Mid Term | R5: Long term
A6: Հունվար 2000 | B6: 36.8 | C6: 43.04 | D6: 42.2 | I6: 36526 | J6: =YEAR(I6)&" q"&ROUNDUP(MONTH(I6)/3,0) -> 2000 q1 | K6: =IFERROR(AVERAGE(B6:E6)/100,"") -> 0.4068 | L6: =IFERROR(AVERAGE(F6:G6)/100,"") | M6: =IF(IFERROR(H6/100,"")=0,"",IFERROR(H6/100,"")) | O6: 2000 q1 | P6: =AVERAGEIF($J$6:$J$297,$O6,K$6:K$297) -> 0.31926199 | Q6: =AVERAGEIF($J$6:$J$297,$O6,L$6:L$297) -> 0.272 | R6: =Q6+AVERAGE($S$24:$S$37) -> 0.29251473
A7: Փետրվար | B7: 30.227513 | C7: 28.172479 | D7: 30.18 | E7: 35.0691 | I7: 36557 | J7: =YEAR(I7)&" q"&ROUNDUP(MONTH(I7)/3,0) -> 2000 q1 | K7: =IFERROR(AVERAGE(B7:E7)/100,"") -> 0.30912273 | L7: =IFERROR(AVERAGE(F7:G7)/100,"") | M7: =IF(IFERROR(H7/100,"")=0,"",IFERROR(H7/100,"")) | O7: 2000 q2 | P7: =AVERAGEIF($J$6:$J$297,$O7,K$6:K$297) -> 0.18687584 | Q7: =AVERAGEIF($J$6:$J$297,$O7,L$6:L$297) -> 0.2185 | R7: =Q7+AVERAGE($S$24:$S$37) -> 0.23901473
A8: Մարտ | B8: 20.967 | C8: 25.85 | D8: 25.741975 | F8: 27.2 | I8: 36586 | J8: =YEAR(I8)&" q"&ROUNDUP(MONTH(I8)/3,0) -> 2000 q1 | K8: =IFERROR(AVERAGE(B8:E8)/100,"") -> 0.24186325 | L8: =IFERROR(AVERAGE(F8:G8)/100,"") -> 0.272 | M8: =IF(IFERROR(H8/100,"")=0,"",IFERROR(H8/100,"")) | O8: 2000 q3 | P8: =AVERAGEIF($J$6:$J$297,$O8,K$6:K$297) -> 0.22851968 | Q8: =AVERAGEIF($J$6:$J$297,$O8,L$6:L$297) -> 0.25496953 | R8: =Q8+AVERAGE($S$24:$S$37) -> 0.27548426
A9: Ապրիլ | B9: 17.151 | C9: 19.877771 | D9: 20.7193 | E9: 21.178 | F9: 24.3 | I9: 36617 | J9: =YEAR(I9)&" q"&ROUNDUP(MONTH(I9)/3,0) -> 2000 q2 | K9: =IFERROR(AVERAGE(B9:E9)/100,"") -> 0.19731518 | L9: =IFERROR(AVERAGE(F9:G9)/100,"") -> 0.243 | M9: =IF(IFERROR(H9/100,"")=0,"",IFERROR(H9/100,"")) | O9: 2000 q4 | P9: =AVERAGEIF($J$6:$J$297,$O9,K$6:K$297) -> 0.26669064 | Q9: =AVERAGEIF($J$6:$J$297,$O9,L$6:L$297) -> 0.275 | R9: =Q9+AVERAGE($S$24:$S$37) -> 0.29551473
A10: Մայիս | B10: 14.4093 | C10: 16.540933 | D10: 18.8686 | E10: 19.7765 | F10: 19.4 | I10: 36647 | J10: =YEAR(I10)&" q"&ROUNDUP(MONTH(I10)/3,0) -> 2000 q2 | K10: =IFERROR(AVERAGE(B10:E10)/100,"") -> 0.17398833 | L10: =IFERROR(AVERAGE(F10:G10)/100,"") -> 0.194 | M10: =IF(IFERROR(H10/100,"")=0,"",IFERROR(H10/100,"")) | O10: 2001 q1 | P10: =AVERAGEIF($J$6:$J$297,$O10,K$6:K$297) -> 0.24431089 | Q10: =AVERAGEIF($J$6:$J$297,$O10,L$6:L$297) -> 0.25923133 | R10: =Q10+AVERAGE($S$24:$S$37) -> 0.27974606
A11: Հունիս | C11: 18.027206 | D11: 18.26 | E11: 20.51 | I11: 36678 | J11: =YEAR(I11)&" q"&ROUNDUP(MONTH(I11)/3,0) -> 2000 q2 | K11: =IFERROR(AVERAGE(B11:E11)/100,"") -> 0.18932402 | L11: =IFERROR(AVERAGE(F11:G11)/100,"") | M11: =IF(IFERROR(H11/100,"")=0,"",IFERROR(H11/100,"")) | O11: 2001 q2 | P11: =AVERAGEIF($J$6:$J$297,$O11,K$6:K$297) -> 0.21401362 | Q11: =AVERAGEIF($J$6:$J$297,$O11,L$6:L$297) -> 0.24666667 | R11: =Q11+AVERAGE($S$24:$S$37) -> 0.26718139
A12: Հուլիս | C12: 19.97852 | D12: 23.651181 | E12: 24.7669 | I12: 36708 | J12: =YEAR(I12)&" q"&ROUNDUP(MONTH(I12)/3,0) -> 2000 q3 | K12: =IFERROR(AVERAGE(B12:E12)/100,"") -> 0.22798867 | L12: =IFERROR(AVERAGE(F12:G12)/100,"") | M12: =IF(IFERROR(H12/100,"")=0,"",IFERROR(H12/100,"")) | O12: 2001 q3 | P12: =AVERAGEIF($J$6:$J$297,$O12,K$6:K$297) -> 0.18122778 | Q12: =AVERAGEIF($J$6:$J$297,$O12,L$6:L$297) -> 0.2227 | R12: =Q12+AVERAGE($S$24:$S$37) -> 0.24321473
A13: Օգոստոս | C13: 24.2508 | D13: 20.774914 | E13: 22.133145 | F13: 26 | I13: 36739 | J13: =YEAR(I13)&" q"&ROUNDUP(MONTH(I13)/3,0) -> 2000 q3 | K13: =IFERROR(AVERAGE(B13:E13)/100,"") -> 0.22386287 | L13: =IFERROR(AVERAGE(F13:G13)/100,"") -> 0.26 | M13: =IF(IFERROR(H13/100,"")=0,"",IFERROR(H13/100,"")) | O13: 2001 q4 | P13: =AVERAGEIF($J$6:$J$297,$O13,K$6:K$297) -> 0.16778994 | Q13: =AVERAGEIF($J$6:$J$297,$O13,L$6:L$297) -> 0.198402 | R13: =Q13+AVERAGE($S$24:$S$37) -> 0.21891673
A14: Սեպտեմբեր | C14: 20.25775 | D14: 23.9226 | E14: 25.9319 | F14: 24.993907 | I14: 36770 | J14: =YEAR(I14)&" q"&ROUNDUP(MONTH(I14)/3,0) -> 2000 q3 | K14: =IFERROR(AVERAGE(B14:E14)/100,"") -> 0.2337075 | L14: =IFERROR(AVERAGE(F14:G14)/100,"") -> 0.24993907 | M14: =IF(IFERROR(H14/100,"")=0,"",IFERROR(H14/100,"")) | O14: 2002 q1 | P14: =AVERAGEIF($J$6:$J$297,$O14,K$6:K$297) -> 0.13747072 | Q14: =AVERAGEIF($J$6:$J$297,$O14,L$6:L$297) -> 0.147182 | R14: =Q14+AVERAGE($S$24:$S$37) -> 0.16769673
A15: Հոկտեմբեր | C15: 25.128179 | D15: 26.4708 | E15: 27.2276 | F15: 27.5 | I15: 36800 | J15: =YEAR(I15)&" q"&ROUNDUP(MONTH(I15)/3,0) -> 2000 q4 | K15: =IFERROR(AVERAGE(B15:E15)/100,"") -> 0.26275526 | L15: =IFERROR(AVERAGE(F15:G15)/100,"") -> 0.275 | M15: =IF(IFERROR(H15/100,"")=0,"",IFERROR(H15/100,"")) | O15: 2002 q2 | P15: =AVERAGEIF($J$6:$J$297,$O15,K$6:K$297) -> 0.14255967 | Q15: =AVERAGEIF($J$6:$J$297,$O15,L$6:L$297) -> 0.17800771 | R15: =Q15+AVERAGE($S$24:$S$37) -> 0.19852244
A16: Նոյեմբեր | C16: 26.312656 | D16: 26.710908 | E16: 28.601 | I16: 36831 | J16: =YEAR(I16)&" q"&ROUNDUP(MONTH(I16)/3,0) -> 2000 q4 | K16: =IFERROR(AVERAGE(B16:E16)/100,"") -> 0.27208188 | L16: =IFERROR(AVERAGE(F16:G16)/100,"") | M16: =IF(IFERROR(H16/100,"")=0,"",IFERROR(H16/100,"")) | O16: 2002 q3 | P16: =AVERAGEIF($J$6:$J$297,$O16,K$6:K$297) -> 0.15358212 | Q16: =AVERAGEIF($J$6:$J$297,$O16,L$6:L$297) -> 0.18351654 | R16: =Q16+AVERAGE($S$24:$S$37) -> 0.20403126
A17: Դեկտեմբեր | B17: 26.5 | C17: 25.4 | D17: 27.670432 | I17: 36861 | J17: =YEAR(I17)&" q"&ROUNDUP(MONTH(I17)/3,0) -> 2000 q4 | K17: =IFERROR(AVERAGE(B17:E17)/100,"") -> 0.26523477 | L17: =IFERROR(AVERAGE(F17:G17)/100,"") | M17: =IF(IFERROR(H17/100,"")=0,"",IFERROR(H17/100,"")) | O17: 2002 q4 | P17: =AVERAGEIF($J$6:$J$297,$O17,K$6:K$297) -> 0.15397614 | Q17: =AVERAGEIF($J$6:$J$297,$O17,L$6:L$297) -> 0.18895736 | R17: =Q17+AVERAGE($S$24:$S$37) -> 0.20947208
A18: Հունվար 2001 | C18: 25.95 | D18: 25.87 | F18: 27.3994 | I18: 36892 | J18: =YEAR(I18)&" q"&ROUNDUP(MONTH(I18)/3,0) -> 2001 q1 | K18: =IFERROR(AVERAGE(B18:E18)/100,"") -> 0.2591 | L18: =IFERROR(AVERAGE(F18:G18)/100,"") -> 0.273994 | M18: =IF(IFERROR(H18/100,"")=0,"",IFERROR(H18/100,"")) | O18: 2003 q1 | P18: =AVERAGEIF($J$6:$J$297,$O18,K$6:K$297) -> 0.13654185 | Q18: =AVERAGEIF($J$6:$J$297,$O18,L$6:L$297) -> 0.1614635 | R18: =Q18+AVERAGE($S$24:$S$37) -> 0.18197823
A19: Փետրվար | B19: 22.27 | C19: 23.65 | F19: 23.16 | I19: 36923 | J19: =YEAR(I19)&" q"&ROUNDUP(MONTH(I19)/3,0) -> 2001 q1 | K19: =IFERROR(AVERAGE(B19:E19)/100,"") -> 0.2296 | L19: =IFERROR(AVERAGE(F19:G19)/100,"") -> 0.2316 | M19: =IF(IFERROR(H19/100,"")=0,"",IFERROR(H19/100,"")) | O19: 2003 q2 | P19: =AVERAGEIF($J$6:$J$297,$O19,K$6:K$297) -> 0.13411011 | Q19: =AVERAGEIF($J$6:$J$297,$O19,L$6:L$297) -> 0.16544733 | R19: =Q19+AVERAGE($S$24:$S$37) -> 0.18596206
A20: Մարտ | C20: 24.02 | D20: 24.12 | E20: 25.1298 | F20: 27.21 | I20: 36951 | J20: =YEAR(I20)&" q"&ROUNDUP(MONTH(I20)/3,0) -> 2001 q1 | K20: =IFERROR(AVERAGE(B20:E20)/100,"") -> 0.24423267 | L20: =IFERROR(AVERAGE(F20:G20)/100,"") -> 0.2721 | M20: =IF(IFERROR(H20/100,"")=0,"",IFERROR(H20/100,"")) | O20: 2003 q3 | P20: =AVERAGEIF($J$6:$J$297,$O20,K$6:K$297) -> 0.10521969 | Q20: =AVERAGEIF($J$6:$J$297,$O20,L$6:L$297) -> 0.15862029 | R20: =Q20+AVERAGE($S$24:$S$37) -> 0.17913501
A21: Ապրիլ | C21: 24.13529 | D21: 24.5308 | E21: 24.556167 | F21: 26 | I21: 36982 | J21: =YEAR(I21)&" q"&ROUNDUP(MONTH(I21)/3,0) -> 2001 q2 | K21: =IFERROR(AVERAGE(B21:E21)/100,"") -> 0.24407419 | L21: =IFERROR(AVERAGE(F21:G21)/100,"") -> 0.26 | M21: =IF(IFERROR(H21/100,"")=0,"",IFERROR(H21/100,"")) | O21: 2003 q4 | P21: =AVERAGEIF($J$6:$J$297,$O21,K$6:K$297) -> 0.099805778 | Q21: =AVERAGEIF($J$6:$J$297,$O21,L$6:L$297) -> 0.0714815 | R21: =Q21+AVERAGE($S$24:$S$37) -> 0.091996228
A22: Մայիս | C22: 19.31 | D22: 20.75 | E22: 21.04 | F22: 24.61 | I22: 37012 | J22: =YEAR(I22)&" q"&ROUNDUP(MONTH(I22)/3,0) -> 2001 q2 | K22: =IFERROR(AVERAGE(B22:E22)/100,"") -> 0.20366667 | L22: =IFERROR(AVERAGE(F22:G22)/100,"") -> 0.2461 | M22: =IF(IFERROR(H22/100,"")=0,"",IFERROR(H22/100,"")) | O22: 2004 q1 | P22: =AVERAGEIF($J$6:$J$297,$O22,K$6:K$297) -> 0.066186056 | Q22: =AVERAGEIF($J$6:$J$297,$O22,L$6:L$297) -> 0.097205 | R22: =Q22+AVERAGE($S$24:$S$37) -> 0.11771973
A23: Հունիս | C23: 18.93 | D23: 19.41 | E23: 19.95 | F23: 23.39 | I23: 37043 | J23: =YEAR(I23)&" q"&ROUNDUP(MONTH(I23)/3,0) -> 2001 q2 | K23: =IFERROR(AVERAGE(B23:E23)/100,"") -> 0.1943 | L23: =IFERROR(AVERAGE(F23:G23)/100,"") -> 0.2339 | M23: =IF(IFERROR(H23/100,"")=0,"",IFERROR(H23/100,"")) | O23: 2004 q2 | P23: =AVERAGEIF($J$6:$J$297,$O23,K$6:K$297) -> 0.056279333 | Q23: =AVERAGEIF($J$6:$J$297,$O23,L$6:L$297) -> 0.091385333 | R23: =Q23+AVERAGE($S$24:$S$37) -> 0.11190006
A24: Հուլիս | C24: 17.7 | D24: 18.33 | E24: 18.46 | F24: 22.33 | I24: 37073 | J24: =YEAR(I24)&" q"&ROUNDUP(MONTH(I24)/3,0) -> 2001 q3 | K24: =IFERROR(AVERAGE(B24:E24)/100,"") -> 0.18163333 | L24: =IFERROR(AVERAGE(F24:G24)/100,"") -> 0.2233 | M24: =IF(IFERROR(H24/100,"")=0,"",IFERROR(H24/100,"")) | O24: 2004 q3 | P24: =AVERAGEIF($J$6:$J$297,$O24,K$6:K$297) -> 0.049925389 | Q24: =AVERAGEIF($J$6:$J$297,$O24,L$6:L$297) -> 0.07316532 | R24: =AVERAGEIF($J$6:$J$297,$O24,M$6:M$297) -> 0.092446 | S24: =R24-Q24 -> 0.01928068
A25: Օգոստոս | D25: 17.7 | E25: 18 | I25: 37104 | J25: =YEAR(I25)&" q"&ROUNDUP(MONTH(I25)/3,0) -> 2001 q3 | K25: =IFERROR(AVERAGE(B25:E25)/100,"") -> 0.1785 | L25: =IFERROR(AVERAGE(F25:G25)/100,"") | M25: =IF(IFERROR(H25/100,"")=0,"",IFERROR(H25/100,"")) | O25: 2004 q4 | P25: =AVERAGEIF($J$6:$J$297,$O25,K$6:K$297) -> 0.039987208 | Q25: =AVERAGEIF($J$6:$J$297,$O25,L$6:L$297) -> 0.066362 | R25: =AVERAGEIF($J$6:$J$297,$O25,M$6:M$297) -> 0.092683 | S25: =R25-Q25 -> 0.026321
A26: Սեպտեմբեր | D26: 17.71 | E26: 19 | F26: 22.21 | I26: 37135 | J26: =YEAR(I26)&" q"&ROUNDUP(MONTH(I26)/3,0) -> 2001 q3 | K26: =IFERROR(AVERAGE(B26:E26)/100,"") -> 0.18355 | L26: =IFERROR(AVERAGE(F26:G26)/100,"") -> 0.2221 | M26: =IF(IFERROR(H26/100,"")=0,"",IFERROR(H26/100,"")) | O26: 2005 q1 | P26: =AVERAGEIF($J$6:$J$297,$O26,K$6:K$297) -> 0.041224556 | Q26: =AVERAGEIF($J$6:$J$297,$O26,L$6:L$297) -> 0.052538667 | R26: =AVERAGEIF($J$6:$J$297,$O26,M$6:M$297) -> 0.0693 | S26: =R26-Q26 -> 0.016761333
A27: Հոկտեմբեր | D27: 16.93 | E27: 17.54 | F27: 20.7657 | I27: 37165 | J27: =YEAR(I27)&" q"&ROUNDUP(MONTH(I27)/3,0) -> 2001 q4 | K27: =IFERROR(AVERAGE(B27:E27)/100,"") -> 0.17235 | L27: =IFERROR(AVERAGE(F27:G27)/100,"") -> 0.207657 | M27: =IF(IFERROR(H27/100,"")=0,"",IFERROR(H27/100,"")) | O27: 2005 q2 | P27: =AVERAGEIF($J$6:$J$297,$O27,K$6:K$297) -> 0.045867097 | Q27: =AVERAGEIF($J$6:$J$297,$O27,L$6:L$297) -> 0.053465833 | R27: =AVERAGEIF($J$6:$J$297,$O27,M$6:M$297) -> 0.0737015 | S27: =R27-Q27 -> 0.020235667
A28: Նոյեմբեր | D28: 16.6254 | E28: 16.840165 | F28: 18.8168 | I28: 37196 | J28: =YEAR(I28)&" q"&ROUNDUP(MONTH(I28)/3,0) -> 2001 q4 | K28: =IFERROR(AVERAGE(B28:E28)/100,"") -> 0.16732782 | L28: =IFERROR(AVERAGE(F28:G28)/100,"") -> 0.188168 | M28: =IF(IFERROR(H28/100,"")=0,"",IFERROR(H28/100,"")) | O28: 2005 q3 | P28: =AVERAGEIF($J$6:$J$297,$O28,K$6:K$297) -> 0.037295944 | Q28: =AVERAGEIF($J$6:$J$297,$O28,L$6:L$297) -> 0.051909 | R28: =AVERAGEIF($J$6:$J$297,$O28,M$6:M$297) -> 0.0537905 | S28: =R28-Q28 -> 0.0018815
A29: Դեկտեմբեր | E29: 16.3692 | F29: 19.9381 | I29: 37226 | J29: =YEAR(I29)&" q"&ROUNDUP(MONTH(I29)/3,0) -> 2001 q4 | K29: =IFERROR(AVERAGE(B29:E29)/100,"") -> 0.163692 | L29: =IFERROR(AVERAGE(F29:G29)/100,"") -> 0.199381 | M29: =IF(IFERROR(H29/100,"")=0,"",IFERROR(H29/100,"")) | O29: 2005 q4 | P29: =AVERAGEIF($J$6:$J$297,$O29,K$6:K$297) -> 0.03758425 | Q29: =AVERAGEIF($J$6:$J$297,$O29,L$6:L$297) -> 0.0518685 | R29: =AVERAGEIF($J$6:$J$297,$O29,M$6:M$297) -> 0.088226 | S29: =R29-Q29 -> 0.0363575
A30: Հունվար 2002 | C30: 14.6792 | D30: 14.4942 | E30: 14.254521 | I30: 37257 | J30: =YEAR(I30)&" q"&ROUNDUP(MONTH(I30)/3,0) -> 2002 q1 | K30: =IFERROR(AVERAGE(B30:E30)/100,"") -> 0.14475974 | L30: =IFERROR(AVERAGE(F30:G30)/100,"") | M30: =IF(IFERROR(H30/100,"")=0,"",IFERROR(H30/100,"")) | O30: 2006 q1 | P30: =AVERAGEIF($J$6:$J$297,$O30,K$6:K$297) -> 0.04205825 | Q30: =AVERAGEIF($J$6:$J$297,$O30,L$6:L$297) -> 0.049107 | R30: =AVERAGEIF($J$6:$J$297,$O30,M$6:M$297) -> 0.085825543 | S30: =R30-Q30 -> 0.036718543
A31: Փետրվար | D31: 13.877 | E31: 13.8134 | I31: 37288 | J31: =YEAR(I31)&" q"&ROUNDUP(MONTH(I31)/3,0) -> 2002 q1 | K31: =IFERROR(AVERAGE(B31:E31)/100,"") -> 0.138452 | L31: =IFERROR(AVERAGE(F31:G31)/100,"") | M31: =IF(IFERROR(H31/100,"")=0,"",IFERROR(H31/100,"")) | O31: 2006 q2 | P31: =AVERAGEIF($J$6:$J$297,$O31,K$6:K$297) -> 0.048277599 | Q31: =AVERAGEIF($J$6:$J$297,$O31,L$6:L$297) -> 0.064560333 | R31: =AVERAGEIF($J$6:$J$297,$O31,M$6:M$297) -> 0.09878 | S31: =R31-Q31 -> 0.034219667
A32: Մարտ | D32: 12.8258 | E32: 13.014287 | F32: 14.7182 | I32: 37316 | J32: =YEAR(I32)&" q"&ROUNDUP(MONTH(I32)/3,0) -> 2002 q1 | K32: =IFERROR(AVERAGE(B32:E32)/100,"") -> 0.12920043 | L32: =IFERROR(AVERAGE(F32:G32)/100,"") -> 0.147182 | M32: =IF(IFERROR(H32/100,"")=0,"",IFERROR(H32/100,"")) | O32: 2006 q3 | P32: =AVERAGEIF($J$6:$J$297,$O32,K$6:K$297) -> 0.049332336 | Q32: =AVERAGEIF($J$6:$J$297,$O32,L$6:L$297) -> 0.064769532 | R32: =AVERAGEIF($J$6:$J$297,$O32,M$6:M$297) -> 0.095756162 | S32: =R32-Q32 -> 0.03098663
A33: Ապրիլ | C33: 13.5844 | D33: 12.4712 | E33: 14.1 | I33: 37347 | J33: =YEAR(I33)&" q"&ROUNDUP(MONTH(I33)/3,0) -> 2002 q2 | K33: =IFERROR(AVERAGE(B33:E33)/100,"") -> 0.133852 | L33: =IFERROR(AVERAGE(F33:G33)/100,"") | M33: =IF(IFERROR(H33/100,"")=0,"",IFERROR(H33/100,"")) | O33: 2006 q4 | P33: =AVERAGEIF($J$6:$J$297,$O33,K$6:K$297) -> 0.054834109 | Q33: =AVERAGEIF($J$6:$J$297,$O33,L$6:L$297) -> 0.066861 | R33: =AVERAGEIF($J$6:$J$297,$O33,M$6:M$297) -> 0.093692 | S33: =R33-Q33 -> 0.026831
A34: Մայիս | E34: 14.327 | F34: 16.9466 | I34: 37377 | J34: =YEAR(I34)&" q"&ROUNDUP(MONTH(I34)/3,0) -> 2002 q2 | K34: =IFERROR(AVERAGE(B34:E34)/100,"") -> 0.14327 | L34: =IFERROR(AVERAGE(F34:G34)/100,"") -> 0.169466 | M34: =IF(IFERROR(H34/100,"")=0,"",IFERROR(H34/100,"")) | O34: 2007 q1 | P34: =AVERAGEIF($J$6:$J$297,$O34,K$6:K$297) -> 0.05894 | Q34: =AVERAGEIF($J$6:$J$297,$O34,L$6:L$297) -> 0.068764333 | R34: =AVERAGEIF($J$6:$J$297,$O34,M$6:M$297) -> 0.079896 | S34: =R34-Q34 -> 0.011131667
A35: Հունիս | D35: 15.1355 | E35: 14.9759 | F35: 18.654942 | I35: 37408 | J35: =YEAR(I35)&" q"&ROUNDUP(MONTH(I35)/3,0) -> 2002 q2 | K35: =IFERROR(AVERAGE(B35:E35)/100,"") -> 0.150557 | L35: =IFERROR(AVERAGE(F35:G35)/100,"") -> 0.18654942 | M35: =IF(IFERROR(H35/100,"")=0,"",IFERROR(H35/100,"")) | O35: 2007 q2 | P35: =AVERAGEIF($J$6:$J$297,$O35,K$6:K$297) -> 0.059858 | Q35: =AVERAGEIF($J$6:$J$297,$O35,L$6:L$297) -> 0.065858333 | R35: =AVERAGEIF($J$6:$J$297,$O35,M$6:M$297) -> 0.067366 | S35: =R35-Q35 -> 0.0015076667
A36: Հուլիս | E36: 15.633133 | F36: 19.207707 | I36: 37438 | J36: =YEAR(I36)&" q"&ROUNDUP(MONTH(I36)/3,0) -> 2002 q3 | K36: =IFERROR(AVERAGE(B36:E36)/100,"") -> 0.15633133 | L36: =IFERROR(AVERAGE(F36:G36)/100,"") -> 0.19207707 | M36: =IF(IFERROR(H36/100,"")=0,"",IFERROR(H36/100,"")) | O36: 2007 q3 | P36: =AVERAGEIF($J$6:$J$297,$O36,K$6:K$297) -> 0.059434333 | Q36: =AVERAGEIF($J$6:$J$297,$O36,L$6:L$297) -> 0.065215833 | R36: =AVERAGEIF($J$6:$J$297,$O36,M$6:M$297) -> 0.067188 | S36: =R36-Q36 -> 0.0019721667
A37: Օգոստոս | D37: 15.301921 | E37: 15.749 | I37: 37469 | J37: =YEAR(I37)&" q"&ROUNDUP(MONTH(I37)/3,0) -> 2002 q3 | K37: =IFERROR(AVERAGE(B37:E37)/100,"") -> 0.15525461 | L37: =IFERROR(AVERAGE(F37:G37)/100,"") | M37: =IF(IFERROR(H37/100,"")=0,"",IFERROR(H37/100,"")) | O37: 2007 q4 | P37: =AVERAGEIF($J$6:$J$297,$O37,K$6:K$297) -> 0.065294 | Q37: =AVERAGEIF($J$6:$J$297,$O37,L$6:L$297) -> 0.071455833 | R37: =AVERAGEIF($J$6:$J$297,$O37,M$6:M$297) -> 0.094457 | S37: =R37-Q37 -> 0.023001167
A38: Սեպտեմբեր | E38: 14.916042 | F38: 17.4956 | I38: 37500 | J38: =YEAR(I38)&" q"&ROUNDUP(MONTH(I38)/3,0) -> 2002 q3 | K38: =IFERROR(AVERAGE(B38:E38)/100,"") -> 0.14916042 | L38: =IFERROR(AVERAGE(F38:G38)/100,"") -> 0.174956 | M38: =IF(IFERROR(H38/100,"")=0,"",IFERROR(H38/100,"")) | O38: 2008 q1 | P38: =AVERAGEIF($J$6:$J$297,$O38,K$6:K$297) -> 0.068918201 | Q38: =AVERAGEIF($J$6:$J$297,$O38,L$6:L$297) -> 0.082521443 | R38: =AVERAGEIF($J$6:$J$297,$O38,M$6:M$297) -> 0.10423639 | S38: =R38-Q38 -> 0.021714949
A39: Հոկտեմբեր | E39: 15.5 | F39: 19.5477 | I39: 37530 | J39: =YEAR(I39)&" q"&ROUNDUP(MONTH(I39)/3,0) -> 2002 q4 | K39: =IFERROR(AVERAGE(B39:E39)/100,"") -> 0.155 | L39: =IFERROR(AVERAGE(F39:G39)/100,"") -> 0.195477 | M39: =IF(IFERROR(H39/100,"")=0,"",IFERROR(H39/100,"")) | O39: 2008 q2 | P39: =AVERAGEIF($J$6:$J$297,$O39,K$6:K$297) -> 0.070631 | Q39: =AVERAGEIF($J$6:$J$297,$O39,L$6:L$297) -> 0.076798963 | R39: =AVERAGEIF($J$6:$J$297,$O39,M$6:M$297) -> 0.10328428 | S39: =R39-Q39 -> 0.026485318
A40: Նոյեմբեր | D40: 15.0732 | E40: 15.112486 | F40: 17.4758 | I40: 37561 | J40: =YEAR(I40)&" q"&ROUNDUP(MONTH(I40)/3,0) -> 2002 q4 | K40: =IFERROR(AVERAGE(B40:E40)/100,"") -> 0.15092843 | L40: =IFERROR(AVERAGE(F40:G40)/100,"") -> 0.174758 | M40: =IF(IFERROR(H40/100,"")=0,"",IFERROR(H40/100,"")) | O40: 2008 q3 | P40: =AVERAGEIF($J$6:$J$297,$O40,K$6:K$297) -> 0.079726417 | Q40: =AVERAGEIF($J$6:$J$297,$O40,L$6:L$297) -> 0.081021244 | R40: =AVERAGEIF($J$6:$J$297,$O40,M$6:M$297) -> 0.10574468 | S40: =R40-Q40 -> 0.024723436
A41: Դեկտեմբեր | E41: 15.6 | F41: 19.663707 | I41: 37591 | J41: =YEAR(I41)&" q"&ROUNDUP(MONTH(I41)/3,0) -> 2002 q4 | K41: =IFERROR(AVERAGE(B41:E41)/100,"") -> 0.156 | L41: =IFERROR(AVERAGE(F41:G41)/100,"") -> 0.19663707 | M41: =IF(IFERROR(H41/100,"")=0,"",IFERROR(H41/100,"")) | O41: 2008 q4 | P41: =AVERAGEIF($J$6:$J$297,$O41,K$6:K$297) -> 0.087888261 | Q41: =AVERAGEIF($J$6:$J$297,$O41,L$6:L$297) -> 0.094150656 | R41: =AVERAGE(R40,R42) -> 0.11727284 | S41: =R41-Q41 -> 0.023122184
A42: Հունվար 2003 | D42: 14.92 | E42: 14.89 | I42: 37622 | J42: =YEAR(I42)&" q"&ROUNDUP(MONTH(I42)/3,0) -> 2003 q1 | K42: =IFERROR(AVERAGE(B42:E42)/100,"") -> 0.14905 | L42: =IFERROR(AVERAGE(F42:G42)/100,"") | M42: =IF(IFERROR(H42/100,"")=0,"",IFERROR(H42/100,"")) | O42: 2009 q1 | P42: =AVERAGEIF($J$6:$J$297,$O42,K$6:K$297) -> 0.099619206 | Q42: =AVERAGEIF($J$6:$J$297,$O42,L$6:L$297) -> 0.1048655 | R42: =AVERAGEIF($J$6:$J$297,$O42,M$6:M$297) -> 0.128801 | S42: =R42-Q42 -> 0.0239355
A43: Փետրվար | D43: 12.1865 | E43: 12.832477 | I43: 37653 | J43: =YEAR(I43)&" q"&ROUNDUP(MONTH(I43)/3,0) -> 2003 q1 | K43: =IFERROR(AVERAGE(B43:E43)/100,"") -> 0.12509488 | L43: =IFERROR(AVERAGE(F43:G43)/100,"") | M43: =IF(IFERROR(H43/100,"")=0,"",IFERROR(H43/100,"")) | O43: 2009 q2 | P43: =AVERAGEIF($J$6:$J$297,$O43,K$6:K$297) -> 0.1095774 | Q43: =AVERAGEIF($J$6:$J$297,$O43,L$6:L$297) -> 0.13429757 | R43: =AVERAGEIF($J$6:$J$297,$O43,M$6:M$297) -> 0.155155 | S43: =R43-Q43 -> 0.020857434
A44: Մարտ | E44: 13.548067 | F44: 16.14635 | I44: 37681 | J44: =YEAR(I44)&" q"&ROUNDUP(MONTH(I44)/3,0) -> 2003 q1 | K44: =IFERROR(AVERAGE(B44:E44)/100,"") -> 0.13548067 | L44: =IFERROR(AVERAGE(F44:G44)/100,"") -> 0.1614635 | M44: =IF(IFERROR(H44/100,"")=0,"",IFERROR(H44/100,"")) | O44: 2009 q3 | P44: =AVERAGEIF($J$6:$J$297,$O44,K$6:K$297) -> 0.076035444 | Q44: =AVERAGEIF($J$6:$J$297,$O44,L$6:L$297) -> 0.1068077 | R44: =AVERAGEIF($J$6:$J$297,$O44,M$6:M$297) -> 0.133343 | S44: =R44-Q44 -> 0.026535305
A45: Ապրիլ | E45: 14.662182 | F45: 17.5684 | I45: 37712 | J45: =YEAR(I45)&" q"&ROUNDUP(MONTH(I45)/3,0) -> 2003 q2 | K45: =IFERROR(AVERAGE(B45:E45)/100,"") -> 0.14662182 | L45: =IFERROR(AVERAGE(F45:G45)/100,"") -> 0.175684 | M45: =IF(IFERROR(H45/100,"")=0,"",IFERROR(H45/100,"")) | O45: 2009 q4 | P45: =AVERAGEIF($J$6:$J$297,$O45,K$6:K$297) -> 0.082983184 | Q45: =AVERAGEIF($J$6:$J$297,$O45,L$6:L$297) -> 0.12842021 | R45: =AVERAGE(R44,R46) -> 0.14625086 | S45: =R45-Q45 -> 0.017830655
A46: Մայիս | D46: 13.9899 | E46: 13.5362 | F46: 16.2487 | I46: 37742 | J46: =YEAR(I46)&" q"&ROUNDUP(MONTH(I46)/3,0) -> 2003 q2 | K46: =IFERROR(AVERAGE(B46:E46)/100,"") -> 0.1376305 | L46: =IFERROR(AVERAGE(F46:G46)/100,"") -> 0.162487 | M46: =IF(IFERROR(H46/100,"")=0,"",IFERROR(H46/100,"")) | O46: 2010 q1 | P46: =AVERAGEIF($J$6:$J$297,$O46,K$6:K$297) -> 0.088015762 | Q46: =AVERAGEIF($J$6:$J$297,$O46,L$6:L$297) -> 0.13447813 | R46: =AVERAGEIF($J$6:$J$297,$O46,M$6:M$297) -> 0.15915873 | S46: =R46-Q46 -> 0.024680596
A47: Հունիս | E47: 11.8078 | F47: 15.8171 | I47: 37773 | J47: =YEAR(I47)&" q"&ROUNDUP(MONTH(I47)/3,0) -> 2003 q2 | K47: =IFERROR(AVERAGE(B47:E47)/100,"") -> 0.118078 | L47: =IFERROR(AVERAGE(F47:G47)/100,"") -> 0.158171 | M47: =IF(IFERROR(H47/100,"")=0,"",IFERROR(H47/100,"")) | O47: 2010 q2 | P47: =AVERAGEIF($J$6:$J$297,$O47,K$6:K$297) -> 0.11362408 | Q47: =AVERAGEIF($J$6:$J$297,$O47,L$6:L$297) -> 0.14493446 | R47: =AVERAGEIF($J$6:$J$297,$O47,M$6:M$297) -> 0.15120133 | S47: =R47-Q47 -> 0.0062668684
A48: Հուլիս | E48: 10.566359 | F48: 16.5046 | I48: 37803 | J48: =YEAR(I48)&" q"&ROUNDUP(MONTH(I48)/3,0) -> 2003 q3 | K48: =IFERROR(AVERAGE(B48:E48)/100,"") -> 0.10566359 | L48: =IFERROR(AVERAGE(F48:G48)/100,"") -> 0.165046 | M48: =IF(IFERROR(H48/100,"")=0,"",IFERROR(H48/100,"")) | O48: 2010 q3 | P48: =AVERAGEIF($J$6:$J$297,$O48,K$6:K$297) -> 0.098185386 | Q48: =AVERAGEIF($J$6:$J$297,$O48,L$6:L$297) -> 0.13485467 | R48: =AVERAGEIF($J$6:$J$297,$O48,M$6:M$297) -> 0.15950542 | S48: =R48-Q48 -> 0.024650755
A49: Օգոստոս | D49: 10.3412 | E49: 10.645087 | I49: 37834 | J49: =YEAR(I49)&" q"&ROUNDUP(MONTH(I49)/3,0) -> 2003 q3 | K49: =IFERROR(AVERAGE(B49:E49)/100,"") -> 0.10493143 | L49: =IFERROR(AVERAGE(F49:G49)/100,"") | M49: =IF(IFERROR(H49/100,"")=0,"",IFERROR(H49/100,"")) | O49: 2010 q4 | P49: =AVERAGEIF($J$6:$J$297,$O49,K$6:K$297) -> 0.092965919 | Q49: =AVERAGEIF($J$6:$J$297,$O49,L$6:L$297) -> 0.14376067 | R49: =AVERAGE(R48,R50) -> 0.15655559 | S49: =R49-Q49 -> 0.012794919
A50: Սեպտեմբեր | E50: 10.506404 | F50: 15.219457 | I50: 37865 | J50: =YEAR(I50)&" q"&ROUNDUP(MONTH(I50)/3,0) -> 2003 q3 | K50: =IFERROR(AVERAGE(B50:E50)/100,"") -> 0.10506404 | L50: =IFERROR(AVERAGE(F50:G50)/100,"") -> 0.15219457 | M50: =IF(IFERROR(H50/100,"")=0,"",IFERROR(H50/100,"")) | O50: 2011 q1 | P50: =AVERAGEIF($J$6:$J$297,$O50,K$6:K$297) -> 0.080862202 | Q50: =AVERAGEIF($J$6:$J$297,$O50,L$6:L$297) -> 0.136819 | R50: =AVERAGEIF($J$6:$J$297,$O50,M$6:M$297) -> 0.15360575 | S50: =R50-Q50 -> 0.01678675
A51: Հոկտեմբեր | E51: 10.121 | F51: 0 | I51: 37895 | J51: =YEAR(I51)&" q"&ROUNDUP(MONTH(I51)/3,0) -> 2003 q4 | K51: =IFERROR(AVERAGE(B51:E51)/100,"") -> 0.10121 | L51: =IFERROR(AVERAGE(F51:G51)/100,"") -> 0 | M51: =IF(IFERROR(H51/100,"")=0,"",IFERROR(H51/100,"")) | O51: 2011 q2 | P51: =AVERAGEIF($J$6:$J$297,$O51,K$6:K$297) -> 0.092917623 | Q51: =AVERAGEIF($J$6:$J$297,$O51,L$6:L$297) -> 0.13870375 | R51: =AVERAGEIF($J$6:$J$297,$O51,M$6:M$297) -> 0.15454939 | S51: =R51-Q51 -> 0.015845637
A52: Նոյեմբեր | E52: 10.136333 | F52: 14.2963 | I52: 37926 | J52: =YEAR(I52)&" q"&ROUNDUP(MONTH(I52)/3,0) -> 2003 q4 | K52: =IFERROR(AVERAGE(B52:E52)/100,"") -> 0.10136333 | L52: =IFERROR(AVERAGE(F52:G52)/100,"") -> 0.142963 | M52: =IF(IFERROR(H52/100,"")=0,"",IFERROR(H52/100,"")) | O52: 2011 q3 | P52: =AVERAGEIF($J$6:$J$297,$O52,K$6:K$297) -> 0.081242333 | Q52: =AVERAGEIF($J$6:$J$297,$O52,L$6:L$297) -> 0.13785461 | R52: =AVERAGEIF($J$6:$J$297,$O52,M$6:M$297) -> 0.15517225 | S52: =R52-Q52 -> 0.017317637
A53: Դեկտեմբեր | E53: 9.6844 | I53: 37956 | J53: =YEAR(I53)&" q"&ROUNDUP(MONTH(I53)/3,0) -> 2003 q4 | K53: =IFERROR(AVERAGE(B53:E53)/100,"") -> 0.096844 | L53: =IFERROR(AVERAGE(F53:G53)/100,"") | M53: =IF(IFERROR(H53/100,"")=0,"",IFERROR(H53/100,"")) | O53: 2011 q4 | P53: =AVERAGEIF($J$6:$J$297,$O53,K$6:K$297) -> 0.092404938 | Q53: =AVERAGEIF($J$6:$J$297,$O53,L$6:L$297) -> 0.13854375 | R53: =AVERAGEIF($J$6:$J$297,$O53,M$6:M$297) -> 0.1582825 | S53: =R53-Q53 -> 0.01973875
A54: Հունվար 2004 | E54: 7.5335 | I54: 37987 | J54: =YEAR(I54)&" q"&ROUNDUP(MONTH(I54)/3,0) -> 2004 q1 | K54: =IFERROR(AVERAGE(B54:E54)/100,"") -> 0.075335 | L54: =IFERROR(AVERAGE(F54:G54)/100,"") | M54: =IF(IFERROR(H54/100,"")=0,"",IFERROR(H54/100,"")) | O54: 2012 q1 | P54: =AVERAGEIF($J$6:$J$297,$O54,K$6:K$297) -> 0.093738806 | Q54: =AVERAGEIF($J$6:$J$297,$O54,L$6:L$297) -> 0.1398555 | R54: =AVERAGEIF($J$6:$J$297,$O54,M$6:M$297) -> 0.157528 | S54: =R54-Q54 -> 0.017672499
A55: Փետրվար | E55: 6.37235 | F55: 9.6565 | I55: 38018 | J55: =YEAR(I55)&" q"&ROUNDUP(MONTH(I55)/3,0) -> 2004 q1 | K55: =IFERROR(AVERAGE(B55:E55)/100,"") -> 0.0637235 | L55: =IFERROR(AVERAGE(F55:G55)/100,"") -> 0.096565 | M55: =IF(IFERROR(H55/100,"")=0,"",IFERROR(H55/100,"")) | O55: 2012 q2 | P55: =AVERAGEIF($J$6:$J$297,$O55,K$6:K$297) -> 0.087835972 | Q55: =AVERAGEIF($J$6:$J$297,$O55,L$6:L$297) -> 0.14122807 | R55: =AVERAGEIF($J$6:$J$297,$O55,M$6:M$297) -> 0.15788217 | S55: =R55-Q55 -> 0.016654101
A56: Մարտ | E56: 5.9499667 | F56: 9.7845 | I56: 38047 | J56: =YEAR(I56)&" q"&ROUNDUP(MONTH(I56)/3,0) -> 2004 q1 | K56: =IFERROR(AVERAGE(B56:E56)/100,"") -> 0.059499667 | L56: =IFERROR(AVERAGE(F56:G56)/100,"") -> 0.097845 | M56: =IF(IFERROR(H56/100,"")=0,"",IFERROR(H56/100,"")) | O56: 2012 q3 | P56: =AVERAGEIF($J$6:$J$297,$O56,K$6:K$297) -> 0.092521111 | Q56: =AVERAGEIF($J$6:$J$297,$O56,L$6:L$297) -> 0.14558145 | R56: =AVERAGEIF($J$6:$J$297,$O56,M$6:M$297) -> 0.15855764 | S56: =R56-Q56 -> 0.012976188
A57: Ապրիլ | E57: 5.8133 | F57: 9.6607 | I57: 38078 | J57: =YEAR(I57)&" q"&ROUNDUP(MONTH(I57)/3,0) -> 2004 q2 | K57: =IFERROR(AVERAGE(B57:E57)/100,"") -> 0.058133 | L57: =IFERROR(AVERAGE(F57:G57)/100,"") -> 0.096607 | M57: =IF(IFERROR(H57/100,"")=0,"",IFERROR(H57/100,"")) | O57: 2012 q4 | P57: =AVERAGEIF($J$6:$J$297,$O57,K$6:K$297) -> 0.099569667 | Q57: =AVERAGEIF($J$6:$J$297,$O57,L$6:L$297) -> 0.14534317 | R57: =AVERAGEIF($J$6:$J$297,$O57,M$6:M$297) -> 0.15882378 | S57: =R57-Q57 -> 0.013480609
A58: Մայիս | E58: 5.8139 | F58: 9.3629 | I58: 38108 | J58: =YEAR(I58)&" q"&ROUNDUP(MONTH(I58)/3,0) -> 2004 q2 | K58: =IFERROR(AVERAGE(B58:E58)/100,"") -> 0.058139 | L58: =IFERROR(AVERAGE(F58:G58)/100,"") -> 0.093629 | M58: =IF(IFERROR(H58/100,"")=0,"",IFERROR(H58/100,"")) | O58: 2013 q1 | P58: =AVERAGEIF($J$6:$J$297,$O58,K$6:K$297) -> 0.0952975 | Q58: =AVERAGEIF($J$6:$J$297,$O58,L$6:L$297) -> 0.14777367 | R58: =AVERAGEIF($J$6:$J$297,$O58,M$6:M$297) -> 0.161998 | S58: =R58-Q58 -> 0.014224333
A59: Հունիս | E59: 5.2566 | F59: 8.392 | I59: 38139 | J59: =YEAR(I59)&" q"&ROUNDUP(MONTH(I59)/3,0) -> 2004 q2 | K59: =IFERROR(AVERAGE(B59:E59)/100,"") -> 0.052566 | L59: =IFERROR(AVERAGE(F59:G59)/100,"") -> 0.08392 | M59: =IF(IFERROR(H59/100,"")=0,"",IFERROR(H59/100,"")) | O59: 2013 q2 | P59: =AVERAGEIF($J$6:$J$297,$O59,K$6:K$297) -> 0.090943931 | Q59: =AVERAGEIF($J$6:$J$297,$O59,L$6:L$297) -> 0.13692447 | R59: =AVERAGEIF($J$6:$J$297,$O59,M$6:M$297) -> 0.15633 | S59: =R59-Q59 -> 0.019405533
A60: Հուլիս | E60: 4.81075 | F60: 7.1522387 | I60: 38169 | J60: =YEAR(I60)&" q"&ROUNDUP(MONTH(I60)/3,0) -> 2004 q3 | K60: =IFERROR(AVERAGE(B60:E60)/100,"") -> 0.0481075 | L60: =IFERROR(AVERAGE(F60:G60)/100,"") -> 0.071522387 | M60: =IF(IFERROR(H60/100,"")=0,"",IFERROR(H60/100,"")) | O60: 2013 q3 | P60: =AVERAGEIF($J$6:$J$297,$O60,K$6:K$297) -> 0.089356 | Q60: =AVERAGEIF($J$6:$J$297,$O60,L$6:L$297) -> 0.1327325 | R60: =AVERAGEIF($J$6:$J$297,$O60,M$6:M$297) -> 0.1496305 | S60: =R60-Q60 -> 0.016898
A61: Օգոստոս | E61: 5.1449667 | F61: 7.4996571 | I61: 38200 | J61: =YEAR(I61)&" q"&ROUNDUP(MONTH(I61)/3,0) -> 2004 q3 | K61: =IFERROR(AVERAGE(B61:E61)/100,"") -> 0.051449667 | L61: =IFERROR(AVERAGE(F61:G61)/100,"") -> 0.074996571 | M61: =IF(IFERROR(H61/100,"")=0,"",IFERROR(H61/100,"")) | O61: 2013 q4 | P61: =AVERAGEIF($J$6:$J$297,$O61,K$6:K$297) -> 0.085680972 | Q61: =AVERAGEIF($J$6:$J$297,$O61,L$6:L$297) -> 0.11070606 | R61: =AVERAGEIF($J$6:$J$297,$O61,M$6:M$297) -> 0.116385 | S61: =R61-Q61 -> 0.0056789447
A62: Սեպտեմբեր | E62: 5.0219 | F62: 7.2977 | H62: 9.2446 | I62: 38231 | J62: =YEAR(I62)&" q"&ROUNDUP(MONTH(I62)/3,0) -> 2004 q3 | K62: =IFERROR(AVERAGE(B62:E62)/100,"") -> 0.050219 | L62: =IFERROR(AVERAGE(F62:G62)/100,"") -> 0.072977 | M62: =IF(IFERROR(H62/100,"")=0,"",IFERROR(H62/100,"")) -> 0.092446 | O62: 2014 q1 | P62: =AVERAGEIF($J$6:$J$297,$O62,K$6:K$297) -> 0.079597111 | Q62: =AVERAGEIF($J$6:$J$297,$O62,L$6:L$297) -> 0.0959155 | R62: =AVERAGEIF($J$6:$J$297,$O62,M$6:M$297) -> 0.109932 | S62: =R62-Q62 -> 0.0140165
A63: Հոկտեմբեր | B63: 3.988075 | F63: 7.2444 | G63: 7.1082 | I63: 38261 | J63: =YEAR(I63)&" q"&ROUNDUP(MONTH(I63)/3,0) -> 2004 q4 | K63: =IFERROR(AVERAGE(B63:E63)/100,"") -> 0.03988075 | L63: =IFERROR(AVERAGE(F63:G63)/100,"") -> 0.071763 | M63: =IF(IFERROR(H63/100,"")=0,"",IFERROR(H63/100,"")) | O63: 2014 q2 | P63: =AVERAGEIF($J$6:$J$297,$O63,K$6:K$297) -> 0.078375194 | Q63: =AVERAGEIF($J$6:$J$297,$O63,L$6:L$297) -> 0.099352667 | R63: =AVERAGEIF($J$6:$J$297,$O63,M$6:M$297) -> 0.115413 | S63: =R63-Q63 -> 0.016060333
A64: Նոյեմբեր | B64: 4.0093667 | F64: 7.1321 | I64: 38292 | J64: =YEAR(I64)&" q"&ROUNDUP(MONTH(I64)/3,0) -> 2004 q4 | K64: =IFERROR(AVERAGE(B64:E64)/100,"") -> 0.040093667 | L64: =IFERROR(AVERAGE(F64:G64)/100,"") -> 0.071321 | M64: =IF(IFERROR(H64/100,"")=0,"",IFERROR(H64/100,"")) | O64: 2014 q3 | P64: =AVERAGEIF($J$6:$J$297,$O64,K$6:K$297) -> 0.074414926 | Q64: =AVERAGEIF($J$6:$J$297,$O64,L$6:L$297) -> 0.098519833 | R64: =AVERAGEIF($J$6:$J$297,$O64,M$6:M$297) -> 0.1159765 | S64: =R64-Q64 -> 0.017456667
A65: Դեկտեմբեր | F65: 5.6002 | H65: 9.2683 | I65: 38322 | J65: =YEAR(I65)&" q"&ROUNDUP(MONTH(I65)/3,0) -> 2004 q4 | K65: =IFERROR(AVERAGE(B65:E65)/100,"") | L65: =IFERROR(AVERAGE(F65:G65)/100,"") -> 0.056002 | M65: =IF(IFERROR(H65/100,"")=0,"",IFERROR(H65/100,"")) -> 0.092683 | O65: 2014 q4 | P65: =AVERAGEIF($J$6:$J$297,$O65,K$6:K$297) -> 0.07093775 | Q65: =AVERAGEIF($J$6:$J$297,$O65,L$6:L$297) -> 0.099113 | R65: =AVERAGEIF($J$6:$J$297,$O65,M$6:M$297) -> 0.121495 | S65: =R65-Q65 -> 0.022382
A66: Հունվար 2005 | C66: 4.3126667 | F66: 5.9506 | I66: 38353 | J66: =YEAR(I66)&" q"&ROUNDUP(MONTH(I66)/3,0) -> 2005 q1 | K66: =IFERROR(AVERAGE(B66:E66)/100,"") -> 0.043126667 | L66: =IFERROR(AVERAGE(F66:G66)/100,"") -> 0.059506 | M66: =IF(IFERROR(H66/100,"")=0,"",IFERROR(H66/100,"")) | O66: 2015 q1 | P66: =AVERAGEIF($J$6:$J$297,$O66,K$6:K$297) -> 0.14423377 | Q66: =AVERAGEIF($J$6:$J$297,$O66,L$6:L$297) -> 0.140466 | R66: =AVERAGEIF($J$6:$J$297,$O66,M$6:M$297) -> 0.160103 | S66: =R66-Q66 -> 0.019637
A67: Փետրվար | C67: 4.1896 | E67: 4.287 | F67: 4.5536 | G67: 5.8398 | I67: 38384 | J67: =YEAR(I67)&" q"&ROUNDUP(MONTH(I67)/3,0) -> 2005 q1 | K67: =IFERROR(AVERAGE(B67:E67)/100,"") -> 0.042383 | L67: =IFERROR(AVERAGE(F67:G67)/100,"") -> 0.051967 | M67: =IF(IFERROR(H67/100,"")=0,"",IFERROR(H67/100,"")) | O67: 2015 q2 | P67: =AVERAGEIF($J$6:$J$297,$O67,K$6:K$297) -> 0.12574417 | Q67: =AVERAGEIF($J$6:$J$297,$O67,L$6:L$297) -> 0.14336056 | R67: =AVERAGEIF($J$6:$J$297,$O67,M$6:M$297) -> 0.15966536 | S67: =R67-Q67 -> 0.016304806
A68: Մարտ | D68: 3.7442 | E68: 3.8886 | F68: 4.6143 | H68: 6.93 | I68: 38412 | J68: =YEAR(I68)&" q"&ROUNDUP(MONTH(I68)/3,0) -> 2005 q1 | K68: =IFERROR(AVERAGE(B68:E68)/100,"") -> 0.038164 | L68: =IFERROR(AVERAGE(F68:G68)/100,"") -> 0.046143 | M68: =IF(IFERROR(H68/100,"")=0,"",IFERROR(H68/100,"")) -> 0.0693 | O68: 2015 q3 | P68: =AVERAGEIF($J$6:$J$297,$O68,K$6:K$297) -> 0.11903283 | Q68: =AVERAGEIF($J$6:$J$297,$O68,L$6:L$297) -> 0.144287 | R68: =AVERAGEIF($J$6:$J$297,$O68,M$6:M$297) -> 0.1594935 | S68: =R68-Q68 -> 0.0152065
A69: Ապրիլ | B69: 3.7658 | C69: 4.1844 | D69: 4.5196 | E69: 3.6936 | F69: 5.2626 | G69: 5.4479 | I69: 38443 | J69: =YEAR(I69)&" q"&ROUNDUP(MONTH(I69)/3,0) -> 2005 q2 | K69: =IFERROR(AVERAGE(B69:E69)/100,"") -> 0.0404085 | L69: =IFERROR(AVERAGE(F69:G69)/100,"") -> 0.0535525 | M69: =IF(IFERROR(H69/100,"")=0,"",IFERROR(H69/100,"")) | O69: 2015 q4 | P69: =AVERAGEIF($J$6:$J$297,$O69,K$6:K$297) -> 0.11904289 | Q69: =AVERAGEIF($J$6:$J$297,$O69,L$6:L$297) -> 0.14828833 | R69: =AVERAGEIF($J$6:$J$297,$O69,M$6:M$297) -> 0.16413816 | S69: =R69-Q69 -> 0.01584983
A70: Մայիս | C70: 4.875137 | D70: 5.0266 | E70: 4.8813 | F70: 4.9494 | H70: 6.6771 | I70: 38473 | J70: =YEAR(I70)&" q"&ROUNDUP(MONTH(I70)/3,0) -> 2005 q2 | K70: =IFERROR(AVERAGE(B70:E70)/100,"") -> 0.04927679 | L70: =IFERROR(AVERAGE(F70:G70)/100,"") -> 0.049494 | M70: =IF(IFERROR(H70/100,"")=0,"",IFERROR(H70/100,"")) -> 0.066771 | O70: 2016 q1 | P70: =AVERAGEIF($J$6:$J$297,$O70,K$6:K$297) -> 0.1105226 | Q70: =AVERAGEIF($J$6:$J$297,$O70,L$6:L$297) -> 0.1450526 | R70: =AVERAGEIF($J$6:$J$297,$O70,M$6:M$297) -> 0.163271 | S70: =R70-Q70 -> 0.018218405
A71: Հունիս | C71: 4.6601 | D71: 4.9231 | F71: 5.7351 | H71: 8.0632 | I71: 38504 | J71: =YEAR(I71)&" q"&ROUNDUP(MONTH(I71)/3,0) -> 2005 q2 | K71: =IFERROR(AVERAGE(B71:E71)/100,"") -> 0.047916 | L71: =IFERROR(AVERAGE(F71:G71)/100,"") -> 0.057351 | M71: =IF(IFERROR(H71/100,"")=0,"",IFERROR(H71/100,"")) -> 0.080632 | O71: 2016 q2 | P71: =AVERAGEIF($J$6:$J$297,$O71,K$6:K$297) -> 0.099144444 | Q71: =AVERAGEIF($J$6:$J$297,$O71,L$6:L$297) -> 0.13779384 | R71: =AVERAGEIF($J$6:$J$297,$O71,M$6:M$297) -> 0.16350406 | S71: =R71-Q71 -> 0.025710218
A72: Հուլիս | C72: 4.0706 | F72: 5.3221 | H72: 4.8581 | I72: 38534 | J72: =YEAR(I72)&" q"&ROUNDUP(MONTH(I72)/3,0) -> 2005 q3 | K72: =IFERROR(AVERAGE(B72:E72)/100,"") -> 0.040706 | L72: =IFERROR(AVERAGE(F72:G72)/100,"") -> 0.053221 | M72: =IF(IFERROR(H72/100,"")=0,"",IFERROR(H72/100,"")) -> 0.048581 | O72: 2016 q3 | P72: =AVERAGEIF($J$6:$J$297,$O72,K$6:K$297) -> 0.083952875 | Q72: =AVERAGEIF($J$6:$J$297,$O72,L$6:L$297) -> 0.11104473 | R72: =AVERAGEIF($J$6:$J$297,$O72,M$6:M$297) -> 0.1360185 | S72: =R72-Q72 -> 0.024973767
A73: Օգոստոս | D73: 3.3685 | E73: 3.2418 | F73: 5.0597 | I73: 38565 | J73: =YEAR(I73)&" q"&ROUNDUP(MONTH(I73)/3,0) -> 2005 q3 | K73: =IFERROR(AVERAGE(B73:E73)/100,"") -> 0.0330515 | L73: =IFERROR(AVERAGE(F73:G73)/100,"") -> 0.050597 | M73: =IF(IFERROR(H73/100,"")=0,"",IFERROR(H73/100,"")) | O73: 2016 q4 | P73: =AVERAGEIF($J$6:$J$297,$O73,K$6:K$297) -> 0.071713352 | Q73: =AVERAGEIF($J$6:$J$297,$O73,L$6:L$297) -> 0.10070533 | R73: =AVERAGEIF($J$6:$J$297,$O73,M$6:M$297) -> 0.12836267 | S73: =R73-Q73 -> 0.027657333
A74: Սեպտեմբեր | E74: 3.8130333 | H74: 5.9 | I74: 38596 | J74: =YEAR(I74)&" q"&ROUNDUP(MONTH(I74)/3,0) -> 2005 q3 | K74: =IFERROR(AVERAGE(B74:E74)/100,"") -> 0.038130333 | L74: =IFERROR(AVERAGE(F74:G74)/100,"") | M74: =IF(IFERROR(H74/100,"")=0,"",IFERROR(H74/100,"")) -> 0.059 | O74: 2017 q1 | P74: =AVERAGEIF($J$6:$J$297,$O74,K$6:K$297) -> 0.069584444 | Q74: =AVERAGEIF($J$6:$J$297,$O74,L$6:L$297) -> 0.099613167 | R74: =AVERAGEIF($J$6:$J$297,$O74,M$6:M$297) -> 0.1253435 | S74: =R74-Q74 -> 0.025730333
A75: Հոկտեմբեր | C75: 3.6913 | E75: 3.8566 | G75: 5.2879 | I75: 38626 | J75: =YEAR(I75)&" q"&ROUNDUP(MONTH(I75)/3,0) -> 2005 q4 | K75: =IFERROR(AVERAGE(B75:E75)/100,"") -> 0.0377395 | L75: =IFERROR(AVERAGE(F75:G75)/100,"") -> 0.052879 | M75: =IF(IFERROR(H75/100,"")=0,"",IFERROR(H75/100,"")) | O75: 2017 q2 | P75: =AVERAGEIF($J$6:$J$297,$O75,K$6:K$297) -> 0.064473667 | Q75: =AVERAGEIF($J$6:$J$297,$O75,L$6:L$297) -> 0.088082474 | R75: =AVERAGEIF($J$6:$J$297,$O75,M$6:M$297) -> 0.12114 | S75: =R75-Q75 -> 0.033057526
A76: Նոյեմբեր | D76: 3.6798 | E76: 3.806 | F76: 5.0858 | I76: 38657 | J76: =YEAR(I76)&" q"&ROUNDUP(MONTH(I76)/3,0) -> 2005 q4 | K76: =IFERROR(AVERAGE(B76:E76)/100,"") -> 0.037429 | L76: =IFERROR(AVERAGE(F76:G76)/100,"") -> 0.050858 | M76: =IF(IFERROR(H76/100,"")=0,"",IFERROR(H76/100,"")) | O76: 2017 q3 | P76: =AVERAGEIF($J$6:$J$297,$O76,K$6:K$297) -> 0.061384444 | Q76: =AVERAGEIF($J$6:$J$297,$O76,L$6:L$297) -> 0.08416417 | R76: =AVERAGEIF($J$6:$J$297,$O76,M$6:M$297) -> 0.100299 | S76: =R76-Q76 -> 0.01613483
A77: Դեկտեմբեր | H77: 8.8226 | I77: 38687 | J77: =YEAR(I77)&" q"&ROUNDUP(MONTH(I77)/3,0) -> 2005 q4 | K77: =IFERROR(AVERAGE(B77:E77)/100,"") | L77: =IFERROR(AVERAGE(F77:G77)/100,"") | M77: =IF(IFERROR(H77/100,"")=0,"",IFERROR(H77/100,"")) -> 0.088226 | O77: 2017 q4 | P77: =AVERAGEIF($J$6:$J$297,$O77,K$6:K$297) -> 0.059343167 | Q77: =AVERAGEIF($J$6:$J$297,$O77,L$6:L$297) -> 0.079013575 | R77: =AVERAGEIF($J$6:$J$297,$O77,M$6:M$297) -> 0.098999 | S77: =R77-Q77 -> 0.019985425
A78: Հունվար 2006 | F78: 4.9396 | I78: 38718 | J78: =YEAR(I78)&" q"&ROUNDUP(MONTH(I78)/3,0) -> 2006 q1 | K78: =IFERROR(AVERAGE(B78:E78)/100,"") | L78: =IFERROR(AVERAGE(F78:G78)/100,"") -> 0.049396 | M78: =IF(IFERROR(H78/100,"")=0,"",IFERROR(H78/100,"")) | O78: 2018 q1 | P78: =AVERAGEIF($J$6:$J$297,$O78,K$6:K$297) -> 0.060449833 | Q78: =AVERAGEIF($J$6:$J$297,$O78,L$6:L$297) -> 0.076176 | R78: =AVERAGEIF($J$6:$J$297,$O78,M$6:M$297) -> 0.122891 | S78: =R78-Q78 -> 0.046715
A79: Փետրվար | C79: 3.9659 | E79: 4.2264 | F79: 4.9133 | I79: 38749 | J79: =YEAR(I79)&" q"&ROUNDUP(MONTH(I79)/3,0) -> 2006 q1 | K79: =IFERROR(AVERAGE(B79:E79)/100,"") -> 0.0409615 | L79: =IFERROR(AVERAGE(F79:G79)/100,"") -> 0.049133 | M79: =IF(IFERROR(H79/100,"")=0,"",IFERROR(H79/100,"")) | O79: 2018 q2 | P79: =AVERAGEIF($J$6:$J$297,$O79,K$6:K$297) -> 0.061320333 | Q79: =AVERAGEIF($J$6:$J$297,$O79,L$6:L$297) -> 0.083643 | R79: =AVERAGEIF($J$6:$J$297,$O79,M$6:M$297) -> 0.093041 | S79: =R79-Q79 -> 0.009398
A80: Մարտ | E80: 4.3155 | F80: 4.8792 | H80: 8.5825543 | I80: 38777 | J80: =YEAR(I80)&" q"&ROUNDUP(MONTH(I80)/3,0) -> 2006 q1 | K80: =IFERROR(AVERAGE(B80:E80)/100,"") -> 0.043155 | L80: =IFERROR(AVERAGE(F80:G80)/100,"") -> 0.048792 | M80: =IF(IFERROR(H80/100,"")=0,"",IFERROR(H80/100,"")) -> 0.085825543 | O80: 2018 q3 | P80: =AVERAGEIF($J$6:$J$297,$O80,K$6:K$297) -> 0.061875389 | Q80: =AVERAGEIF($J$6:$J$297,$O80,L$6:L$297) -> 0.082392 | R80: =AVERAGEIF($J$6:$J$297,$O80,M$6:M$297) -> 0.113743 | S80: =R80-Q80 -> 0.031351
A81: Ապրիլ | D81: 4.4424 | E81: 4.8556 | G81: 6.5267 | I81: 38808 | J81: =YEAR(I81)&" q"&ROUNDUP(MONTH(I81)/3,0) -> 2006 q2 | K81: =IFERROR(AVERAGE(B81:E81)/100,"") -> 0.04649 | L81: =IFERROR(AVERAGE(F81:G81)/100,"") -> 0.065267 | M81: =IF(IFERROR(H81/100,"")=0,"",IFERROR(H81/100,"")) | O81: 2018 q4 | P81: =AVERAGEIF($J$6:$J$297,$O81,K$6:K$297) -> 0.061693639 | Q81: =AVERAGEIF($J$6:$J$297,$O81,L$6:L$297) -> 0.081789 | R81: =AVERAGEIF($J$6:$J$297,$O81,M$6:M$297) -> 0.092475 | S81: =R81-Q81 -> 0.010686
A82: Մայիս | E82: 4.9216797 | G82: 6.776 | I82: 38838 | J82: =YEAR(I82)&" q"&ROUNDUP(MONTH(I82)/3,0) -> 2006 q2 | K82: =IFERROR(AVERAGE(B82:E82)/100,"") -> 0.049216797 | L82: =IFERROR(AVERAGE(F82:G82)/100,"") -> 0.06776 | M82: =IF(IFERROR(H82/100,"")=0,"",IFERROR(H82/100,"")) | O82: 2019 q1 | P82: =AVERAGEIF($J$6:$J$297,$O82,K$6:K$297) -> 0.061574778 | Q82: =AVERAGEIF($J$6:$J$297,$O82,L$6:L$297) -> 0.083415 | R82: =AVERAGEIF($J$6:$J$297,$O82,M$6:M$297) -> 0.097418 | S82: =R82-Q82 -> 0.014003
A83: Հունիս | D83: 4.9126 | F83: 6.0654 | H83: 9.878 | I83: 38869 | J83: =YEAR(I83)&" q"&ROUNDUP(MONTH(I83)/3,0) -> 2006 q2 | K83: =IFERROR(AVERAGE(B83:E83)/100,"") -> 0.049126 | L83: =IFERROR(AVERAGE(F83:G83)/100,"") -> 0.060654 | M83: =IF(IFERROR(H83/100,"")=0,"",IFERROR(H83/100,"")) -> 0.09878 | O83: 2019 q2 | P83: =AVERAGEIF($J$6:$J$297,$O83,K$6:K$297) -> 0.059476744 | Q83: =AVERAGEIF($J$6:$J$297,$O83,L$6:L$297) -> 0.078354 | R83: =AVERAGEIF($J$6:$J$297,$O83,M$6:M$297) -> 0.116442 | S83: =R83-Q83 -> 0.038088
A84: Հուլիս | C84: 4.8115 | E84: 4.9252 | G84: 6.7112 | I84: 38899 | J84: =YEAR(I84)&" q"&ROUNDUP(MONTH(I84)/3,0) -> 2006 q3 | K84: =IFERROR(AVERAGE(B84:E84)/100,"") -> 0.0486835 | L84: =IFERROR(AVERAGE(F84:G84)/100,"") -> 0.067112 | M84: =IF(IFERROR(H84/100,"")=0,"",IFERROR(H84/100,"")) | O84: 2019 q3 | P84: =AVERAGEIF($J$6:$J$297,$O84,K$6:K$297) -> 0.059088083 | Q84: =AVERAGEIF($J$6:$J$297,$O84,L$6:L$297) -> 0.075621 | R84: =AVERAGEIF($J$6:$J$297,$O84,M$6:M$297) -> 0.096749 | S84: =R84-Q84 -> 0.021128
A85: Օգոստոս | C85: 4.9685 | D85: 4.9669 | G85: 6.7639 | I85: 38930 | J85: =YEAR(I85)&" q"&ROUNDUP(MONTH(I85)/3,0) -> 2006 q3 | K85: =IFERROR(AVERAGE(B85:E85)/100,"") -> 0.049677 | L85: =IFERROR(AVERAGE(F85:G85)/100,"") -> 0.067639 | M85: =IF(IFERROR(H85/100,"")=0,"",IFERROR(H85/100,"")) | O85: 2019 q4 | P85: =AVERAGEIF($J$6:$J$297,$O85,K$6:K$297) -> 0.0567185 | Q85: =AVERAGEIF($J$6:$J$297,$O85,L$6:L$297) -> 0.0682585 | R85: =AVERAGEIF($J$6:$J$297,$O85,M$6:M$297) -> 0.109021 | S85: =R85-Q85 -> 0.0407625
A86: Սեպտեմբեր | D86: 4.9825 | E86: 4.9448018 | F86: 5.9557597 | H86: 9.5756162 | I86: 38961 | J86: =YEAR(I86)&" q"&ROUNDUP(MONTH(I86)/3,0) -> 2006 q3 | K86: =IFERROR(AVERAGE(B86:E86)/100,"") -> 0.049636509 | L86: =IFERROR(AVERAGE(F86:G86)/100,"") -> 0.059557597 | M86: =IF(IFERROR(H86/100,"")=0,"",IFERROR(H86/100,"")) -> 0.095756162 | O86: 2020 q1 | P86: =AVERAGEIF($J$6:$J$297,$O86,K$6:K$297) -> 0.05586892 | Q86: =AVERAGEIF($J$6:$J$297,$O86,L$6:L$297) -> 0.0646055 | R86: =AVERAGEIF($J$6:$J$297,$O86,M$6:M$297) -> 0.081011 | S86: =R86-Q86 -> 0.0164055
A87: Հոկտեմբեր | C87: 5 | D87: 4.9977162 | E87: 4.9999068 | G87: 6.7539 | I87: 38991 | J87: =YEAR(I87)&" q"&ROUNDUP(MONTH(I87)/3,0) -> 2006 q4 | K87: =IFERROR(AVERAGE(B87:E87)/100,"") -> 0.049992077 | L87: =IFERROR(AVERAGE(F87:G87)/100,"") -> 0.067539 | M87: =IF(IFERROR(H87/100,"")=0,"",IFERROR(H87/100,"")) | O87: 2020 q2 | P87: =AVERAGEIF($J$6:$J$297,$O87,K$6:K$297) -> 0.057161909 | Q87: =AVERAGEIF($J$6:$J$297,$O87,L$6:L$297) -> 0.06892707 | R87: =AVERAGEIF($J$6:$J$297,$O87,M$6:M$297) -> 0.093685052 | S87: =R87-Q87 -> 0.024757981
A88: Նոյեմբեր | B88: 5.81685 | E88: 5 | G88: 6.808 | I88: 39022 | J88: =YEAR(I88)&" q"&ROUNDUP(MONTH(I88)/3,0) -> 2006 q4 | K88: =IFERROR(AVERAGE(B88:E88)/100,"") -> 0.05408425 | L88: =IFERROR(AVERAGE(F88:G88)/100,"") -> 0.06808 | M88: =IF(IFERROR(H88/100,"")=0,"",IFERROR(H88/100,"")) | O88: 2020 q3 | P88: =AVERAGEIF($J$6:$J$297,$O88,K$6:K$297) -> 0.055652243 | Q88: =AVERAGEIF($J$6:$J$297,$O88,L$6:L$297) -> 0.066683295 | R88: =AVERAGEIF($J$6:$J$297,$O88,M$6:M$297) -> 0.079247801 | S88: =R88-Q88 -> 0.012564507
A89: Դեկտեմբեր | B89: 6.0426 | F89: 6.4964 | H89: 9.3692 | I89: 39052 | J89: =YEAR(I89)&" q"&ROUNDUP(MONTH(I89)/3,0) -> 2006 q4 | K89: =IFERROR(AVERAGE(B89:E89)/100,"") -> 0.060426 | L89: =IFERROR(AVERAGE(F89:G89)/100,"") -> 0.064964 | M89: =IF(IFERROR(H89/100,"")=0,"",IFERROR(H89/100,"")) -> 0.093692 | O89: 2020 q4 | P89: =AVERAGEIF($J$6:$J$297,$O89,K$6:K$297) -> 0.059642677 | Q89: =AVERAGEIF($J$6:$J$297,$O89,L$6:L$297) -> 0.073491744 | R89: =AVERAGEIF($J$6:$J$297,$O89,M$6:M$297) -> 0.090678439 | S89: =R89-Q89 -> 0.017186695
A90: Հունվար 2007 | E90: 5.9496 | G90: 7.1309 | I90: 39083 | J90: =YEAR(I90)&" q"&ROUNDUP(MONTH(I90)/3,0) -> 2007 q1 | K90: =IFERROR(AVERAGE(B90:E90)/100,"") -> 0.059496 | L90: =IFERROR(AVERAGE(F90:G90)/100,"") -> 0.071309 | M90: =IF(IFERROR(H90/100,"")=0,"",IFERROR(H90/100,"")) | O90: 2021 q1 | P90: =AVERAGEIF($J$6:$J$297,$O90,K$6:K$297) -> 0.067318911 | Q90: =AVERAGEIF($J$6:$J$297,$O90,L$6:L$297) -> 0.0803195 | R90: =AVERAGEIF($J$6:$J$297,$O90,M$6:M$297) -> 0.096814315 | S90: =R90-Q90 -> 0.016494815
A91: Փետրվար | E91: 5.8384 | G91: 7.0986 | I91: 39114 | J91: =YEAR(I91)&" q"&ROUNDUP(MONTH(I91)/3,0) -> 2007 q1 | K91: =IFERROR(AVERAGE(B91:E91)/100,"") -> 0.058384 | L91: =IFERROR(AVERAGE(F91:G91)/100,"") -> 0.070986 | M91: =IF(IFERROR(H91/100,"")=0,"",IFERROR(H91/100,"")) | O91: 2021 q2 | P91: =AVERAGEIF($J$6:$J$297,$O91,K$6:K$297) -> 0.070593 | Q91: =AVERAGEIF($J$6:$J$297,$O91,L$6:L$297) -> 0.085431 | R91: =AVERAGEIF($J$6:$J$297,$O91,M$6:M$297) -> 0.098704543 | S91: =R91-Q91 -> 0.013273543
A92: Մարտ | F92: 6.3998 | H92: 7.9896 | I92: 39142 | J92: =YEAR(I92)&" q"&ROUNDUP(MONTH(I92)/3,0) -> 2007 q1 | K92: =IFERROR(AVERAGE(B92:E92)/100,"") | L92: =IFERROR(AVERAGE(F92:G92)/100,"") -> 0.063998 | M92: =IF(IFERROR(H92/100,"")=0,"",IFERROR(H92/100,"")) -> 0.079896 | O92: 2021 q3 | P92: =AVERAGEIF($J$6:$J$297,$O92,K$6:K$297) -> 0.081341329 | Q92: =AVERAGEIF($J$6:$J$297,$O92,L$6:L$297) -> 0.09479 | R92: =AVERAGEIF($J$6:$J$297,$O92,M$6:M$297) -> 0.099131 | S92: =R92-Q92 -> 0.004341
A93: Ապրիլ | F93: 6.457 | G93: 7.1238 | I93: 39173 | J93: =YEAR(I93)&" q"&ROUNDUP(MONTH(I93)/3,0) -> 2007 q2 | K93: =IFERROR(AVERAGE(B93:E93)/100,"") | L93: =IFERROR(AVERAGE(F93:G93)/100,"") -> 0.067904 | M93: =IF(IFERROR(H93/100,"")=0,"",IFERROR(H93/100,"")) | O93: 2021 q4 | P93: =AVERAGEIF($J$6:$J$297,$O93,K$6:K$297) -> 0.086817 | Q93: =AVERAGEIF($J$6:$J$297,$O93,L$6:L$297) -> 0.097094333 | R93: =AVERAGEIF($J$6:$J$297,$O93,M$6:M$297) -> 0.10289875 | S93: =R93-Q93 -> 0.0058044119
A94: Մայիս | D94: 5.9858 | G94: 6.9761 | I94: 39203 | J94: =YEAR(I94)&" q"&ROUNDUP(MONTH(I94)/3,0) -> 2007 q2 | K94: =IFERROR(AVERAGE(B94:E94)/100,"") -> 0.059858 | L94: =IFERROR(AVERAGE(F94:G94)/100,"") -> 0.069761 | M94: =IF(IFERROR(H94/100,"")=0,"",IFERROR(H94/100,"")) | O94: 2022 q1 | P94: =AVERAGEIF($J$6:$J$297,$O94,K$6:K$297) -> 0.092928028 | Q94: =AVERAGEIF($J$6:$J$297,$O94,L$6:L$297) -> 0.1017895 | R94: =AVERAGEIF($J$6:$J$297,$O94,M$6:M$297) -> 0.106031 | S94: =R94-Q94 -> 0.0042415
A95: Հունիս | F95: 5.991 | H95: 6.7366 | I95: 39234 | J95: =YEAR(I95)&" q"&ROUNDUP(MONTH(I95)/3,0) -> 2007 q2 | K95: =IFERROR(AVERAGE(B95:E95)/100,"") | L95: =IFERROR(AVERAGE(F95:G95)/100,"") -> 0.05991 | M95: =IF(IFERROR(H95/100,"")=0,"",IFERROR(H95/100,"")) -> 0.067366 | O95: 2022 q2 | P95: =AVERAGEIF($J$6:$J$297,$O95,K$6:K$297) -> 0.10354001 | Q95: =AVERAGEIF($J$6:$J$297,$O95,L$6:L$297) -> 0.1108865 | R95: =AVERAGEIF($J$6:$J$297,$O95,M$6:M$297) -> 0.11692732 | S95: =R95-Q95 -> 0.0060408215
A96: Հուլիս | E96: 5.7512 | F96: 5.9794 | G96: 6.6579 | I96: 39264 | J96: =YEAR(I96)&" q"&ROUNDUP(MONTH(I96)/3,0) -> 2007 q3 | K96: =IFERROR(AVERAGE(B96:E96)/100,"") -> 0.057512 | L96: =IFERROR(AVERAGE(F96:G96)/100,"") -> 0.0631865 | M96: =IF(IFERROR(H96/100,"")=0,"",IFERROR(H96/100,"")) | O96: 2022 q3 | P96: =AVERAGEIF($J$6:$J$297,$O96,K$6:K$297) -> 0.1065155 | Q96: =AVERAGEIF($J$6:$J$297,$O96,L$6:L$297) -> 0.11275076 | R96: =AVERAGEIF($J$6:$J$297,$O96,M$6:M$297) -> 0.118903 | S96: =R96-Q96 -> 0.0061522356
A97: Օգոստոս | E97: 5.6767 | G97: 6.7213 | I97: 39295 | J97: =YEAR(I97)&" q"&ROUNDUP(MONTH(I97)/3,0) -> 2007 q3 | K97: =IFERROR(AVERAGE(B97:E97)/100,"") -> 0.056767 | L97: =IFERROR(AVERAGE(F97:G97)/100,"") -> 0.067213 | M97: =IF(IFERROR(H97/100,"")=0,"",IFERROR(H97/100,"")) | O97: 2022 q4 | P97: =AVERAGEIF($J$6:$J$297,$O97,K$6:K$297) -> 0.11495819 | Q97: =AVERAGEIF($J$6:$J$297,$O97,L$6:L$297) -> 0.11762 | R97: =AVERAGE(R96,R98) -> 0.119352 | S97: =R97-Q97 -> 0.001732
A98: Սեպտեմբեր | E98: 6.4024 | F98: 6.5248 | H98: 6.7188 | I98: 39326 | J98: =YEAR(I98)&" q"&ROUNDUP(MONTH(I98)/3,0) -> 2007 q3 | K98: =IFERROR(AVERAGE(B98:E98)/100,"") -> 0.064024 | L98: =IFERROR(AVERAGE(F98:G98)/100,"") -> 0.065248 | M98: =IF(IFERROR(H98/100,"")=0,"",IFERROR(H98/100,"")) -> 0.067188 | O98: 2023 q1 | P98: =AVERAGEIF($J$6:$J$297,$O98,K$6:K$297) -> 0.11442347 | Q98: =AVERAGEIF($J$6:$J$297,$O98,L$6:L$297) -> 0.1192995 | R98: =AVERAGEIF($J$6:$J$297,$O98,M$6:M$297) -> 0.119801 | S98: =R98-Q98 -> 0.0005015
A99: Հոկտեմբեր | F99: 6.7567 | G99: 6.8212 | I99: 39356 | J99: =YEAR(I99)&" q"&ROUNDUP(MONTH(I99)/3,0) -> 2007 q4 | K99: =IFERROR(AVERAGE(B99:E99)/100,"") | L99: =IFERROR(AVERAGE(F99:G99)/100,"") -> 0.0678895 | M99: =IF(IFERROR(H99/100,"")=0,"",IFERROR(H99/100,"")) | O99: 2023 q2 | P99: =AVERAGEIF($J$6:$J$297,$O99,K$6:K$297) -> 0.11378157 | Q99: =AVERAGEIF($J$6:$J$297,$O99,L$6:L$297) -> 0.11451893 | R99: =AVERAGEIF($J$6:$J$297,$O99,M$6:M$297) -> 0.11785311 | S99: =R99-Q99 -> 0.0033341847
A100: Նոյեմբեր | E100: 6.5294 | G100: 7.125 | I100: 39387 | J100: =YEAR(I100)&" q"&ROUNDUP(MONTH(I100)/3,0) -> 2007 q4 | K100: =IFERROR(AVERAGE(B100:E100)/100,"") -> 0.065294 | L100: =IFERROR(AVERAGE(F100:G100)/100,"") -> 0.07125 | M100: =IF(IFERROR(H100/100,"")=0,"",IFERROR(H100/100,"")) | O100: 2023 q3 | P100: =AVERAGEIF($J$6:$J$297,$O100,K$6:K$297) -> 0.10584257 | Q100: =AVERAGEIF($J$6:$J$297,$O100,L$6:L$297) -> 0.1064985 | R100: =AVERAGEIF($J$6:$J$297,$O100,M$6:M$297) -> 0.111163 | S100: =R100-Q100 -> 0.0046645
A101: Դեկտեմբեր | F101: 7.5228 | H101: 9.4457 | I101: 39417 | J101: =YEAR(I101)&" q"&ROUNDUP(MONTH(I101)/3,0) -> 2007 q4 | K101: =IFERROR(AVERAGE(B101:E101)/100,"") | L101: =IFERROR(AVERAGE(F101:G101)/100,"") -> 0.075228 | M101: =IF(IFERROR(H101/100,"")=0,"",IFERROR(H101/100,"")) -> 0.094457 | O101: 2023 q4 | P101: =AVERAGEIF($J$6:$J$297,$O101,K$6:K$297) -> 0.10544073 | Q101: =AVERAGEIF($J$6:$J$297,$O101,L$6:L$297) -> 0.10843333 | R101: =AVERAGEIF($J$6:$J$297,$O101,M$6:M$297) -> 0.10855048 | S101: =R101-Q101 -> 0.00011714486
...

Sheet policy tool rates
A1: Ֆինանսական շուկայում ՀՀ ԿԲ գործառնությունների տոկոսադրույքները (%)
A4: Գործողության ժամկետը | B4: Վեռաֆինանսավորման տոկոսադրույք | C4: Ներգրաված միջոցներ | D4: Լոմբարդային ռեպո 1 | E4: Trimmed date | F4: Quarter | G4: Repo rate | J4: Quarter | K4: Average repo rate
A5: 27.12.2003-08.03.2004 | B5: 9 | C5: 5 | D5: 20 | E5: =TRIM(A5) -> 27.12.2003-08.03.2004 | F5: =RIGHT(E5,4)&" q"&ROUNDUP(VALUE(LEFT(RIGHT(E5,7),2))/3,0) -> 2004 q1 | G5: =B5 -> 9 | J5: 2004 q1 | K5: =AVERAGEIF($F$5:$F$145,J5,$G$5:$G$145)/100 -> 0.09 | M5: 2003 q1 | N5: =N6 -> 0.09
A6: 09.03.2004-06.04.2004 | B6: 6 | C6: 3 | D6: 20 | E6: =TRIM(A6) -> 09.03.2004-06.04.2004 | F6: =RIGHT(E6,4)&" q"&ROUNDUP(VALUE(LEFT(RIGHT(E6,7),2))/3,0) -> 2004 q2 | G6: =B6 -> 6 | J6: 2004 q2 | K6: =AVERAGEIF($F$5:$F$145,J6,$G$5:$G$145)/100 -> 0.06 | M6: 2003 q2 | N6: =N7 -> 0.09
A7: 07.04.2004-13.07.2004 | B7: 6 | C7: 1 | D7: 20 | E7: =TRIM(A7) -> 07.04.2004-13.07.2004 | F7: =RIGHT(E7,4)&" q"&ROUNDUP(VALUE(LEFT(RIGHT(E7,7),2))/3,0) -> 2004 q3 | G7: =B7 -> 6 | J7: 2004 q3 | K7: =AVERAGEIF($F$5:$F$145,J7,$G$5:$G$145)/100 -> 0.055 | M7: 2003 q3 | N7: =N8 -> 0.09
A8: 14.07.2004-22.08.2004 | B8: 5 | C8: 1 | D8: 20 | E8: =TRIM(A8) -> 14.07.2004-22.08.2004 | F8: =RIGHT(E8,4)&" q"&ROUNDUP(VALUE(LEFT(RIGHT(E8,7),2))/3,0) -> 2004 q3 | G8: =B8 -> 5 | J8: 2004 q4 | K8: =AVERAGEIF($F$5:$F$145,J8,$G$5:$G$145)/100 -> 0.04 | M8: 2003 q4 | N8: =N9 -> 0.09
A9: 23.08.2004-17.10.2004 | B9: 4 | C9: 1 | D9: 16 | E9: =TRIM(A9) -> 23.08.2004-17.10.2004 | F9: =RIGHT(E9,4)&" q"&ROUNDUP(VALUE(LEFT(RIGHT(E9,7),2))/3,0) -> 2004 q4 | G9: =B9 -> 4 | J9: 2005 q1 | K9: =AVERAGEIF($F$5:$F$145,J9,$G$5:$G$145)/100 -> 0.0375 | M9: 2004 q1 | N9: =VLOOKUP(M9,$J$5:$K$72,2,FALSE) -> 0.09
A10: 18.10.2004-09.01.2005 | B10: 3.75 | C10: 1 | D10: 16 | E10: =TRIM(A10) -> 18.10.2004-09.01.2005 | F10: =RIGHT(E10,4)&" q"&ROUNDUP(VALUE(LEFT(RIGHT(E10,7),2))/3,0) -> 2005 q1 | G10: =B10 -> 3.75 | J10: 2005 q2 | K10: =AVERAGEIF($F$5:$F$145,J10,$G$5:$G$145)/100 -> 0.045 | M10: 2004 q2 | N10: =VLOOKUP(M10,$J$5:$K$72,2,FALSE) -> 0.06
A11: 10.01.2005-13.06.2005 | B11: 4.5 | C11: 1.75 | D11: 16 | E11: =TRIM(A11) -> 10.01.2005-13.06.2005 | F11: =RIGHT(E11,4)&" q"&ROUNDUP(VALUE(LEFT(RIGHT(E11,7),2))/3,0) -> 2005 q2 | G11: =B11 -> 4.5 | J11: 2005 q3 | K11: =AVERAGEIF($F$5:$F$145,J11,$G$5:$G$145)/100 -> 0.0375 | M11: 2004 q3 | N11: =VLOOKUP(M11,$J$5:$K$72,2,FALSE) -> 0.055
A12: 14.06.2005-09.08.2005 | B12: 3.75 | C12: 1.75 | D12: 16 | E12: =TRIM(A12) -> 14.06.2005-09.08.2005 | F12: =RIGHT(E12,4)&" q"&ROUNDUP(VALUE(LEFT(RIGHT(E12,7),2))/3,0) -> 2005 q3 | G12: =B12 -> 3.75 | J12: 2005 q4 | K12: =AVERAGEIF($F$5:$F$145,J12,$G$5:$G$145)/100 -> 0.03 | M12: 2004 q4 | N12: =VLOOKUP(M12,$J$5:$K$72,2,FALSE) -> 0.04
A13: 10.08.2005-25.12.2005 | B13: 3 | C13: 1 | D13: 16 | E13: =TRIM(A13) -> 10.08.2005-25.12.2005 | F13: =RIGHT(E13,4)&" q"&ROUNDUP(VALUE(LEFT(RIGHT(E13,7),2))/3,0) -> 2005 q4 | G13: =B13 -> 3 | J13: 2006 q1 | K13: =AVERAGEIF($F$5:$F$145,J13,$G$5:$G$145)/100 -> 0.0375 | M13: 2005 q1 | N13: =VLOOKUP(M13,$J$5:$K$72,2,FALSE) -> 0.0375
A14: 26.12.2005-05.02.2006 | B14: 3.5 | C14: 1 | D14: 16 | E14: =TRIM(A14) -> 26.12.2005-05.02.2006 | F14: =RIGHT(E14,4)&" q"&ROUNDUP(VALUE(LEFT(RIGHT(E14,7),2))/3,0) -> 2006 q1 | G14: =B14 -> 3.5 | J14: 2006 q2 | K14: =AVERAGEIF($F$5:$F$145,J14,$G$5:$G$145)/100 -> 0.04 | M14: 2005 q2 | N14: =VLOOKUP(M14,$J$5:$K$72,2,FALSE) -> 0.045
A15: 06.02.2006-15.03.2006 | B15: 4 | C15: 1 | D15: 16 | E15: =TRIM(A15) -> 06.02.2006-15.03.2006 | F15: =RIGHT(E15,4)&" q"&ROUNDUP(VALUE(LEFT(RIGHT(E15,7),2))/3,0) -> 2006 q1 | G15: =B15 -> 4 | J15: 2006 q3 | K15: =AVERAGEIF($F$5:$F$145,J15,$G$5:$G$145)/100 -> 0.04125 | M15: 2005 q3 | N15: =VLOOKUP(M15,$J$5:$K$72,2,FALSE) -> 0.0375
A16: 16.03.2006-02.04.2006 | B16: 4 | C16: 1 | D16: 12 | E16: =TRIM(A16) -> 16.03.2006-02.04.2006 | F16: =RIGHT(E16,4)&" q"&ROUNDUP(VALUE(LEFT(RIGHT(E16,7),2))/3,0) -> 2006 q2 | G16: =B16 -> 4 | J16: 2006 q4 | K16: =AVERAGEIF($F$5:$F$145,J16,$G$5:$G$145)/100 -> 0.045 | M16: 2005 q4 | N16: =VLOOKUP(M16,$J$5:$K$72,2,FALSE) -> 0.03
A17: 03.04.2006-03.05.2006 | B17: 4 | C17: 1 | D17: 8 | E17: =TRIM(A17) -> 03.04.2006-03.05.2006 | F17: =RIGHT(E17,4)&" q"&ROUNDUP(VALUE(LEFT(RIGHT(E17,7),2))/3,0) -> 2006 q2 | G17: =B17 -> 4 | J17: 2007 q2 | K17: =AVERAGEIF($F$5:$F$145,J17,$G$5:$G$145)/100 -> 0.0475 | M17: 2006 q1 | N17: =VLOOKUP(M17,$J$5:$K$72,2,FALSE) -> 0.0375
A18: 04.05.2006-31.07.2006 | B18: 4 | C18: 1 | D18: 7 | E18: =TRIM(A18) -> 04.05.2006-31.07.2006 | F18: =RIGHT(E18,4)&" q"&ROUNDUP(VALUE(LEFT(RIGHT(E18,7),2))/3,0) -> 2006 q3 | G18: =B18 -> 4 | J18: 2007 q3 | K18: =AVERAGEIF($F$5:$F$145,J18,$G$5:$G$145)/100 -> 0.045 | M18: 2006 q2 | N18: =VLOOKUP(M18,$J$5:$K$72,2,FALSE) -> 0.04
A19: 01.08.2006-31.08.2006 | B19: 4.25 | C19: 1 | D19: 7 | E19: =TRIM(A19) -> 01.08.2006-31.08.2006 | F19: =RIGHT(E19,4)&" q"&ROUNDUP(VALUE(LEFT(RIGHT(E19,7),2))/3,0) -> 2006 q3 | G19: =B19 -> 4.25 | J19: 2007 q4 | K19: =AVERAGEIF($F$5:$F$145,J19,$G$5:$G$145)/100 -> 0.05 | M19: 2006 q3 | N19: =VLOOKUP(M19,$J$5:$K$72,2,FALSE) -> 0.04125
A20: 01.09.2006-02.10.2006 | B20: 4.5 | C20: 1.5 | D20: 7.5 | E20: =TRIM(A20) -> 01.09.2006-02.10.2006 | F20: =RIGHT(E20,4)&" q"&ROUNDUP(VALUE(LEFT(RIGHT(E20,7),2))/3,0) -> 2006 q4 | G20: =B20 -> 4.5 | J20: 2008 q1 | K20: =AVERAGEIF($F$5:$F$145,J20,$G$5:$G$145)/100 -> 0.05875 | M20: 2006 q4 | N20: =VLOOKUP(M20,$J$5:$K$72,2,FALSE) -> 0.045
A21: 03.10.2006-02.04.2007 | B21: 4.75 | C21: 1.75 | D21: 7.75 | E21: =TRIM(A21) -> 03.10.2006-02.04.2007 | F21: =RIGHT(E21,4)&" q"&ROUNDUP(VALUE(LEFT(RIGHT(E21,7),2))/3,0) -> 2007 q2 | G21: =B21 -> 4.75 | J21: 2008 q2 | K21: =AVERAGEIF($F$5:$F$145,J21,$G$5:$G$145)/100 -> 0.065 | M21: 2007 q1 | N21: =AVERAGE(N20,N22) -> 0.04625
A22: 03.04.2007-02.07.2007 | B22: 4.5 | C22: 1.5 | D22: 7.5 | E22: =TRIM(A22) -> 03.04.2007-02.07.2007 | F22: =RIGHT(E22,4)&" q"&ROUNDUP(VALUE(LEFT(RIGHT(E22,7),2))/3,0) -> 2007 q3 | G22: =B22 -> 4.5 | J22: 2008 q3 | K22: =AVERAGEIF($F$5:$F$145,J22,$G$5:$G$145)/100 -> 0.0725 | M22: 2007 q2 | N22: =VLOOKUP(M22,$J$5:$K$72,2,FALSE) -> 0.0475
A23: 03.07.2007-02.10.2007 | B23: 4.75 | C23: 1.75 | D23: 7.75 | E23: =TRIM(A23) -> 03.07.2007-02.10.2007 | F23: =RIGHT(E23,4)&" q"&ROUNDUP(VALUE(LEFT(RIGHT(E23,7),2))/3,0) -> 2007 q4 | G23: =B23 -> 4.75 | J23: 2008 q4 | K23: =AVERAGEIF($F$5:$F$145,J23,$G$5:$G$145)/100 -> 0.0775 | M23: 2007 q3 | N23: =VLOOKUP(M23,$J$5:$K$72,2,FALSE) -> 0.045
A24: 03.10.2007-04.11.2007 | B24: 5 | C24: 2 | D24: 8 | E24: =TRIM(A24) -> 03.10.2007-04.11.2007 | F24: =RIGHT(E24,4)&" q"&ROUNDUP(VALUE(LEFT(RIGHT(E24,7),2))/3,0) -> 2007 q4 | G24: =B24 -> 5 | J24: 2009 q1 | K24: =AVERAGEIF($F$5:$F$145,J24,$G$5:$G$145)/100 -> 0.07 | M24: 2007 q4 | N24: =VLOOKUP(M24,$J$5:$K$72,2,FALSE) -> 0.05
A25: 05.11.2007-04.12.2007 | B25: 5.25 | C25: 2.25 | D25: 8.25 | E25: =TRIM(A25) -> 05.11.2007-04.12.2007 | F25: =RIGHT(E25,4)&" q"&ROUNDUP(VALUE(LEFT(RIGHT(E25,7),2))/3,0) -> 2007 q4 | G25: =B25 -> 5.25 | J25: 2009 q2 | K25: =AVERAGEIF($F$5:$F$145,J25,$G$5:$G$145)/100 -> 0.071875 | M25: 2008 q1 | N25: =VLOOKUP(M25,$J$5:$K$72,2,FALSE) -> 0.05875
A26: 05.12.2007-04.02.2008 | B26: 5.75 | C26: 2.75 | D26: 8.75 | E26: =TRIM(A26) -> 05.12.2007-04.02.2008 | F26: =RIGHT(E26,4)&" q"&ROUNDUP(VALUE(LEFT(RIGHT(E26,7),2))/3,0) -> 2008 q1 | G26: =B26 -> 5.75 | J26: 2009 q3 | K26: =AVERAGEIF($F$5:$F$145,J26,$G$5:$G$145)/100 -> 0.055833333 | M26: 2008 q2 | N26: =VLOOKUP(M26,$J$5:$K$72,2,FALSE) -> 0.065
A27: 05.02.2008-04.03.2008 | B27: 6 | C27: 3 | D27: 9 | E27: =TRIM(A27) -> 05.02.2008-04.03.2008 | F27: =RIGHT(E27,4)&" q"&ROUNDUP(VALUE(LEFT(RIGHT(E27,7),2))/3,0) -> 2008 q1 | G27: =B27 -> 6 | J27: 2009 q4 | K27: =AVERAGEIF($F$5:$F$145,J27,$G$5:$G$145)/100 -> 0.05 | M27: 2008 q3 | N27: =VLOOKUP(M27,$J$5:$K$72,2,FALSE) -> 0.0725
A28: 04.03.2008-02.04.2008 | B28: 6.25 | C28: 3.25 | D28: 9.25 | E28: =TRIM(A28) -> 04.03.2008-02.04.2008 | F28: =RIGHT(E28,4)&" q"&ROUNDUP(VALUE(LEFT(RIGHT(E28,7),2))/3,0) -> 2008 q2 | G28: =B28 -> 6.25 | J28: 2010 q1 | K28: =AVERAGEIF($F$5:$F$145,J28,$G$5:$G$145)/100 -> 0.0575 | M28: 2008 q4 | N28: =VLOOKUP(M28,$J$5:$K$72,2,FALSE) -> 0.0775
A29: 03.04.2008-05.05.2008 | B29: 6.5 | C29: 3.5 | D29: 9.5 | E29: =TRIM(A29) -> 03.04.2008-05.05.2008 | F29: =RIGHT(E29,4)&" q"&ROUNDUP(VALUE(LEFT(RIGHT(E29,7),2))/3,0) -> 2008 q2 | G29: =B29 -> 6.5 | J29: 2010 q2 | K29: =AVERAGEIF($F$5:$F$145,J29,$G$5:$G$145)/100 -> 0.069166667 | M29: 2009 q1 | N29: =VLOOKUP(M29,$J$5:$K$72,2,FALSE) -> 0.07
A30: 06.05.2008-03.06.2008 | B30: 6.75 | C30: 3.75 | D30: 9.75 | E30: =TRIM(A30) -> 06.05.2008-03.06.2008 | F30: =RIGHT(E30,4)&" q"&ROUNDUP(VALUE(LEFT(RIGHT(E30,7),2))/3,0) -> 2008 q2 | G30: =B30 -> 6.75 | J30: 2010 q3 | K30: =AVERAGEIF($F$5:$F$145,J30,$G$5:$G$145)/100 -> 0.0725 | M30: 2009 q2 | N30: =VLOOKUP(M30,$J$5:$K$72,2,FALSE) -> 0.071875
A31: 04.06.2008-02.07.2008 | B31: 7 | C31: 4 | D31: 10 | E31: =TRIM(A31) -> 04.06.2008-02.07.2008 | F31: =RIGHT(E31,4)&" q"&ROUNDUP(VALUE(LEFT(RIGHT(E31,7),2))/3,0) -> 2008 q3 | G31: =B31 -> 7 | J31: 2010 q4 | K31: =AVERAGEIF($F$5:$F$145,J31,$G$5:$G$145)/100 -> 0.0725 | M31: 2009 q3 | N31: =VLOOKUP(M31,$J$5:$K$72,2,FALSE) -> 0.055833333
A32: 03.07.2008-04.08.2008 | B32: 7.25 | C32: 4.25 | D32: 10.25 | E32: =TRIM(A32) -> 03.07.2008-04.08.2008 | F32: =RIGHT(E32,4)&" q"&ROUNDUP(VALUE(LEFT(RIGHT(E32,7),2))/3,0) -> 2008 q3 | G32: =B32 -> 7.25 | J32: 2011 q1 | K32: =AVERAGEIF($F$5:$F$145,J32,$G$5:$G$145)/100 -> 0.074166667 | M32: 2009 q4 | N32: =VLOOKUP(M32,$J$5:$K$72,2,FALSE) -> 0.05
A33: 05.08.2008-02.09.2008 | B33: 7.5 | C33: 4.5 | D33: 10.5 | E33: =TRIM(A33) -> 05.08.2008-02.09.2008 | F33: =RIGHT(E33,4)&" q"&ROUNDUP(VALUE(LEFT(RIGHT(E33,7),2))/3,0) -> 2008 q3 | G33: =B33 -> 7.5 | J33: 2011 q2 | K33: =AVERAGEIF($F$5:$F$145,J33,$G$5:$G$145)/100 -> 0.084166667 | M33: 2010 q1 | N33: =VLOOKUP(M33,$J$5:$K$72,2,FALSE) -> 0.0575
... A53: 12.05.2010-08.06.2010 | B53: 7.25 | C53: 4.25 | D53: 12.25 | E53: =TRIM(A53) -> 12.05.2010-08.06.2010 | F53: =RIGHT(E53,4)&" q"&ROUNDUP(VALUE(LEFT(RIGHT(E53,7),2))/3,0) -> 2010 q2 | G53: =B53 -> 7.25 | J53: 2016 q3 | K53: =AVERAGEIF($F$5:$F$145,J53,$G$5:$G$145)/100 -> 0.07375 | M53: 2015 q1 | N53: =VLOOKUP(M53,$J$5:$K$72,2,FALSE) -> 0.0975
A54: 09.06.2010-13.07.2010 | B54: 7.25 | C54: 4.25 | D54: 10.25 | E54: =TRIM(A54) -> 09.06.2010-13.07.2010 | F54: =RIGHT(E54,4)&" q"&ROUNDUP(VALUE(LEFT(RIGHT(E54,7),2))/3,0) -> 2010 q3 | G54: =B54 -> 7.25 | J54: 2016 q4 | K54: =AVERAGEIF($F$5:$F$145,J54,$G$5:$G$145)/100 -> 0.06625 | M54: 2015 q2 | N54: =AVERAGE(N53,N55) -> 0.10125
A55: 14.07.2010-10.08.2010 | B55: 7.25 | C55: 4.25 | D55: 10.25 | E55: =TRIM(A55) -> 14.07.2010-10.08.2010 | F55: =RIGHT(E55,4)&" q"&ROUNDUP(VALUE(LEFT(RIGHT(E55,7),2))/3,0) -> 2010 q3 | G55: =B55 -> 7.25 | J55: 2017 q1 | K55: =AVERAGEIF($F$5:$F$145,J55,$G$5:$G$145)/100 -> 0.0625 | M55: 2015 q3 | N55: =VLOOKUP(M55,$J$5:$K$72,2,FALSE) -> 0.105
A56: 11.08.2010-07.09.2010 | B56: 7.25 | C56: 4.25 | D56: 10.25 | E56: =TRIM(A56) -> 11.08.2010-07.09.2010 | F56: =RIGHT(E56,4)&" q"&ROUNDUP(VALUE(LEFT(RIGHT(E56,7),2))/3,0) -> 2010 q3 | G56: =B56 -> 7.25 | J56: 2019 q1 | K56: =AVERAGEIF($F$5:$F$145,J56,$G$5:$G$145)/100 -> 0.06 | M56: 2015 q4 | N56: =VLOOKUP(M56,$J$5:$K$72,2,FALSE) -> 0.1
A57: 08.09.2010-12.10.2010 | B57: 7.25 | C57: 4.25 | D57: 10.25 | E57: =TRIM(A57) -> 08.09.2010-12.10.2010 | F57: =RIGHT(E57,4)&" q"&ROUNDUP(VALUE(LEFT(RIGHT(E57,7),2))/3,0) -> 2010 q4 | G57: =B57 -> 7.25 | J57: 2019 q3 | K57: =AVERAGEIF($F$5:$F$145,J57,$G$5:$G$145)/100 -> 0.0575 | M57: 2016 q1 | N57: =VLOOKUP(M57,$J$5:$K$72,2,FALSE) -> 0.08625
A58: 13.10.2010-09.11.2010 | B58: 7.25 | C58: 4.25 | D58: 10.25 | E58: =TRIM(A58) -> 13.10.2010-09.11.2010 | F58: =RIGHT(E58,4)&" q"&ROUNDUP(VALUE(LEFT(RIGHT(E58,7),2))/3,0) -> 2010 q4 | G58: =B58 -> 7.25 | J58: 2020 q1 | K58: =AVERAGEIF($F$5:$F$145,J58,$G$5:$G$145)/100 -> 0.055 | M58: 2016 q2 | N58: =VLOOKUP(M58,$J$5:$K$72,2,FALSE) -> 0.08
A59: 10.11.2010-07.12.2010 | B59: 7.25 | C59: 4.25 | D59: 10.25 | E59: =TRIM(A59) -> 10.11.2010-07.12.2010 | F59: =RIGHT(E59,4)&" q"&ROUNDUP(VALUE(LEFT(RIGHT(E59,7),2))/3,0) -> 2010 q4 | G59: =B59 -> 7.25 | J59: 2020 q2 | K59: =AVERAGEIF($F$5:$F$145,J59,$G$5:$G$145)/100 -> 0.05125 | M59: 2016 q3 | N59: =VLOOKUP(M59,$J$5:$K$72,2,FALSE) -> 0.07375
A60: 08.12.2010-11.01.2011 | B60: 7.25 | C60: 4.25 | D60: 10.25 | E60: =TRIM(A60) -> 08.12.2010-11.01.2011 | F60: =RIGHT(E60,4)&" q"&ROUNDUP(VALUE(LEFT(RIGHT(E60,7),2))/3,0) -> 2011 q1 | G60: =B60 -> 7.25 | J60: 2020 q3 | K60: =AVERAGEIF($F$5:$F$145,J60,$G$5:$G$145)/100 -> 0.045 | M60: 2016 q4 | N60: =VLOOKUP(M60,$J$5:$K$72,2,FALSE) -> 0.06625
A61: 12.01.2011-08.02.2011 | B61: 7.25 | C61: 4.25 | D61: 10.25 | E61: =TRIM(A61) -> 12.01.2011-08.02.2011 | F61: =RIGHT(E61,4)&" q"&ROUNDUP(VALUE(LEFT(RIGHT(E61,7),2))/3,0) -> 2011 q1 | G61: =B61 -> 7.25 | J61: 2020 q4 | K61: =AVERAGEIF($F$5:$F$145,J61,$G$5:$G$145)/100 -> 0.0425 | M61: 2017 q1 | N61: =VLOOKUP(M61,$J$5:$K$72,2,FALSE) -> 0.0625
A62: 09.02.2011-04.03.2011 | B62: 7.75 | C62: 4.75 | D62: 10.75 | E62: =TRIM(A62) -> 09.02.2011-04.03.2011 | F62: =RIGHT(E62,4)&" q"&ROUNDUP(VALUE(LEFT(RIGHT(E62,7),2))/3,0) -> 2011 q1 | G62: =B62 -> 7.75 | J62: 2021 q1 | K62: =AVERAGEIF($F$5:$F$145,J62,$G$5:$G$145)/100 -> 0.05375 | M62: 2017 q2 | N62: =N61 -> 0.0625
A63: 05.03.2011-12.04.2011 | B63: 8.25 | C63: 5.25 | D63: 11.25 | E63: =TRIM(A63) -> 05.03.2011-12.04.2011 | F63: =RIGHT(E63,4)&" q"&ROUNDUP(VALUE(LEFT(RIGHT(E63,7),2))/3,0) -> 2011 q2 | G63: =B63 -> 8.25 | J63: 2021 q2 | K63: =AVERAGEIF($F$5:$F$145,J63,$G$5:$G$145)/100 -> 0.0575 | M63: 2017 q3 | N63: =N62 -> 0.0625
A64: 13.04.2011-10.05.2011 | B64: 8.5 | C64: 5.5 | D64: 11.5 | E64: =TRIM(A64) -> 13.04.2011-10.05.2011 | F64: =RIGHT(E64,4)&" q"&ROUNDUP(VALUE(LEFT(RIGHT(E64,7),2))/3,0) -> 2011 q2 | G64: =B64 -> 8.5 | J64: 2021 q3 | K64: =AVERAGEIF($F$5:$F$145,J64,$G$5:$G$145)/100 -> 0.0675 | M64: 2017 q4 | N64: =N63 -> 0.0625
A65: 11.05.2011-07.06.2011 | B65: 8.5 | C65: 5.5 | D65: 11.5 | E65: =TRIM(A65) -> 11.05.2011-07.06.2011 | F65: =RIGHT(E65,4)&" q"&ROUNDUP(VALUE(LEFT(RIGHT(E65,7),2))/3,0) -> 2011 q2 | G65: =B65 -> 8.5 | J65: 2021 q4 | K65: =AVERAGEIF($F$5:$F$145,J65,$G$5:$G$145)/100 -> 0.0725 | M65: 2018 q1 | N65: =N64 -> 0.0625
A66: 08.06.2011-12.07.2011 | B66: 8.5 | C66: 5.5 | D66: 11.5 | E66: =TRIM(A66) -> 08.06.2011-12.07.2011 | F66: =RIGHT(E66,4)&" q"&ROUNDUP(VALUE(LEFT(RIGHT(E66,7),2))/3,0) -> 2011 q3 | G66: =B66 -> 8.5 | J66: 2022 q1 | K66: =AVERAGEIF($F$5:$F$145,J66,$G$5:$G$145)/100 -> 0.08 | M66: 2018 q2 | N66: =N65 -> 0.0625
A67: 13.07.2011-09.08.2011 | B67: 8.5 | C67: 5.5 | D67: 11.5 | E67: =TRIM(A67) -> 13.07.2011-09.08.2011 | F67: =RIGHT(E67,4)&" q"&ROUNDUP(VALUE(LEFT(RIGHT(E67,7),2))/3,0) -> 2011 q3 | G67: =B67 -> 8.5 | J67: 2022 q3 | K67: =AVERAGEIF($F$5:$F$145,J67,$G$5:$G$145)/100 -> 0.09375 | M67: 2018 q3 | N67: =N66 -> 0.0625
A68: 10.08.2011-06.09.2011 | B68: 8.5 | C68: 5.5 | D68: 11.5 | E68: =TRIM(A68) -> 10.08.2011-06.09.2011 | F68: =RIGHT(E68,4)&" q"&ROUNDUP(VALUE(LEFT(RIGHT(E68,7),2))/3,0) -> 2011 q3 | G68: =B68 -> 8.5 | J68: 2022 q4 | K68: =AVERAGEIF($F$5:$F$145,J68,$G$5:$G$145)/100 -> 0.1025 | M68: 2018 q4 | N68: =N67 -> 0.0625
A69: 07.09.2011-11.10.2011 | B69: 8 | C69: 5 | D69: 11 | E69: =TRIM(A69) -> 07.09.2011-11.10.2011 | F69: =RIGHT(E69,4)&" q"&ROUNDUP(VALUE(LEFT(RIGHT(E69,7),2))/3,0) -> 2011 q4 | G69: =B69 -> 8 | J69: 2023 q2 | K69: =AVERAGEIF($F$5:$F$145,J69,$G$5:$G$145)/100 -> 0.1075 | M69: 2019 q1 | N69: =VLOOKUP(M69,$J$5:$K$72,2,FALSE) -> 0.06
A70: 12.10.2011-08.11.2011 | B70: 8 | C70: 5 | D70: 11 | E70: =TRIM(A70) -> 12.10.2011-08.11.2011 | F70: =RIGHT(E70,4)&" q"&ROUNDUP(VALUE(LEFT(RIGHT(E70,7),2))/3,0) -> 2011 q4 | G70: =B70 -> 8 | J70: 2023 q3 | K70: =AVERAGEIF($F$5:$F$145,J70,$G$5:$G$145)/100 -> 0.10375 | M70: 2019 q2 | N70: =AVERAGE(N69,N71) -> 0.05875
A71: 09.11.2011-06.12.2011 | B71: 8 | C71: 5 | D71: 11 | E71: =TRIM(A71) -> 09.11.2011-06.12.2011 | F71: =RIGHT(E71,4)&" q"&ROUNDUP(VALUE(LEFT(RIGHT(E71,7),2))/3,0) -> 2011 q4 | G71: =B71 -> 8 | J71: 2023 q4 | K71: =AVERAGEIF($F$5:$F$145,J71,$G$5:$G$145)/100 -> 0.09625 | M71: 2019 q3 | N71: =VLOOKUP(M71,$J$5:$K$72,2,FALSE) -> 0.0575
A72: 07.12.2011-10.01.2012 | B72: 8 | C72: 5 | D72: 11 | E72: =TRIM(A72) -> 07.12.2011-10.01.2012 | F72: =RIGHT(E72,4)&" q"&ROUNDUP(VALUE(LEFT(RIGHT(E72,7),2))/3,0) -> 2012 q1 | G72: =B72 -> 8 | J72: 2024 q1 | K72: =AVERAGEIF($F$5:$F$145,J72,$G$5:$G$145)/100 -> 0.09 | M72: 2019 q4 | N72: =AVERAGE(N71,N73) -> 0.05625
A73: 11.01.2012-07.02.2012 | B73: 8 | C73: 5 | D73: 11 | E73: =TRIM(A73) -> 11.01.2012-07.02.2012 | F73: =RIGHT(E73,4)&" q"&ROUNDUP(VALUE(LEFT(RIGHT(E73,7),2))/3,0) -> 2012 q1 | G73: =B73 -> 8 | M73: 2020 q1 | N73: =VLOOKUP(M73,$J$5:$K$72,2,FALSE) -> 0.055
A74: 08.02.2012-06.03.2012 | B74: 8 | C74: 5 | D74: 11 | E74: =TRIM(A74) -> 08.02.2012-06.03.2012 | F74: =RIGHT(E74,4)&" q"&ROUNDUP(VALUE(LEFT(RIGHT(E74,7),2))/3,0) -> 2012 q1 | G74: =B74 -> 8 | M74: 2020 q2 | N74: =VLOOKUP(M74,$J$5:$K$72,2,FALSE) -> 0.05125
A75: 07.03.2012-10.04.2012 | B75: 8 | C75: 5 | D75: 11 | E75: =TRIM(A75) -> 07.03.2012-10.04.2012 | F75: =RIGHT(E75,4)&" q"&ROUNDUP(VALUE(LEFT(RIGHT(E75,7),2))/3,0) -> 2012 q2 | G75: =B75 -> 8 | M75: 2020 q3 | N75: =VLOOKUP(M75,$J$5:$K$72,2,FALSE) -> 0.045
A76: 11.04.2012-08.05.2012 | B76: 8 | C76: 5 | D76: 11 | E76: =TRIM(A76) -> 11.04.2012-08.05.2012 | F76: =RIGHT(E76,4)&" q"&ROUNDUP(VALUE(LEFT(RIGHT(E76,7),2))/3,0) -> 2012 q2 | G76: =B76 -> 8 | M76: 2020 q4 | N76: =VLOOKUP(M76,$J$5:$K$72,2,FALSE) -> 0.0425
A77: 09.05.2012-05.06.2012 | B77: 8 | C77: 5 | D77: 11 | E77: =TRIM(A77) -> 09.05.2012-05.06.2012 | F77: =RIGHT(E77,4)&" q"&ROUNDUP(VALUE(LEFT(RIGHT(E77,7),2))/3,0) -> 2012 q2 | G77: =B77 -> 8 | M77: 2021 q1 | N77: =VLOOKUP(M77,$J$5:$K$72,2,FALSE) -> 0.05375
A78: 06.06.2012-10.07.2012 | B78: 8 | C78: 5.5 | D78: 10.5 | E78: =TRIM(A78) -> 06.06.2012-10.07.2012 | F78: =RIGHT(E78,4)&" q"&ROUNDUP(VALUE(LEFT(RIGHT(E78,7),2))/3,0) -> 2012 q3 | G78: =B78 -> 8 | M78: 2021 q2 | N78: =VLOOKUP(M78,$J$5:$K$72,2,FALSE) -> 0.0575
A79: 11.07.2012-07.08.2012 | B79: 8 | C79: 5.5 | D79: 10.5 | E79: =TRIM(A79) -> 11.07.2012-07.08.2012 | F79: =RIGHT(E79,4)&" q"&ROUNDUP(VALUE(LEFT(RIGHT(E79,7),2))/3,0) -> 2012 q3 | G79: =B79 -> 8 | M79: 2021 q3 | N79: =VLOOKUP(M79,$J$5:$K$72,2,FALSE) -> 0.0675
A80: 08.08.2012-04.09.2012 | B80: 8 | C80: 5.5 | D80: 10.5 | E80: =TRIM(A80) -> 08.08.2012-04.09.2012 | F80: =RIGHT(E80,4)&" q"&ROUNDUP(VALUE(LEFT(RIGHT(E80,7),2))/3,0) -> 2012 q3 | G80: =B80 -> 8 | M80: 2021 q4 | N80: =VLOOKUP(M80,$J$5:$K$72,2,FALSE) -> 0.0725
A81: 05.09.2012-09.10.2012 | B81: 8 | C81: 6 | D81: 10 | E81: =TRIM(A81) -> 05.09.2012-09.10.2012 | F81: =RIGHT(E81,4)&" q"&ROUNDUP(VALUE(LEFT(RIGHT(E81,7),2))/3,0) -> 2012 q4 | G81: =B81 -> 8 | M81: 2022 q1 | N81: =VLOOKUP(M81,$J$5:$K$72,2,FALSE) -> 0.08
A82: 10.10.2012-06.11.2012 | B82: 8 | C82: 6 | D82: 10 | E82: =TRIM(A82) -> 10.10.2012-06.11.2012 | F82: =RIGHT(E82,4)&" q"&ROUNDUP(VALUE(LEFT(RIGHT(E82,7),2))/3,0) -> 2012 q4 | G82: =B82 -> 8 | M82: 2022 q2 | N82: =AVERAGE(N81,N83) -> 0.086875
A83: 07.11.2012-11.12.2012 | B83: 8 | C83: 6.5 | D83: 9.5 | E83: =TRIM(A83) -> 07.11.2012-11.12.2012 | F83: =RIGHT(E83,4)&" q"&ROUNDUP(VALUE(LEFT(RIGHT(E83,7),2))/3,0) -> 2012 q4 | G83: =B83 -> 8 | M83: 2022 q3 | N83: =VLOOKUP(M83,$J$5:$K$72,2,FALSE) -> 0.09375
A84: 12.12.2012-12.02.2013 | B84: 8 | C84: 6.5 | D84: 9.5 | E84: =TRIM(A84) -> 12.12.2012-12.02.2013 | F84: =RIGHT(E84,4)&" q"&ROUNDUP(VALUE(LEFT(RIGHT(E84,7),2))/3,0) -> 2013 q1 | G84: =B84 -> 8 | M84: 2022 q4 | N84: =VLOOKUP(M84,$J$5:$K$72,2,FALSE) -> 0.1025
A85: 13.02.2013-26.03.2013 | B85: 8 | C85: 6.5 | D85: 9.5 | E85: =TRIM(A85) -> 13.02.2013-26.03.2013 | F85: =RIGHT(E85,4)&" q"&ROUNDUP(VALUE(LEFT(RIGHT(E85,7),2))/3,0) -> 2013 q1 | G85: =B85 -> 8 | M85: 2023 q1 | N85: =AVERAGE(N84,N86) -> 0.105
A86: 27.03.2013-14.05.2013 | B86: 8 | C86: 6.5 | D86: 9.5 | E86: =TRIM(A86) -> 27.03.2013-14.05.2013 | F86: =RIGHT(E86,4)&" q"&ROUNDUP(VALUE(LEFT(RIGHT(E86,7),2))/3,0) -> 2013 q2 | G86: =B86 -> 8 | M86: 2023 q2 | N86: =VLOOKUP(M86,$J$5:$K$72,2,FALSE) -> 0.1075
A87: 15.05.2013-25.06.2013 | B87: 8 | C87: 6.5 | D87: 9.5 | E87: =TRIM(A87) -> 15.05.2013-25.06.2013 | F87: =RIGHT(E87,4)&" q"&ROUNDUP(VALUE(LEFT(RIGHT(E87,7),2))/3,0) -> 2013 q2 | G87: =B87 -> 8 | M87: 2023 q3 | N87: =VLOOKUP(M87,$J$5:$K$72,2,FALSE) -> 0.10375
A88: 26.06.2013-13.08.2013 | B88: 8 | C88: 6.5 | D88: 9.5 | E88: =TRIM(A88) -> 26.06.2013-13.08.2013 | F88: =RIGHT(E88,4)&" q"&ROUNDUP(VALUE(LEFT(RIGHT(E88,7),2))/3,0) -> 2013 q3 | G88: =B88 -> 8 | M88: 2023 q4 | N88: =VLOOKUP(M88,$J$5:$K$72,2,FALSE) -> 0.09625
A89: 14.08.2013-24.09.2013 | B89: 8.5 | C89: 7 | D89: 10 | E89: =TRIM(A89) -> 14.08.2013-24.09.2013 | F89: =RIGHT(E89,4)&" q"&ROUNDUP(VALUE(LEFT(RIGHT(E89,7),2))/3,0) -> 2013 q3 | G89: =B89 -> 8.5 | M89: 2024 q1 | N89: =VLOOKUP(M89,$J$5:$K$72,2,FALSE) -> 0.09
A90: 25.09.2013-12.11.2013 | B90: 8.5 | C90: 7 | D90: 10 | E90: =TRIM(A90) -> 25.09.2013-12.11.2013 | F90: =RIGHT(E90,4)&" q"&ROUNDUP(VALUE(LEFT(RIGHT(E90,7),2))/3,0) -> 2013 q4 | G90: =B90 -> 8.5
A91: 13.11.2013-24.12.2013 | B91: 8 | C91: 6.5 | D91: 9.5 | E91: =TRIM(A91) -> 13.11.2013-24.12.2013 | F91: =RIGHT(E91,4)&" q"&ROUNDUP(VALUE(LEFT(RIGHT(E91,7),2))/3,0) -> 2013 q4 | G91: =B91 -> 8
A92: 25.12.2013-11.02.2014 | B92: 7.75 | C92: 6.25 | D92: 9.25 | E92: =TRIM(A92) -> 25.12.2013-11.02.2014 | F92: =RIGHT(E92,4)&" q"&ROUNDUP(VALUE(LEFT(RIGHT(E92,7),2))/3,0) -> 2014 q1 | G92: =B92 -> 7.75
A93: 12.02.2014-24.03.2014 | B93: 7.5 | C93: 6 | D93: 9 | E93: =TRIM(A93) -> 12.02.2014-24.03.2014 | F93: =RIGHT(E93,4)&" q"&ROUNDUP(VALUE(LEFT(RIGHT(E93,7),2))/3,0) -> 2014 q1 | G93: =B93 -> 7.5
A94: 25.03.2014-13.05.2014 | B94: 7.5 | C94: 6 | D94: 9 | E94: =TRIM(A94) -> 25.03.2014-13.05.2014 | F94: =RIGHT(E94,4)&" q"&ROUNDUP(VALUE(LEFT(RIGHT(E94,7),2))/3,0) -> 2014 q2 | G94: =B94 -> 7.5
A95: 14.05.2014-24.06.2014 | B95: 7.25 | C95: 5.75 | D95: 8.75 | E95: =TRIM(A95) -> 14.05.2014-24.06.2014 | F95: =RIGHT(E95,4)&" q"&ROUNDUP(VALUE(LEFT(RIGHT(E95,7),2))/3,0) -> 2014 q2 | G95: =B95 -> 7.25
A96: 25.06.2014-12.08.2014 | B96: 7 | C96: 5.5 | D96: 8.5 | E96: =TRIM(A96) -> 25.06.2014-12.08.2014 | F96: =RIGHT(E96,4)&" q"&ROUNDUP(VALUE(LEFT(RIGHT(E96,7),2))/3,0) -> 2014 q3 | G96: =B96 -> 7
A97: 13.08.2014-23.09.2014 | B97: 6.75 | C97: 5.25 | D97: 8.25 | E97: =TRIM(A97) -> 13.08.2014-23.09.2014 | F97: =RIGHT(E97,4)&" q"&ROUNDUP(VALUE(LEFT(RIGHT(E97,7),2))/3,0) -> 2014 q3 | G97: =B97 -> 6.75
A98: 24.09.2014-24.11.2014 | B98: 6.75 | C98: 5.25 | D98: 8.25 | E98: =TRIM(A98) -> 24.09.2014-24.11.2014 | F98: =RIGHT(E98,4)&" q"&ROUNDUP(VALUE(LEFT(RIGHT(E98,7),2))/3,0) -> 2014 q4 | G98: =B98 -> 6.75
A99: 25.11.2014-02.12.2014 | B99: 6.75 | C99: 5.25 | D99: 10.25 | E99: =TRIM(A99) -> 25.11.2014-02.12.2014 | F99: =RIGHT(E99,4)&" q"&ROUNDUP(VALUE(LEFT(RIGHT(E99,7),2))/3,0) -> 2014 q4 | G99: =B99 -> 6.75
A100: 03.12.2014-23.12.2014 | B100: 6.75 | C100: 5.25 | D100: 21 | E100: =TRIM(A100) -> 03.12.2014-23.12.2014 | F100: =RIGHT(E100,4)&" q"&ROUNDUP(VALUE(LEFT(RIGHT(E100,7),2))/3,0) -> 2014 q4 | G100: =B100 -> 6.75
A101: 24.12.2014-21.01.2015 | B101: 8.5 | C101: 7 | D101: 20 | E101: =TRIM(A101) -> 24.12.2014-21.01.2015 | F101: =RIGHT(E101,4)&" q"&ROUNDUP(VALUE(LEFT(RIGHT(E101,7),2))/3,0) -> 2015 q1 | G101: =B101 -> 8.5
... A145: 01.05.2024- | B145: 8.25 | C145: 6.75 | D145: 9.75 | E145: =TRIM(A145) -> 01.05.2024- | F145: =RIGHT(E145,4)&" q"&ROUNDUP(VALUE(LEFT(RIGHT(E145,7),2))/3,0) -> 024- q2 | G145: =B145 -> 8.25
A148: 1 ØÇÝã¨ 2010Ã. ÷»ïñí³ñÁ ³Ûë ·áñÍ³éÝáõÃÛáõÝÁ Ïáãí»É ¿ ÉáÙµ³ñ¹³ÛÇÝ í³ñÏ:

Sheet Mortgage rate
D2: Report 1
B4: Ամսաթիվ | C4: Տոկոսադրույք*Գումար դրամով | D4: Գումար դրամով | E4: Q
B5: 39593 | C5: 29018198 | D5: 1485516.6 | E5: =YEAR(B5)&" q"&ROUNDUP(MONTH(B5)/3,0) -> 2008 q2 | I5: 2008 q2 | J5: =(SUMIF($E$5:$E$817,I5,C$5:C$817)/SUMIF($E$5:$E$817,I5,D$5:D$817))/100 -> 0.19534078 | M5: 2003 q1 | N5: =VLOOKUP(M5,$I$5:$J$69,2,FALSE) -> #N/A
B6: 39642 | C6: 20810539 | D6: 1353332.8 | E6: =YEAR(B6)&" q"&ROUNDUP(MONTH(B6)/3,0) -> 2008 q3 | I6: 2008 q3 | J6: =(SUMIF($E$5:$E$817,I6,C$5:C$817)/SUMIF($E$5:$E$817,I6,D$5:D$817))/100 -> 0.14502906 | M6: 2003 q2
B7: 39649 | C7: 26591154 | D7: 1755416.5 | E7: =YEAR(B7)&" q"&ROUNDUP(MONTH(B7)/3,0) -> 2008 q3 | I7: 2008 q4 | J7: =(SUMIF($E$5:$E$817,I7,C$5:C$817)/SUMIF($E$5:$E$817,I7,D$5:D$817))/100 -> 0.14221443 | M7: 2003 q3
B8: 39656 | C8: 27722239 | D8: 1743731.2 | E8: =YEAR(B8)&" q"&ROUNDUP(MONTH(B8)/3,0) -> 2008 q3 | I8: 2009 q1 | J8: =(SUMIF($E$5:$E$817,I8,C$5:C$817)/SUMIF($E$5:$E$817,I8,D$5:D$817))/100 -> 0.16803473 | M8: 2003 q4
B9: 39663 | C9: 21097825 | D9: 1399476.1 | E9: =YEAR(B9)&" q"&ROUNDUP(MONTH(B9)/3,0) -> 2008 q3 | I9: 2009 q2 | J9: =(SUMIF($E$5:$E$817,I9,C$5:C$817)/SUMIF($E$5:$E$817,I9,D$5:D$817))/100 -> 0.16278515 | M9: 2004 q1
B10: 39670 | C10: 17815389 | D10: 1234620.5 | E10: =YEAR(B10)&" q"&ROUNDUP(MONTH(B10)/3,0) -> 2008 q3 | I10: 2009 q3 | J10: =(SUMIF($E$5:$E$817,I10,C$5:C$817)/SUMIF($E$5:$E$817,I10,D$5:D$817))/100 -> 0.15403407 | M10: 2004 q2
B11: 39677 | C11: 15514395 | D11: 1107808 | E11: =YEAR(B11)&" q"&ROUNDUP(MONTH(B11)/3,0) -> 2008 q3 | I11: 2009 q4 | J11: =(SUMIF($E$5:$E$817,I11,C$5:C$817)/SUMIF($E$5:$E$817,I11,D$5:D$817))/100 -> 0.14499949 | M11: 2004 q3
B12: 39684 | C12: 7192171.3 | D12: 520034.67 | E12: =YEAR(B12)&" q"&ROUNDUP(MONTH(B12)/3,0) -> 2008 q3 | I12: 2010 q1 | J12: =(SUMIF($E$5:$E$817,I12,C$5:C$817)/SUMIF($E$5:$E$817,I12,D$5:D$817))/100 -> 0.14000675 | M12: 2004 q4
B13: 39691 | C13: 11376783 | D13: 868893.41 | E13: =YEAR(B13)&" q"&ROUNDUP(MONTH(B13)/3,0) -> 2008 q3 | I13: 2010 q2 | J13: =(SUMIF($E$5:$E$817,I13,C$5:C$817)/SUMIF($E$5:$E$817,I13,D$5:D$817))/100 -> 0.13882834 | M13: 2005 q1
B14: 39698 | C14: 12285054 | D14: 955416.08 | E14: =YEAR(B14)&" q"&ROUNDUP(MONTH(B14)/3,0) -> 2008 q3 | I14: 2010 q3 | J14: =(SUMIF($E$5:$E$817,I14,C$5:C$817)/SUMIF($E$5:$E$817,I14,D$5:D$817))/100 -> 0.13754829 | M14: 2005 q2
B15: 39705 | C15: 21024185 | D15: 1496785.9 | E15: =YEAR(B15)&" q"&ROUNDUP(MONTH(B15)/3,0) -> 2008 q3 | I15: 2010 q4 | J15: =(SUMIF($E$5:$E$817,I15,C$5:C$817)/SUMIF($E$5:$E$817,I15,D$5:D$817))/100 -> 0.12821951 | M15: 2005 q3
B16: 39712 | C16: 7528208 | D16: 553788.96 | E16: =YEAR(B16)&" q"&ROUNDUP(MONTH(B16)/3,0) -> 2008 q3 | I16: 2011 q1 | J16: =(SUMIF($E$5:$E$817,I16,C$5:C$817)/SUMIF($E$5:$E$817,I16,D$5:D$817))/100 -> 0.12678789 | M16: 2005 q4
B17: 39719 | C17: 7390462.5 | D17: 549251.57 | E17: =YEAR(B17)&" q"&ROUNDUP(MONTH(B17)/3,0) -> 2008 q3 | I17: 2011 q2 | J17: =(SUMIF($E$5:$E$817,I17,C$5:C$817)/SUMIF($E$5:$E$817,I17,D$5:D$817))/100 -> 0.12478769 | M17: 2006 q1
... B69: 40083 | C69: 4930457 | D69: 328187.76 | E69: =YEAR(B69)&" q"&ROUNDUP(MONTH(B69)/3,0) -> 2009 q3 | I69: 2024 q2 | J69: =(SUMIF($E$5:$E$817,I69,C$5:C$817)/SUMIF($E$5:$E$817,I69,D$5:D$817))/100 -> 0.12535502 | M69: 2019 q1
B70: 40090 | C70: 11452727 | D70: 775476.1 | E70: =YEAR(B70)&" q"&ROUNDUP(MONTH(B70)/3,0) -> 2009 q4 | M70: 2019 q2
B71: 40097 | C71: 6401719 | D71: 439298.78 | E71: =YEAR(B71)&" q"&ROUNDUP(MONTH(B71)/3,0) -> 2009 q4 | M71: 2019 q3
B72: 40104 | C72: 7993726.6 | D72: 526999.05 | E72: =YEAR(B72)&" q"&ROUNDUP(MONTH(B72)/3,0) -> 2009 q4 | M72: 2019 q4
B73: 40111 | C73: 4618099 | D73: 311659.11 | E73: =YEAR(B73)&" q"&ROUNDUP(MONTH(B73)/3,0) -> 2009 q4 | M73: 2020 q1
B74: 40118 | C74: 7615742.6 | D74: 551857.46 | E74: =YEAR(B74)&" q"&ROUNDUP(MONTH(B74)/3,0) -> 2009 q4 | M74: 2020 q2
B75: 40125 | C75: 7354099.8 | D75: 496330.66 | E75: =YEAR(B75)&" q"&ROUNDUP(MONTH(B75)/3,0) -> 2009 q4 | M75: 2020 q3
B76: 40132 | C76: 9326040.4 | D76: 676531.1 | E76: =YEAR(B76)&" q"&ROUNDUP(MONTH(B76)/3,0) -> 2009 q4 | M76: 2020 q4
B77: 40139 | C77: 9182652.1 | D77: 636010.55 | E77: =YEAR(B77)&" q"&ROUNDUP(MONTH(B77)/3,0) -> 2009 q4 | M77: 2021 q1
B78: 40146 | C78: 6220403.3 | D78: 480144.54 | E78: =YEAR(B78)&" q"&ROUNDUP(MONTH(B78)/3,0) -> 2009 q4 | M78: 2021 q2
B79: 40153 | C79: 12638278 | D79: 853783.36 | E79: =YEAR(B79)&" q"&ROUNDUP(MONTH(B79)/3,0) -> 2009 q4 | M79: 2021 q3
B80: 40160 | C80: 6097407.2 | D80: 420771.85 | E80: =YEAR(B80)&" q"&ROUNDUP(MONTH(B80)/3,0) -> 2009 q4 | M80: 2021 q4
B81: 40167 | C81: 9065881.2 | D81: 592929.89 | E81: =YEAR(B81)&" q"&ROUNDUP(MONTH(B81)/3,0) -> 2009 q4 | M81: 2022 q1
... B90: 40237 | C90: 6271682.7 | D90: 460353.83 | E90: =YEAR(B90)&" q"&ROUNDUP(MONTH(B90)/3,0) -> 2010 q1 | M90: 2024 q2
B91: 40244 | C91: 7467570 | D91: 527330.39 | E91: =YEAR(B91)&" q"&ROUNDUP(MONTH(B91)/3,0) -> 2010 q1
B92: 40251 | C92: 7226799.1 | D92: 533733.84 | E92: =YEAR(B92)&" q"&ROUNDUP(MONTH(B92)/3,0) -> 2010 q1
B93: 40258 | C93: 10329354 | D93: 733076.3 | E93: =YEAR(B93)&" q"&ROUNDUP(MONTH(B93)/3,0) -> 2010 q1
B94: 40265 | C94: 7653092.4 | D94: 526291.46 | E94: =YEAR(B94)&" q"&ROUNDUP(MONTH(B94)/3,0) -> 2010 q1
B95: 40272 | C95: 8930943.3 | D95: 616032.86 | E95: =YEAR(B95)&" q"&ROUNDUP(MONTH(B95)/3,0) -> 2010 q2
B96: 40279 | C96: 8300169 | D96: 601528.68 | E96: =YEAR(B96)&" q"&ROUNDUP(MONTH(B96)/3,0) -> 2010 q2
B97: 40286 | C97: 7002372.2 | D97: 523927.85 | E97: =YEAR(B97)&" q"&ROUNDUP(MONTH(B97)/3,0) -> 2010 q2
B98: 40293 | C98: 7050944.7 | D98: 505968.62 | E98: =YEAR(B98)&" q"&ROUNDUP(MONTH(B98)/3,0) -> 2010 q2
B99: 40300 | C99: 12452991 | D99: 912080.94 | E99: =YEAR(B99)&" q"&ROUNDUP(MONTH(B99)/3,0) -> 2010 q2
B100: 40307 | C100: 4444851.2 | D100: 332055.78 | E100: =YEAR(B100)&" q"&ROUNDUP(MONTH(B100)/3,0) -> 2010 q2
B101: 40314 | C101: 5733059.8 | D101: 395728.2 | E101: =YEAR(B101)&" q"&ROUNDUP(MONTH(B101)/3,0) -> 2010 q2
B102: 40321 | C102: 7826955.7 | D102: 536777.71 | E102: =YEAR(B102)&" q"&ROUNDUP(MONTH(B102)/3,0) -> 2010 q2
... B817: 45424 | C817: 59860001 | D817: 4735642.4 | E817: =YEAR(B817)&" q"&ROUNDUP(MONTH(B817)/3,0) -> 2024 q2

Sheet Construction loans
B1: FROM ADICS | G1: FROM MAIN INDICATORS
B2: Ամսաթիվ | C2: 02.03.01.01.04~Շինարարության ոլորտում դրամով ռեզիդենտներին տրված վարկեր, ավանդներ, ֆակտորինգ, լիզինգ ռեպո | D2: 02.03.02.01.04~Շինարարության ոլորտում արտարժութով ռեզիդենտներին տրված վարկեր, ավանդներ, ֆակտորինգ, լիզինգ ռեպո | E2: Construction loans | G2: Ամսաթիվ | H2: 02.03.01.01.03~Շինարարության ոլորտում դրամով ռեզիդենտներին տրված վարկեր, ավանդներ, ֆակտորինգ, լիզինգ ռեպո | I2: 02.03.02.01.03~Շինարարության ոլորտում արտարժութով ռեզիդենտներին տրված վարկեր, ավանդներ, ֆակտորինգ, լիզինգ ռեպո | J2: Main indicators | K2: Adics | L2: Final
B3: 42766 | C3: 13417730 | D3: 97211788 | E3: =SUM(C3:D3) -> 1.1062952e+08 | F3: =YEAR(G3)&" q"&ROUNDUP(MONTH(G3)/3,0) -> 2003 q1 | G3: 37652 | H3: 843584 | I3: 2599559 | J3: 3443143 | L3: =J3 -> 3443143 | O3: 2003 q1 | P3: =AVERAGEIF($F$3:$F$257,O3,$L$3:$L$257) -> 3442836.7
B4: 42794 | C4: 13941118 | D4: 95872115 | E4: =SUM(C4:D4) -> 1.0981323e+08 | F4: =YEAR(G4)&" q"&ROUNDUP(MONTH(G4)/3,0) -> 2003 q1 | G4: 37680 | H4: 953818 | I4: 2378925 | J4: 3332743 | L4: =J4 -> 3332743 | O4: 2003 q2 | P4: =AVERAGEIF($F$3:$F$257,O4,$L$3:$L$257) -> 3781467.7
B5: 42825 | C5: 12933657 | D5: 1.0062267e+08 | E5: =SUM(C5:D5) -> 1.1355633e+08 | F5: =YEAR(G5)&" q"&ROUNDUP(MONTH(G5)/3,0) -> 2003 q1 | G5: 37711 | H5: 1054493 | I5: 2498131 | J5: 3552624 | L5: =J5 -> 3552624 | O5: 2003 q3 | P5: =AVERAGEIF($F$3:$F$257,O5,$L$3:$L$257) -> 4388627.7
B6: 42855 | C6: 15037911 | D6: 1.0181145e+08 | E6: =SUM(C6:D6) -> 1.1684936e+08 | F6: =YEAR(G6)&" q"&ROUNDUP(MONTH(G6)/3,0) -> 2003 q2 | G6: 37741 | H6: 1260510 | I6: 2188019 | J6: 3448529 | L6: =J6 -> 3448529 | O6: 2003 q4 | P6: =AVERAGEIF($F$3:$F$257,O6,$L$3:$L$257) -> 4986759.3
B7: 42886 | C7: 15566135 | D7: 1.0212653e+08 | E7: =SUM(C7:D7) -> 1.1769267e+08 | F7: =YEAR(G7)&" q"&ROUNDUP(MONTH(G7)/3,0) -> 2003 q2 | G7: 37772 | H7: 1348965 | I7: 2791624 | J7: 4140589 | L7: =J7 -> 4140589 | O7: 2004 q1 | P7: =AVERAGEIF($F$3:$F$257,O7,$L$3:$L$257) -> 5024665
B8: 42916 | C8: 20490639 | D8: 1.0340034e+08 | E8: =SUM(C8:D8) -> 1.2389098e+08 | F8: =YEAR(G8)&" q"&ROUNDUP(MONTH(G8)/3,0) -> 2003 q2 | G8: 37802 | H8: 1128800 | I8: 2626485 | J8: 3755285 | L8: =J8 -> 3755285 | O8: 2004 q2 | P8: =AVERAGEIF($F$3:$F$257,O8,$L$3:$L$257) -> 5275383.1
B9: 42947 | C9: 20274905 | D9: 1.0501386e+08 | E9: =SUM(C9:D9) -> 1.2528876e+08 | F9: =YEAR(G9)&" q"&ROUNDUP(MONTH(G9)/3,0) -> 2003 q3 | G9: 37833 | H9: 1603251 | I9: 2193199 | J9: 3796450 | L9: =J9 -> 3796450 | O9: 2004 q3 | P9: =AVERAGEIF($F$3:$F$257,O9,$L$3:$L$257) -> 5653119.8
B10: 42978 | C10: 21059647 | D10: 97612620 | E10: =SUM(C10:D10) -> 1.1867227e+08 | F10: =YEAR(G10)&" q"&ROUNDUP(MONTH(G10)/3,0) -> 2003 q3 | G10: 37864 | H10: 1950653 | I10: 2451067 | J10: 4401720 | L10: =J10 -> 4401720 | O10: 2004 q4 | P10: =AVERAGEIF($F$3:$F$257,O10,$L$3:$L$257) -> 5419070.3
B11: 43008 | C11: 20963910 | D11: 1.1040468e+08 | E11: =SUM(C11:D11) -> 1.3136859e+08 | F11: =YEAR(G11)&" q"&ROUNDUP(MONTH(G11)/3,0) -> 2003 q3 | G11: 37894 | H11: 2073265 | I11: 2894448 | J11: 4967713 | L11: =J11 -> 4967713 | O11: 2005 q1 | P11: =AVERAGEIF($F$3:$F$257,O11,$L$3:$L$257) -> 5559564.6
B12: 43039 | C12: 22943809 | D12: 1.1363209e+08 | E12: =SUM(C12:D12) -> 1.365759e+08 | F12: =YEAR(G12)&" q"&ROUNDUP(MONTH(G12)/3,0) -> 2003 q4 | G12: 37925 | H12: 2278264 | I12: 2820861 | J12: 5099125 | L12: =J12 -> 5099125 | O12: 2005 q2 | P12: =AVERAGEIF($F$3:$F$257,O12,$L$3:$L$257) -> 6289087.3
B13: 43069 | C13: 25128908 | D13: 1.1553262e+08 | E13: =SUM(C13:D13) -> 1.4066153e+08 | F13: =YEAR(G13)&" q"&ROUNDUP(MONTH(G13)/3,0) -> 2003 q4 | G13: 37955 | H13: 2404609 | I13: 2651094 | J13: 5055703 | L13: =J13 -> 5055703 | O13: 2005 q3 | P13: =AVERAGEIF($F$3:$F$257,O13,$L$3:$L$257) -> 7141805.4
B14: 43100 | C14: 26755772 | D14: 1.22009e+08 | E14: =SUM(C14:D14) -> 1.4876478e+08 | F14: =YEAR(G14)&" q"&ROUNDUP(MONTH(G14)/3,0) -> 2003 q4 | G14: 37986 | H14: 2115391 | I14: 2690059 | J14: 4805450 | L14: =J14 -> 4805450 | O14: 2005 q4 | P14: =AVERAGEIF($F$3:$F$257,O14,$L$3:$L$257) -> 7744711.1
... B87: 45322 | C87: 2.2882194e+08 | D87: 2.8734662e+08 | E87: =SUM(C87:D87) -> 5.1616856e+08 | F87: =YEAR(G87)&" q"&ROUNDUP(MONTH(G87)/3,0) -> 2010 q1 | G87: 40209 | H87: 16686393 | I87: 35923538 | J87: 52609931 | L87: =J87 -> 52609931 | O87: 2024 q1 | P87: =AVERAGEIF($F$3:$F$257,O87,$L$3:$L$257) -> 5.2872528e+08
B88: 45351 | C88: 2.3246884e+08 | D88: 2.9613266e+08 | E88: =SUM(C88:D88) -> 5.286015e+08 | F88: =YEAR(G88)&" q"&ROUNDUP(MONTH(G88)/3,0) -> 2010 q1 | G88: 40237 | H88: 16661683 | I88: 37211145 | J88: 53872828 | L88: =J88 -> 53872828
B89: 45382 | C89: 2.43995e+08 | D89: 2.9741078e+08 | E89: =SUM(C89:D89) -> 5.4140578e+08 | F89: =YEAR(G89)&" q"&ROUNDUP(MONTH(G89)/3,0) -> 2010 q1 | G89: 40268 | H89: 17747300 | I89: 39733897 | J89: 57481197 | L89: =J89 -> 57481197
B90: 45412 | C90: 2.3296332e+08 | D90: 2.8667074e+08 | E90: =SUM(C90:D90) -> 5.1963406e+08 | F90: =YEAR(G90)&" q"&ROUNDUP(MONTH(G90)/3,0) -> 2010 q2 | G90: 40298 | H90: 17802918 | I90: 41749846 | J90: 59552765 | L90: =J90 -> 59552765
F91: =YEAR(G91)&" q"&ROUNDUP(MONTH(G91)/3,0) -> 2010 q2 | G91: 40329 | H91: 17592727 | I91: 41786986 | J91: 59379713 | L91: =J91 -> 59379713
F92: =YEAR(G92)&" q"&ROUNDUP(MONTH(G92)/3,0) -> 2010 q2 | G92: 40359 | H92: 17996055 | I92: 40779074 | J92: 58775129 | L92: =J92 -> 58775129
F93: =YEAR(G93)&" q"&ROUNDUP(MONTH(G93)/3,0) -> 2010 q3 | G93: 40390 | H93: 18616634 | I93: 44682269 | J93: 63298903 | L93: =J93 -> 63298903
F94: =YEAR(G94)&" q"&ROUNDUP(MONTH(G94)/3,0) -> 2010 q3 | G94: 40421 | H94: 17243352 | I94: 42056140 | J94: 59299493 | L94: =J94 -> 59299493
F95: =YEAR(G95)&" q"&ROUNDUP(MONTH(G95)/3,0) -> 2010 q3 | G95: 40451 | H95: 19162758 | I95: 46119226 | J95: 65281984 | L95: =J95 -> 65281984
F96: =YEAR(G96)&" q"&ROUNDUP(MONTH(G96)/3,0) -> 2010 q4 | G96: 40482 | H96: 18067346 | I96: 49893008 | J96: 67960354 | L96: =J96 -> 67960354
F97: =YEAR(G97)&" q"&ROUNDUP(MONTH(G97)/3,0) -> 2010 q4 | G97: 40512 | H97: 18410241 | I97: 52404125 | J97: 70814366 | L97: =J97 -> 70814366
F98: =YEAR(G98)&" q"&ROUNDUP(MONTH(G98)/3,0) -> 2010 q4 | G98: 40543 | H98: 18276820 | I98: 56517893 | J98: 74794712 | L98: =J98 -> 74794712
F99: =YEAR(G99)&" q"&ROUNDUP(MONTH(G99)/3,0) -> 2011 q1 | G99: 40574 | H99: 18764888 | I99: 55211609 | J99: 73976497 | L99: =J99 -> 73976497
F100: =YEAR(G100)&" q"&ROUNDUP(MONTH(G100)/3,0) -> 2011 q1 | G100: 40602 | H100: 19352490 | I100: 57274099 | J100: 76626590 | L100: =J100 -> 76626590
F101: =YEAR(G101)&" q"&ROUNDUP(MONTH(G101)/3,0) -> 2011 q1 | G101: 40633 | H101: 18829862 | I101: 59930301 | J101: 78760163 | L101: =J101 -> 78760163
F102: =YEAR(G102)&" q"&ROUNDUP(MONTH(G102)/3,0) -> 2011 q2 | G102: 40663 | H102: 19427783 | I102: 61955545 | J102: 81383328 | L102: =J102 -> 81383328
... F170: =YEAR(G170)&" q"&ROUNDUP(MONTH(G170)/3,0) -> 2016 q4 | G170: 42735 | H170: 13759868 | I170: 89053073 | J170: 102812941 | L170: =J170 -> 102812941
F171: =YEAR(G171)&" q"&ROUNDUP(MONTH(G171)/3,0) -> 2017 q1 | G171: 42766 | H171: 12977854 | I171: 87896068 | J171: 100873922 | K171: =E3 -> 1.1062952e+08 | L171: =K171 -> 1.1062952e+08
F172: =YEAR(G172)&" q"&ROUNDUP(MONTH(G172)/3,0) -> 2017 q1 | G172: 42794 | H172: 13452404 | I172: 87750861 | J172: 101203265 | K172: =E4 -> 1.0981323e+08 | L172: =K172 -> 1.0981323e+08
F173: =YEAR(G173)&" q"&ROUNDUP(MONTH(G173)/3,0) -> 2017 q1 | G173: 42825 | H173: 12462838 | I173: 95816103 | J173: 108278941 | K173: =E5 -> 1.1355633e+08 | L173: =K173 -> 1.1355633e+08
F174: =YEAR(G174)&" q"&ROUNDUP(MONTH(G174)/3,0) -> 2017 q2 | G174: 42855 | H174: 14531790 | I174: 96866592 | J174: 111398382 | K174: =E6 -> 1.1684936e+08 | L174: =K174 -> 1.1684936e+08
F175: =YEAR(G175)&" q"&ROUNDUP(MONTH(G175)/3,0) -> 2017 q2 | G175: 42886 | H175: 15015470 | I175: 97458524 | J175: 112473994 | K175: =E7 -> 1.1769267e+08 | L175: =K175 -> 1.1769267e+08
F176: =YEAR(G176)&" q"&ROUNDUP(MONTH(G176)/3,0) -> 2017 q2 | G176: 42916 | H176: 19932491 | I176: 98786051 | J176: 118718542 | K176: =E8 -> 1.2389098e+08 | L176: =K176 -> 1.2389098e+08
F177: =YEAR(G177)&" q"&ROUNDUP(MONTH(G177)/3,0) -> 2017 q3 | G177: 42947 | H177: 19654982 | I177: 100112795 | J177: 119767777 | K177: =E9 -> 1.2528876e+08 | L177: =K177 -> 1.2528876e+08
F178: =YEAR(G178)&" q"&ROUNDUP(MONTH(G178)/3,0) -> 2017 q3 | G178: 42978 | H178: 20391964 | I178: 92565425 | J178: 112957389 | K178: =E10 -> 1.1867227e+08 | L178: =K178 -> 1.1867227e+08
F179: =YEAR(G179)&" q"&ROUNDUP(MONTH(G179)/3,0) -> 2017 q3 | G179: 43008 | H179: 21174708 | I179: 104372150 | J179: 125546858 | K179: =E11 -> 1.3136859e+08 | L179: =K179 -> 1.3136859e+08
F180: =YEAR(G180)&" q"&ROUNDUP(MONTH(G180)/3,0) -> 2017 q4 | G180: 43039 | H180: 22337577 | I180: 108243961 | J180: 130581538 | K180: =E12 -> 1.365759e+08 | L180: =K180 -> 1.365759e+08
F181: =YEAR(G181)&" q"&ROUNDUP(MONTH(G181)/3,0) -> 2017 q4 | G181: 43069 | H181: 24500857 | I181: 109973958 | J181: 134474815 | K181: =E13 -> 1.4066153e+08 | L181: =K181 -> 1.4066153e+08
F182: =YEAR(G182)&" q"&ROUNDUP(MONTH(G182)/3,0) -> 2017 q4 | G182: 43100 | H182: 26120388 | I182: 117657499 | J182: 143777887 | K182: =E14 -> 1.4876478e+08 | L182: =K182 -> 1.4876478e+08
... F245: =YEAR(G245)&" q"&ROUNDUP(MONTH(G245)/3,0) -> 2023 q1 | G245: 45016 | H245: 1.5242031e+08 | I245: 2.1787354e+08 | J245: 3.7029385e+08 | K245: =E77 -> 3.8410658e+08 | L245: =K245 -> 3.8410658e+08
F246: =YEAR(G246)&" q"&ROUNDUP(MONTH(G246)/3,0) -> 2023 q2 | G246: 45046 | H246: 15641671 | I246: 25570576 | K246: =E78 -> 3.9165284e+08 | L246: =K246 -> 3.9165284e+08
F247: =YEAR(G247)&" q"&ROUNDUP(MONTH(G247)/3,0) -> 2023 q2 | G247: 45077 | H247: 1.6473267e+08 | I247: 2.309714e+08 | K247: =E79 -> 4.0962916e+08 | L247: =K247 -> 4.0962916e+08
F248: =YEAR(G248)&" q"&ROUNDUP(MONTH(G248)/3,0) -> 2023 q2 | G248: 45107 | H248: 3.4603252e+08 | I248: 2.7390086e+08 | K248: =E80 -> 4.1285087e+08 | L248: =K248 -> 4.1285087e+08
F249: =YEAR(G249)&" q"&ROUNDUP(MONTH(G249)/3,0) -> 2023 q3 | G249: 45138 | H249: 545354.96 | I249: 1410499.8 | K249: =E81 -> 4.3624643e+08 | L249: =K249 -> 4.3624643e+08
F250: =YEAR(G250)&" q"&ROUNDUP(MONTH(G250)/3,0) -> 2023 q3 | G250: 45169 | H250: 535754.87 | I250: 1815524.5 | K250: =E82 -> 4.4775789e+08 | L250: =K250 -> 4.4775789e+08
F251: =YEAR(G251)&" q"&ROUNDUP(MONTH(G251)/3,0) -> 2023 q3 | G251: 45199 | H251: 633049.86 | I251: 2057215.7 | K251: =E83 -> 4.5460142e+08 | L251: =K251 -> 4.5460142e+08
F252: =YEAR(G252)&" q"&ROUNDUP(MONTH(G252)/3,0) -> 2023 q4 | G252: 45230 | H252: 589066.59 | I252: 2153170.6 | K252: =E84 -> 4.7972587e+08 | L252: =K252 -> 4.7972587e+08
F253: =YEAR(G253)&" q"&ROUNDUP(MONTH(G253)/3,0) -> 2023 q4 | G253: 45260 | K253: =E85 -> 4.9452966e+08 | L253: =K253 -> 4.9452966e+08
F254: =YEAR(G254)&" q"&ROUNDUP(MONTH(G254)/3,0) -> 2023 q4 | G254: 45291 | K254: =E86 -> 5.0921936e+08 | L254: =K254 -> 5.0921936e+08
F255: =YEAR(G255)&" q"&ROUNDUP(MONTH(G255)/3,0) -> 2024 q1 | G255: 45322 | K255: =E87 -> 5.1616856e+08 | L255: =K255 -> 5.1616856e+08
F256: =YEAR(G256)&" q"&ROUNDUP(MONTH(G256)/3,0) -> 2024 q1 | G256: 45351 | K256: =E88 -> 5.286015e+08 | L256: =K256 -> 5.286015e+08
F257: =YEAR(G257)&" q"&ROUNDUP(MONTH(G257)/3,0) -> 2024 q1 | G257: 45382 | K257: =E89 -> 5.4140578e+08 | L257: =K257 -> 5.4140578e+08

Sheet Copper prices
A1: Macrotrends Data Download
A3: Copper Prices - 45 Year Historical Chart
A5: DISCLAIMER AND TERMS OF USE: HISTORICAL DATA IS PROVIDED "AS IS" AND SOLELY
A6: FOR INFORMATIONAL PURPOSES - NOT FOR TRADING PURPOSES OR ADVICE. | C6: US dollar per pound
A7: NEITHER MACROTRENDS LLC NOR ANY OF OUR INFORMATION PROVIDERS WILL BE LIABLE
A8: FOR ANY DAMAGES RELATING TO YOUR USE OF THE DATA PROVIDED.
A12: ATTRIBUTION: Proper attribution requires clear indication of the data source as "www.macrotrends.net".
A13: A "dofollow" backlink to the originating page is also required if the data is displayed on a web page.
A16: date | B16: value
A17: 21733 | B17: 0.293 | C17: =YEAR(A17)&" q"&ROUNDUP(MONTH(A17)/3,0) -> 1959 q3 | F17: 1959 q3 | G17: =AVERAGEIF($C$17:$C$16300,F17,$B$17:$B$16300) -> 0.2970381
A18: 21737 | B18: 0.291 | C18: =YEAR(A18)&" q"&ROUNDUP(MONTH(A18)/3,0) -> 1959 q3 | F18: 1959 q4 | G18: =AVERAGEIF($C$17:$C$16300,F18,$B$17:$B$16300) -> 0.32466129
A19: 21738 | B19: 0.282 | C19: =YEAR(A19)&" q"&ROUNDUP(MONTH(A19)/3,0) -> 1959 q3 | F19: 1960 q1 | G19: =AVERAGEIF($C$17:$C$16300,F19,$B$17:$B$16300) -> 0.3100381
A20: 21739 | B20: 0.2846 | C20: =YEAR(A20)&" q"&ROUNDUP(MONTH(A20)/3,0) -> 1959 q3 | F20: 1960 q2 | G20: =AVERAGEIF($C$17:$C$16300,F20,$B$17:$B$16300) -> 0.30282698
A21: 21740 | B21: 0.276 | C21: =YEAR(A21)&" q"&ROUNDUP(MONTH(A21)/3,0) -> 1959 q3 | F21: 1960 q3 | G21: =AVERAGEIF($C$17:$C$16300,F21,$B$17:$B$16300) -> 0.30003125
A22: 21741 | B22: 0.2757 | C22: =YEAR(A22)&" q"&ROUNDUP(MONTH(A22)/3,0) -> 1959 q3 | F22: 1960 q4 | G22: =AVERAGEIF($C$17:$C$16300,F22,$B$17:$B$16300) -> 0.28014194
A23: 21744 | B23: 0.278 | C23: =YEAR(A23)&" q"&ROUNDUP(MONTH(A23)/3,0) -> 1959 q3 | F23: 1961 q1 | G23: =AVERAGEIF($C$17:$C$16300,F23,$B$17:$B$16300) -> 0.28037903
A24: 21745 | B24: 0.2855 | C24: =YEAR(A24)&" q"&ROUNDUP(MONTH(A24)/3,0) -> 1959 q3 | F24: 1961 q2 | G24: =AVERAGEIF($C$17:$C$16300,F24,$B$17:$B$16300) -> 0.30632698
A25: 21746 | B25: 0.2873 | C25: =YEAR(A25)&" q"&ROUNDUP(MONTH(A25)/3,0) -> 1959 q3 | F25: 1961 q3 | G25: =AVERAGEIF($C$17:$C$16300,F25,$B$17:$B$16300) -> 0.30653968
A26: 21747 | B26: 0.2915 | C26: =YEAR(A26)&" q"&ROUNDUP(MONTH(A26)/3,0) -> 1959 q3 | F26: 1961 q4 | G26: =AVERAGEIF($C$17:$C$16300,F26,$B$17:$B$16300) -> 0.29893226
A27: 21748 | B27: 0.2916 | C27: =YEAR(A27)&" q"&ROUNDUP(MONTH(A27)/3,0) -> 1959 q3 | F27: 1962 q1 | G27: =AVERAGEIF($C$17:$C$16300,F27,$B$17:$B$16300) -> 0.30388871
A28: 21751 | B28: 0.2893 | C28: =YEAR(A28)&" q"&ROUNDUP(MONTH(A28)/3,0) -> 1959 q3 | F28: 1962 q2 | G28: =AVERAGEIF($C$17:$C$16300,F28,$B$17:$B$16300) -> 0.29350635
... A276: 22111 | B276: 0.3086 | C276: =YEAR(A276)&" q"&ROUNDUP(MONTH(A276)/3,0) -> 1960 q3 | F276: 2024 q2 | G276: =AVERAGEIF($C$17:$C$16300,F276,$B$17:$B$16300) -> 4.5032
A277: 22112 | B277: 0.3055 | C277: =YEAR(A277)&" q"&ROUNDUP(MONTH(A277)/3,0) -> 1960 q3
A278: 22115 | B278: 0.3076 | C278: =YEAR(A278)&" q"&ROUNDUP(MONTH(A278)/3,0) -> 1960 q3
A279: 22116 | B279: 0.3058 | C279: =YEAR(A279)&" q"&ROUNDUP(MONTH(A279)/3,0) -> 1960 q3
A280: 22117 | B280: 0.3096 | C280: =YEAR(A280)&" q"&ROUNDUP(MONTH(A280)/3,0) -> 1960 q3
A281: 22118 | B281: 0.309 | C281: =YEAR(A281)&" q"&ROUNDUP(MONTH(A281)/3,0) -> 1960 q3
A282: 22119 | B282: 0.3074 | C282: =YEAR(A282)&" q"&ROUNDUP(MONTH(A282)/3,0) -> 1960 q3
A283: 22122 | B283: 0.3068 | C283: =YEAR(A283)&" q"&ROUNDUP(MONTH(A283)/3,0) -> 1960 q3
A284: 22123 | B284: 0.308 | C284: =YEAR(A284)&" q"&ROUNDUP(MONTH(A284)/3,0) -> 1960 q3
A285: 22124 | B285: 0.3088 | C285: =YEAR(A285)&" q"&ROUNDUP(MONTH(A285)/3,0) -> 1960 q3
A286: 22125 | B286: 0.3071 | C286: =YEAR(A286)&" q"&ROUNDUP(MONTH(A286)/3,0) -> 1960 q3
A287: 22126 | B287: 0.3072 | C287: =YEAR(A287)&" q"&ROUNDUP(MONTH(A287)/3,0) -> 1960 q3
A288: 22129 | B288: 0.3084 | C288: =YEAR(A288)&" q"&ROUNDUP(MONTH(A288)/3,0) -> 1960 q3
... A16279: 45432 | B16279: 5.1056 | C16279: =YEAR(A16279)&" q"&ROUNDUP(MONTH(A16279)/3,0) -> 2024 q2
A16280: 45433 | C16280: =YEAR(A16280)&" q"&ROUNDUP(MONTH(A16280)/3,0) -> 2024 q2
A16281: 45434 | C16281: =YEAR(A16281)&" q"&ROUNDUP(MONTH(A16281)/3,0) -> 2024 q2
A16282: 45435 | C16282: =YEAR(A16282)&" q"&ROUNDUP(MONTH(A16282)/3,0) -> 2024 q2
A16283: 45436 | C16283: =YEAR(A16283)&" q"&ROUNDUP(MONTH(A16283)/3,0) -> 2024 q2
A16284: 45437 | C16284: =YEAR(A16284)&" q"&ROUNDUP(MONTH(A16284)/3,0) -> 2024 q2
A16285: 45438 | C16285: =YEAR(A16285)&" q"&ROUNDUP(MONTH(A16285)/3,0) -> 2024 q2
A16286: 45439 | C16286: =YEAR(A16286)&" q"&ROUNDUP(MONTH(A16286)/3,0) -> 2024 q2
A16287: 45440 | C16287: =YEAR(A16287)&" q"&ROUNDUP(MONTH(A16287)/3,0) -> 2024 q2
A16288: 45441 | C16288: =YEAR(A16288)&" q"&ROUNDUP(MONTH(A16288)/3,0) -> 2024 q2
A16289: 45442 | C16289: =YEAR(A16289)&" q"&ROUNDUP(MONTH(A16289)/3,0) -> 2024 q2
A16290: 45443 | C16290: =YEAR(A16290)&" q"&ROUNDUP(MONTH(A16290)/3,0) -> 2024 q2
A16291: 45444 | C16291: =YEAR(A16291)&" q"&ROUNDUP(MONTH(A16291)/3,0) -> 2024 q2
... A16300: 45453 | C16300: =YEAR(A16300)&" q"&ROUNDUP(MONTH(A16300)/3,0) -> 2024 q2
